Workbook

Sheet Cover
B2: Helix Support Partners
B3: FY2026 operating plan & monthly P&L forecast (Jan-Dec 2026) - Business Finance case study
B4: Currency: mln IRT (Toman) unless stated; unit economics in IRT. Prepared by: Nima
B6: MODEL MAP
B7: Dashboard | C7: Headline KPIs and charts
B8: Assumptions | C8: Every driver, Given vs Assumed, with rationale (task: "state every ratio you assume")
B9: Topline_ExC | C9: Exhibit C completed: calls handled, rate card, other fees, revenue (task 1 input)
B10: Capacity_ExD | C10: Exhibit D: volume -> workload hours -> productive hours/FTE -> agent FTE -> hiring flow -> support roles -> seats (tasks 1-2)
B11: Erlang_Check | C11: Erlang C validation of the 78% voice occupancy against the 80/20 service level
B12: Costs | C12: Full cost stack: people, recruitment & attrition, technology & telephony, facilities, management, corporate overhead (task 3)
B13: PnL_ExE | C13: Exhibit E: monthly P&L revenue -> net profit with GM, EBITDA, EBITDA margin per month and FY (task 4)
B14: UnitEcon | C14: Revenue, cost and contribution per call vs per ticket; which line is more profitable and why (task 5)
B15: CostProgram_ExF | C15: Exhibit F: 8 cost initiatives ranked by net 12-month EBITDA impact; 90-day flags
B16: ZBB_Register | C16: Zero-based justification of every cost line: driver, minimum level, decision, owner
B17: Sensitivity | C17: One-at-a-time flex of key drivers (tornado data)
B19: CONVENTIONS
B20: Blue text | C20: Hard-coded input
B21: Black text | C21: Formula
B22: Green text | C22: Link to another sheet
B23: Yellow fill | C23: Key assumption / most sensitive input
B24: Costs in P&L | C24: Shown as negatives; FY column = sum (ratios recomputed on FY totals)
B26: NOTES ON THE CASE
B27: Exhibit labels | C27: Task text refers to "topline in Exhibit A" and "P&L structure in Exhibit D"; the case pages label these Exhibit C and E. Model follows the page labels.
B28: Rate card | C28: Blank in Exhibit C - assumed 32,000 IRT/call and 17,000 IRT/ticket (same ~425 IRT per handle-second). Flex in Assumptions row p_c / p_t.
B29: Currency | C29: Exhibit B quotes salaries in mln IRT; the "$60 allowance" note is treated as already embedded in the 50 mln IRT blended salary.
B30: Staffing risk | C30: Lever vol_real (Assumptions F) flexes billable volume while staffing stays on plan.

Sheet Dashboard
A1: Helix Support Partners - FY26 operating plan: dashboard
A2: All figures link to the model (mln IRT unless stated).
B4: FY26 KPI | C4: Value
B5: Revenue | C5: =PnL_ExE!$O$9 -> 204064.08
B6: Gross profit | C6: =PnL_ExE!$O$19 -> 81882.654
B7: Gross margin | C7: =PnL_ExE!$O$20 -> 0.40125952
B8: EBITDA | C8: =PnL_ExE!$O$35 -> 26561.855
B9: EBITDA margin | C9: =PnL_ExE!$O$36 -> 0.13016428
B10: Net profit | C10: =PnL_ExE!$O$42 -> 17785.447
B11: Net margin | C11: =PnL_ExE!$O$43 -> 0.087156184
B12: Avg agent HC | C12: =PnL_ExE!$O$49 -> 109.57883
B13: Avg total HC | C13: =PnL_ExE!$O$50 -> 135.16216
B14: Calls handled | C14: =PnL_ExE!$O$46 -> 4653400
B15: Tickets handled | C15: =PnL_ExE!$O$47 -> 3210000
B16: EBITDA per call (IRT) | C16: =UnitEcon!$O$23 -> 2996.2117
B17: EBITDA per ticket (IRT) | C17: =UnitEcon!$O$38 -> 3748.9106
B18: Voice EBITDA margin | C18: =UnitEcon!$O$24 -> 0.093631615
B19: Ticket EBITDA margin | C19: =UnitEcon!$O$39 -> 0.22052415
B20: Cost program - net 12m EBITDA | C20: =CostProgram_ExF!$M$16 -> 14409.52
B25: Chart data
B26: Month | C26: Jan-26 | D26: Feb-26 | E26: Mar-26 | F26: Apr-26 | G26: May-26 | H26: Jun-26 | I26: Jul-26 | J26: Aug-26 | K26: Sep-26 | L26: Oct-26 | M26: Nov-26 | N26: Dec-26
B27: Revenue | C27: =PnL_ExE!C9 -> 13502.8 | D27: =PnL_ExE!D9 -> 14803.312 | E27: =PnL_ExE!E9 -> 11840.8 | F27: =PnL_ExE!F9 -> 12808 | G27: =PnL_ExE!G9 -> 13605.2 | H27: =PnL_ExE!H9 -> 15029.6 | I27: =PnL_ExE!I9 -> 16794 | J27: =PnL_ExE!J9 -> 17591.2 | ... N27: =PnL_ExE!N9 -> 22140
B28: EBITDA | C28: =PnL_ExE!C35 -> 3226.1711 | D28: =PnL_ExE!D35 -> 3187.1184 | E28: =PnL_ExE!E35 -> 1101.7066 | F28: =PnL_ExE!F35 -> 81.838129 | G28: =PnL_ExE!G35 -> 830.85007 | H28: =PnL_ExE!H35 -> 950.75603 | I28: =PnL_ExE!I35 -> 1440.1246 | J28: =PnL_ExE!J35 -> 2028.5719 | ... N28: =PnL_ExE!N35 -> 3807.0277
B29: EBITDA margin | C29: =PnL_ExE!C36 -> 0.23892608 | D29: =PnL_ExE!D36 -> 0.21529765 | E29: =PnL_ExE!E36 -> 0.093043258 | F29: =PnL_ExE!F36 -> 0.0063896103 | G29: =PnL_ExE!G36 -> 0.061068567 | H29: =PnL_ExE!H36 -> 0.063258904 | I29: =PnL_ExE!I36 -> 0.085752325 | J29: =PnL_ExE!J36 -> 0.11531742 | ... N29: =PnL_ExE!N36 -> 0.17195247
B30: Agent HC | C30: =PnL_ExE!C49 -> 85.687461 | D30: =PnL_ExE!D49 -> 95.033824 | E30: =PnL_ExE!E49 -> 91.232471 | F30: =PnL_ExE!F49 -> 87.583172 | G30: =PnL_ExE!G49 -> 86.360399 | H30: =PnL_ExE!H49 -> 95.575913 | I30: =PnL_ExE!I49 -> 106.73547 | J30: =PnL_ExE!J49 -> 111.82924 | ... N30: =PnL_ExE!N49 -> 141.98098
B31: Agent FTE required | C31: =PnL_ExE!C48 -> 85.687461 | D31: =PnL_ExE!D48 -> 95.033824 | E31: =PnL_ExE!E48 -> 75.200841 | F31: =PnL_ExE!F48 -> 81.266631 | G31: =PnL_ExE!G48 -> 86.360399 | H31: =PnL_ExE!H48 -> 95.575913 | I31: =PnL_ExE!I48 -> 106.73547 | J31: =PnL_ExE!J48 -> 111.82924 | ... N31: =PnL_ExE!N48 -> 139.98049

Sheet Assumptions
A1: Assumptions register
A2: Every driver in one place. Blue = hard-coded input; yellow fill = key assumption (most sensitive). Source column states Given (case) vs Assumed (mine).
A4: ID | B4: Parameter | C4: Value | D4: Unit | E4: Source | F4: Rationale
A5: A. OPERATING DRIVERS - GIVEN (Exhibit A, 2025 actuals)
A6: aht_c | B6: Average handling time - call | C6: 75 | D6: seconds | E6: Given | F6: Talk + hold + after-call work per answered call
A7: aht_t | B7: Average handling time - ticket | C7: 40 | D7: seconds | E7: Given | F7: Per ticket resolved incl. re-reads and internal notes
A8: sl_tgt | B8: Service level target - voice (% answered) | C8: 0.8 | D8: % | E8: Given | F8: 80% answered within threshold below; used in Erlang C cross-check
A9: sl_sec | B9: Service level threshold - voice | C9: 20 | D9: seconds | E9: Given | F9: 80/20 contractual; breach triggers service credits
A10: occ_c | B10: Occupancy - voice | C10: 0.78 | D10: % | E10: Given | F10: Measured 2025 actual; embeds real-time queueing (Erlang) slack. Validated in Erlang sheet
A11: shr | B11: Shrinkage | C11: 0.3 | D11: % | E11: Given | F11: Paid but unavailable: breaks, leave, sickness, training, coaching, meetings
A12: paid | B12: Paid hours per agent per month | C12: 176 | D12: hours | E12: Given | F12: 22 working days x 8 hours
A13: sp_tl | B13: Span of control - team leader | C13: 15 | D13: agents / TL | E13: Given
A14: sp_om | B14: Span of control - operations manager | C14: 6 | D14: TLs / OM | E14: Given
A15: sp_qa | B15: Quality analysts | C15: 40 | D15: agents / QA | E15: Given | F15: Manual scoring, 2% sample
A16: n_sd | B16: Site director | C16: 1 | D16: FTE | E16: Given | F16: Fixed
A17: n_fh | B17: Finance / HR business partner | C17: 1 | D17: FTE | E17: Given | F17: Fixed
A18: tax | B18: Corporate tax rate | C18: 0.22 | D18: % | E18: Given | F18: Applied to profit before tax; monthly accrual, FY = sum
A19: B. OPERATING DRIVERS - ASSUMED (not in case; stated per instructions)
A20: occ_t | B20: Occupancy - tickets | C20: 0.9 | D20: % | E20: Assumed | F20: Tickets are asynchronous (95% < 4h): worked from a backlog, so no Erlang queueing slack; 10% kept for system latency / fatigue
A21: ot | B21: Share of productive hours covered by overtime | C21: 0.03 | D21: % | E21: Given (Ex. B) | F21: OT hours = 3% x workload hours; agent FTE sized on remaining 97%
A22: attr | B22: Agent attrition (monthly) | C22: 0.04 | D22: % of HC / month | E22: Assumed | F22: ~40% annualised - typical for high-volume contact centres
A23: nh_tr | B23: New-hire training (paid, non-productive) | C23: 0.5 | D23: months / hire | E23: Assumed | F23: 2 weeks classroom + nesting before an agent counts as productive capacity
A24: sp_wfm | B24: Workforce management analysts | C24: 75 | D24: agents / WFM | E24: Assumed | F24: Forecasting, scheduling, real-time adherence (industry 1:50-1:100)
A25: sp_trn | B25: Trainers | C25: 60 | D25: agents / trainer | E25: Assumed | F25: New-hire + refresher training; driven by 40% attrition
A26: sp_it | B26: IT / MIS support | C26: 75 | D26: agents / IT FTE | E26: Assumed | F26: Desktop, telephony and reporting support
A27: sp_hr | B27: HR, recruitment & admin | C27: 75 | D27: agents / FTE | E27: Assumed | F27: High hiring load (attrition + growth)
A28: n_am | B28: Client / account managers | C28: 2 | D28: FTE | E28: Assumed | F28: Fixed; own client QBRs, volume re-baselining and SLA reporting
A29: seat_r | B29: Agents per seat | C29: 1.5 | D29: agents / seat | E29: Assumed | F29: 16h x 7d operation - two shifts share a workstation; support staff 1 seat each
A30: seat_b | B30: Seat buffer on lease | C30: 0.1 | D30: % | E30: Assumed | F30: Lease sized to FY peak seats + buffer, signed for the full year (fixed cost)
A31: op_h | B31: Voice operating hours per day | C31: 16 | D31: hours | E31: Assumed | F31: 08:00-24:00, 7 days; used in Erlang C cross-check
A32: sched | B32: Schedule inefficiency allowance | C32: 0.05 | D32: % | E32: Assumed | F32: Shift granularity: rostered hours exceed pure Erlang need
A33: C. COST DRIVERS - GIVEN (Exhibit B) - gross monthly salary, mln IRT
A34: s_ag | B34: Agent - gross monthly salary | C34: 50 | D34: mln IRT / month | E34: Given | F34: Blended across shifts incl. shift & performance allowance
A35: s_tl | B35: Team leader | C35: 100 | D35: mln IRT / month | E35: Given
A36: s_qa | B36: Quality analyst | C36: 40 | D36: mln IRT / month | E36: Given
A37: s_om | B37: Operations manager | C37: 150 | D37: mln IRT / month | E37: Given
A38: s_sd | B38: Site director | C38: 200 | D38: mln IRT / month | E38: Given
A39: s_fh | B39: Finance / HR business partner | C39: 150 | D39: mln IRT / month | E39: Given
A40: oncost | B40: Employer on-costs | C40: 0.22 | D40: % of gross | E40: Given | F40: Social security, insurance, statutory benefits - all roles incl. overtime pay
A41: infl | B41: Annual wage inflation | C41: 0.25 | D41: % | E41: Given | F41: Effective 1 April 2026 - all salary lines and overtime rate
A42: infl_m | B42: Wage inflation effective month # | C42: 4 | D42: month # (Apr = 4) | E42: Given
A43: ot_rate | B43: Overtime cost per hour | C43: 0.5 | D43: mln IRT / hour | E43: Given | F43: Gross; on-costs and April inflation applied on top
A44: D. COST DRIVERS - ASSUMED
A45: s_wfm | B45: WFM analyst - gross monthly salary | C45: 70 | D45: mln IRT / month | E45: Assumed | F45: Specialist analytical role, between QA and TL
A46: s_trn | B46: Trainer - gross monthly salary | C46: 60 | D46: mln IRT / month | E46: Assumed | F46: Senior-agent grade + premium
A47: s_it | B47: IT / MIS support - gross monthly salary | C47: 80 | D47: mln IRT / month | E47: Assumed | F47: Tech talent premium
A48: s_hr | B48: HR / recruitment / admin - gross monthly salary | C48: 45 | D48: mln IRT / month | E48: Assumed
A49: s_am | B49: Account manager - gross monthly salary | C49: 120 | D49: mln IRT / month | E49: Assumed | F49: Client-facing, OM-adjacent grade
A50: rec | B50: Recruitment cost per hire | C50: 6 | D50: mln IRT / hire | E50: Assumed | F50: Job boards, assessment, background check, onboarding kit
A51: lic | B51: Contact-centre platform licences | C51: 2.5 | D51: mln IRT / agent / month | E51: Assumed | F51: ACD/CTI, CRM & ticketing, call recording, WFM/QA tools (named-agent)
A52: itfix | B52: IT infrastructure (fixed) | C52: 150 | D52: mln IRT / month | E52: Assumed | F52: Servers/cloud, data links, security, back-up
A53: tel_c | B53: Telephony - per handled call | C53: 400 | D53: IRT / call | E53: Assumed | F53: Inbound trunk minutes incl. queue time (~1.3 min/call)
A54: tel_f | B54: Telephony - fixed (numbers, SIP trunks) | C54: 50 | D54: mln IRT / month | E54: Assumed
A55: msg_t | B55: Messaging / e-mail platform - per ticket | C55: 100 | D55: IRT / ticket | E55: Assumed | F55: SMS / e-mail / in-app gateway fees
A56: lease | B56: Facility lease per seat | C56: 8 | D56: mln IRT / seat / month | E56: Assumed | F56: ~6 sqm/seat incl. common area in Tehran office space; fixed for 12-month lease
A57: util | B57: Utilities, cleaning, security per occupied seat | C57: 2 | D57: mln IRT / seat / month | E57: Assumed | F57: Variable with seats in use
A58: np_infl | B58: Non-payroll cost indexation | C58: 0.15 | D58: % | E58: Assumed | F58: Supplier price reset at the new Iranian year (from April); lease excluded (fixed contract)
A59: capex | B59: Capex per seat (PC, headset, fit-out) | C59: 80 | D59: mln IRT / seat | E59: Assumed | F59: Depreciated straight-line
A60: dep | B60: Depreciation life | C60: 36 | D60: months | E60: Assumed
A61: corp | B61: Corporate overhead allocation | C61: 0.03 | D61: % of revenue | E61: Assumed | F61: HQ legal, audit, insurance, finance systems, management fee
A62: ga | B62: Other G&A per employee | C62: 1 | D62: mln IRT / employee / month | E62: Assumed | F62: Stationery, travel, staff welfare, misc.
A63: fin | B63: Net finance cost | C63: 0 | D63: mln IRT / month | E63: Assumed | F63: Debt-free; working-capital interest ignored in P&L
A64: E. COMMERCIAL - RATE CARD 2026 (fixed for the year; assumed - blank in Exhibit C)
A65: p_c | B65: Price per handled call | C65: 32000 | D65: IRT / call | E65: Assumed | F65: ~427 IRT per handle-second. Set from FY26 fully-loaded cost-to-serve (~29,000 IRT/call) + target margin, so the line stays profitable after the April wage step
A66: p_t | B66: Price per handled ticket | C66: 17000 | D66: IRT / ticket | E66: Assumed | F66: 425 IRT per handle-second, i.e. same per-second rate as calls (time-based price parity)
A67: sc_th | B67: Service-credit trigger: abandonment above | C67: 0.03 | D67: % | E67: Assumed | F67: Abandonment > 3% signals an 80/20 breach risk
A68: sc_r | B68: Service credit (provision) | C68: 0.015 | D68: % of call revenue | E68: Assumed | F68: Provision in Feb & Nov (4% abandonment months)
A69: F. SCENARIO LEVERS (1.00 = base plan)
A70: vol_real | B70: Realised volume vs. staffed plan | C70: 1 | D70: x | E70: Lever | F70: Flex billable volume while staffing stays on plan - shows Helix's staffing risk

Sheet Topline_ExC
A1: Exhibit C - 2026 Topline (volumes, rate card, revenue)
A2: Calls offered, abandonment and tickets per Exhibit C. Rate card and other fees are my assumptions (blank in case). Units as stated per row.
A4: Line item | B4: Unit | C4: Jan-26 | D4: Feb-26 | E4: Mar-26 | F4: Apr-26 | G4: May-26 | H4: Jun-26 | I4: Jul-26 | J4: Aug-26 | K4: Sep-26 | L4: Oct-26 | M4: Nov-26 | N4: Dec-26 | O4: FY26 | P4: Basis / note
A5: TIMING & INDICES
A6: Month # | B6: # | C6: 1 | D6: 2 | E6: 3 | F6: 4 | G6: 5 | H6: 6 | I6: 7 | J6: 8 | K6: 9 | L6: 10 | M6: 11 | N6: 12
A7: Calendar days | B7: days | C7: 31 | D7: 28 | E7: 31 | F7: 30 | G7: 31 | H7: 30 | I7: 31 | J7: 31 | K7: 30 | L7: 31 | M7: 30 | N7: 31 | O7: =SUM(C7:N7) -> 365
A8: Wage index (1 Apr +25%) | B8: index | C8: =IF(C6>=Assumptions!$C$42,1+Assumptions!$C$41,1) -> 1 | D8: =IF(D6>=Assumptions!$C$42,1+Assumptions!$C$41,1) -> 1 | E8: =IF(E6>=Assumptions!$C$42,1+Assumptions!$C$41,1) -> 1 | F8: =IF(F6>=Assumptions!$C$42,1+Assumptions!$C$41,1) -> 1.25 | G8: =IF(G6>=Assumptions!$C$42,1+Assumptions!$C$41,1) -> 1.25 | H8: =IF(H6>=Assumptions!$C$42,1+Assumptions!$C$41,1) -> 1.25 | I8: =IF(I6>=Assumptions!$C$42,1+Assumptions!$C$41,1) -> 1.25 | J8: =IF(J6>=Assumptions!$C$42,1+Assumptions!$C$41,1) -> 1.25 | ... N8: =IF(N6>=Assumptions!$C$42,1+Assumptions!$C$41,1) -> 1.25 | O8: =AVERAGE(C8:N8) -> 1.1875
A9: Non-payroll cost index | B9: index | C9: =IF(C6>=Assumptions!$C$42,1+Assumptions!$C$58,1) -> 1 | D9: =IF(D6>=Assumptions!$C$42,1+Assumptions!$C$58,1) -> 1 | E9: =IF(E6>=Assumptions!$C$42,1+Assumptions!$C$58,1) -> 1 | F9: =IF(F6>=Assumptions!$C$42,1+Assumptions!$C$58,1) -> 1.15 | G9: =IF(G6>=Assumptions!$C$42,1+Assumptions!$C$58,1) -> 1.15 | H9: =IF(H6>=Assumptions!$C$42,1+Assumptions!$C$58,1) -> 1.15 | I9: =IF(I6>=Assumptions!$C$42,1+Assumptions!$C$58,1) -> 1.15 | J9: =IF(J6>=Assumptions!$C$42,1+Assumptions!$C$58,1) -> 1.15 | ... N9: =IF(N6>=Assumptions!$C$42,1+Assumptions!$C$58,1) -> 1.15 | O9: =AVERAGE(C9:N9) -> 1.1125
A10: VOLUME
A11: Inbound calls offered | B11: # | C11: 320000 | D11: 360000 | E11: 280000 | F11: 300000 | G11: 320000 | H11: 360000 | I11: 400000 | J11: 420000 | K11: 480000 | L11: 490000 | M11: 540000 | N11: 500000 | O11: =SUM(C11:N11) -> 4770000 | P11: Exhibit C (agreed with clients)
A12: Call abandonment rate | B12: % | C12: 0.03 | D12: 0.04 | E12: 0.02 | F12: 0.02 | G12: 0.02 | H12: 0.02 | I12: 0.02 | J12: 0.02 | K12: 0.02 | L12: 0.02 | M12: 0.04 | N12: 0.02 | O12: =1-O13/O11 -> 0.024444444 | P12: Exhibit C
A13: Calls handled - staffing plan | B13: # | C13: =C11*(1-C12) -> 310400 | D13: =D11*(1-D12) -> 345600 | E13: =E11*(1-E12) -> 274400 | F13: =F11*(1-F12) -> 294000 | G13: =G11*(1-G12) -> 313600 | H13: =H11*(1-H12) -> 352800 | I13: =I11*(1-I12) -> 392000 | J13: =J11*(1-J12) -> 411600 | ... N13: =N11*(1-N12) -> 490000 | O13: =SUM(C13:N13) -> 4653400 | P13: Offered x (1 - abandonment). Drives workload / FTE
A14: Tickets handled - staffing plan | B14: # | C14: 210000 | D14: 230000 | E14: 180000 | F14: 200000 | G14: 210000 | H14: 220000 | I14: 250000 | J14: 260000 | K14: 320000 | L14: 350000 | M14: 400000 | N14: 380000 | O14: =SUM(C14:N14) -> 3210000 | P14: Exhibit C
A15: Realised volume vs. plan (scenario lever) | B15: x | C15: =Assumptions!$C$70 -> 1 | D15: =Assumptions!$C$70 -> 1 | E15: =Assumptions!$C$70 -> 1 | F15: =Assumptions!$C$70 -> 1 | G15: =Assumptions!$C$70 -> 1 | H15: =Assumptions!$C$70 -> 1 | I15: =Assumptions!$C$70 -> 1 | J15: =Assumptions!$C$70 -> 1 | ... N15: =Assumptions!$C$70 -> 1 | O15: =AVERAGE(C15:N15) -> 1 | P15: 1.00 in base case
A16: Calls handled / billable | B16: # | C16: =C13*C15 -> 310400 | D16: =D13*D15 -> 345600 | E16: =E13*E15 -> 274400 | F16: =F13*F15 -> 294000 | G16: =G13*G15 -> 313600 | H16: =H13*H15 -> 352800 | I16: =I13*I15 -> 392000 | J16: =J13*J15 -> 411600 | ... N16: =N13*N15 -> 490000 | O16: =SUM(C16:N16) -> 4653400 | P16: Billing per call answered
A17: Tickets handled / billable | B17: # | C17: =C14*C15 -> 210000 | D17: =D14*D15 -> 230000 | E17: =E14*E15 -> 180000 | F17: =F14*F15 -> 200000 | G17: =G14*G15 -> 210000 | H17: =H14*H15 -> 220000 | I17: =I14*I15 -> 250000 | J17: =J14*J15 -> 260000 | ... N17: =N14*N15 -> 380000 | O17: =SUM(C17:N17) -> 3210000
A18: Total billable contacts | B18: # | C18: =C16+C17 -> 520400 | D18: =D16+D17 -> 575600 | E18: =E16+E17 -> 454400 | F18: =F16+F17 -> 494000 | G18: =G16+G17 -> 523600 | H18: =H16+H17 -> 572800 | I18: =I16+I17 -> 642000 | J18: =J16+J17 -> 671600 | ... N18: =N16+N17 -> 870000 | O18: =SUM(C18:N18) -> 7863400
A19: Voice share of contacts | B19: % | C19: =C16/C18 -> 0.59646426 | D19: =D16/D18 -> 0.60041696 | E19: =E16/E18 -> 0.60387324 | F19: =F16/F18 -> 0.5951417 | G19: =G16/G18 -> 0.59893048 | H19: =H16/H18 -> 0.61592179 | I19: =I16/I18 -> 0.6105919 | J19: =J16/J18 -> 0.6128648 | ... O19: =O16/O18 -> 0.59177964
A20: RATE CARD (fixed for 2026)
A21: Price per handled call | B21: IRT | C21: =Assumptions!$C$65 -> 32000 | D21: =Assumptions!$C$65 -> 32000 | E21: =Assumptions!$C$65 -> 32000 | F21: =Assumptions!$C$65 -> 32000 | G21: =Assumptions!$C$65 -> 32000 | H21: =Assumptions!$C$65 -> 32000 | I21: =Assumptions!$C$65 -> 32000 | J21: =Assumptions!$C$65 -> 32000 | ... N21: =Assumptions!$C$65 -> 32000 | O21: =IFERROR(O27*1000000/O16,0) -> 32000 | P21: Assumption E - see Assumptions
A22: Price per handled ticket | B22: IRT | C22: =Assumptions!$C$66 -> 17000 | D22: =Assumptions!$C$66 -> 17000 | E22: =Assumptions!$C$66 -> 17000 | F22: =Assumptions!$C$66 -> 17000 | G22: =Assumptions!$C$66 -> 17000 | H22: =Assumptions!$C$66 -> 17000 | I22: =Assumptions!$C$66 -> 17000 | J22: =Assumptions!$C$66 -> 17000 | ... N22: =Assumptions!$C$66 -> 17000 | O22: =IFERROR(O28*1000000/O17,0) -> 17000
A23: One-off: onboarding / set-up fee | B23: mln IRT | C23: 0 | D23: 0 | E23: 0 | F23: 0 | G23: 0 | H23: 0 | I23: 0 | J23: 0 | K23: 1000 | L23: 0 | M23: 0 | N23: 0 | O23: =SUM(C23:N23) -> 1000 | P23: Assumed: fee agreed for the Sep ramp of a new ticket workstream (+23% tickets)
A24: Service credits (SLA provision) | B24: mln IRT | C24: =-IF(C12>Assumptions!$C$67,Assumptions!$C$68*C27,0) -> 0 | D24: =-IF(D12>Assumptions!$C$67,Assumptions!$C$68*D27,0) -> -165.888 | E24: =-IF(E12>Assumptions!$C$67,Assumptions!$C$68*E27,0) -> 0 | F24: =-IF(F12>Assumptions!$C$67,Assumptions!$C$68*F27,0) -> 0 | G24: =-IF(G12>Assumptions!$C$67,Assumptions!$C$68*G27,0) -> 0 | H24: =-IF(H12>Assumptions!$C$67,Assumptions!$C$68*H27,0) -> 0 | I24: =-IF(I12>Assumptions!$C$67,Assumptions!$C$68*I27,0) -> 0 | J24: =-IF(J12>Assumptions!$C$67,Assumptions!$C$68*J27,0) -> 0 | ... N24: =-IF(N12>Assumptions!$C$67,Assumptions!$C$68*N27,0) -> 0 | O24: =SUM(C24:N24) -> -414.72 | P24: Assumed: 1.5% of call revenue when abandonment > 3%
A25: Other / one-off fees (net) | B25: mln IRT | C25: =C23+C24 -> 0 | D25: =D23+D24 -> -165.888 | E25: =E23+E24 -> 0 | F25: =F23+F24 -> 0 | G25: =G23+G24 -> 0 | H25: =H23+H24 -> 0 | I25: =I23+I24 -> 0 | J25: =J23+J24 -> 0 | ... N25: =N23+N24 -> 0 | O25: =SUM(C25:N25) -> 585.28
A26: REVENUE (derived) - mln IRT
A27: Call revenue | B27: mln IRT | C27: =C16*C21/1000000 -> 9932.8 | D27: =D16*D21/1000000 -> 11059.2 | E27: =E16*E21/1000000 -> 8780.8 | F27: =F16*F21/1000000 -> 9408 | G27: =G16*G21/1000000 -> 10035.2 | H27: =H16*H21/1000000 -> 11289.6 | I27: =I16*I21/1000000 -> 12544 | J27: =J16*J21/1000000 -> 13171.2 | ... N27: =N16*N21/1000000 -> 15680 | O27: =SUM(C27:N27) -> 148908.8
A28: Ticket revenue | B28: mln IRT | C28: =C17*C22/1000000 -> 3570 | D28: =D17*D22/1000000 -> 3910 | E28: =E17*E22/1000000 -> 3060 | F28: =F17*F22/1000000 -> 3400 | G28: =G17*G22/1000000 -> 3570 | H28: =H17*H22/1000000 -> 3740 | I28: =I17*I22/1000000 -> 4250 | J28: =J17*J22/1000000 -> 4420 | ... N28: =N17*N22/1000000 -> 6460 | O28: =SUM(C28:N28) -> 54570
A29: Other / one-off fees (net) | B29: mln IRT | C29: =C25 -> 0 | D29: =D25 -> -165.888 | E29: =E25 -> 0 | F29: =F25 -> 0 | G29: =G25 -> 0 | H29: =H25 -> 0 | I29: =I25 -> 0 | J29: =J25 -> 0 | ... N29: =N25 -> 0 | O29: =SUM(C29:N29) -> 585.28
A30: Gross revenue | B30: mln IRT | C30: =SUM(C27:C29) -> 13502.8 | D30: =SUM(D27:D29) -> 14803.312 | E30: =SUM(E27:E29) -> 11840.8 | F30: =SUM(F27:F29) -> 12808 | G30: =SUM(G27:G29) -> 13605.2 | H30: =SUM(H27:H29) -> 15029.6 | I30: =SUM(I27:I29) -> 16794 | J30: =SUM(J27:J29) -> 17591.2 | ... N30: =SUM(N27:N29) -> 22140 | O30: =SUM(C30:N30) -> 204064.08
A31: Revenue growth MoM | B31: % | C31: =0 -> 0 | D31: =D30/C30-1 -> 0.096314246 | E31: =E30/D30-1 -> -0.20012495 | F31: =F30/E30-1 -> 0.08168367 | G31: =G30/F30-1 -> 0.062242349 | H31: =H30/G30-1 -> 0.10469526 | I31: =I30/H30-1 -> 0.11739501 | J31: =J30/I30-1 -> 0.047469334 | K31: =K30/J30-1 -> 0.22179271 | ... N31: =N30/M30-1 -> -0.043213889

Sheet Capacity_ExD
A1: Exhibit D - Capacity & FTE build
A2: Volume -> workload hours -> net productive hours per FTE -> agent FTE -> headcount flow -> support roles -> seats. No jump straight to headcount.
A4: Line item | B4: Unit | C4: Jan-26 | D4: Feb-26 | E4: Mar-26 | F4: Apr-26 | G4: May-26 | H4: Jun-26 | I4: Jul-26 | J4: Aug-26 | K4: Sep-26 | L4: Oct-26 | M4: Nov-26 | N4: Dec-26 | O4: FY26 | P4: Basis / note
A5: 1. WORKLOAD - volume x AHT = productive hours required
A6: Calls handled (plan) | B6: # | C6: =Topline_ExC!C13 -> 310400 | D6: =Topline_ExC!D13 -> 345600 | E6: =Topline_ExC!E13 -> 274400 | F6: =Topline_ExC!F13 -> 294000 | G6: =Topline_ExC!G13 -> 313600 | H6: =Topline_ExC!H13 -> 352800 | I6: =Topline_ExC!I13 -> 392000 | J6: =Topline_ExC!J13 -> 411600 | ... N6: =Topline_ExC!N13 -> 490000 | O6: =SUM(C6:N6) -> 4653400
A7: AHT - call | B7: sec | C7: =Assumptions!$C$6 -> 75 | D7: =Assumptions!$C$6 -> 75 | E7: =Assumptions!$C$6 -> 75 | F7: =Assumptions!$C$6 -> 75 | G7: =Assumptions!$C$6 -> 75 | H7: =Assumptions!$C$6 -> 75 | I7: =Assumptions!$C$6 -> 75 | J7: =Assumptions!$C$6 -> 75 | ... N7: =Assumptions!$C$6 -> 75 | O7: =AVERAGE(C7:N7) -> 75
A8: Voice workload | B8: hours | C8: =C6*C7/3600 -> 6466.6667 | D8: =D6*D7/3600 -> 7200 | E8: =E6*E7/3600 -> 5716.6667 | F8: =F6*F7/3600 -> 6125 | G8: =G6*G7/3600 -> 6533.3333 | H8: =H6*H7/3600 -> 7350 | I8: =I6*I7/3600 -> 8166.6667 | J8: =J6*J7/3600 -> 8575 | ... N8: =N6*N7/3600 -> 10208.333 | O8: =SUM(C8:N8) -> 96945.833
A9: Tickets handled (plan) | B9: # | C9: =Topline_ExC!C14 -> 210000 | D9: =Topline_ExC!D14 -> 230000 | E9: =Topline_ExC!E14 -> 180000 | F9: =Topline_ExC!F14 -> 200000 | G9: =Topline_ExC!G14 -> 210000 | H9: =Topline_ExC!H14 -> 220000 | I9: =Topline_ExC!I14 -> 250000 | J9: =Topline_ExC!J14 -> 260000 | ... N9: =Topline_ExC!N14 -> 380000 | O9: =SUM(C9:N9) -> 3210000
A10: AHT - ticket | B10: sec | C10: =Assumptions!$C$7 -> 40 | D10: =Assumptions!$C$7 -> 40 | E10: =Assumptions!$C$7 -> 40 | F10: =Assumptions!$C$7 -> 40 | G10: =Assumptions!$C$7 -> 40 | H10: =Assumptions!$C$7 -> 40 | I10: =Assumptions!$C$7 -> 40 | J10: =Assumptions!$C$7 -> 40 | ... N10: =Assumptions!$C$7 -> 40 | O10: =AVERAGE(C10:N10) -> 40
A11: Ticket workload | B11: hours | C11: =C9*C10/3600 -> 2333.3333 | D11: =D9*D10/3600 -> 2555.5556 | E11: =E9*E10/3600 -> 2000 | F11: =F9*F10/3600 -> 2222.2222 | G11: =G9*G10/3600 -> 2333.3333 | H11: =H9*H10/3600 -> 2444.4444 | I11: =I9*I10/3600 -> 2777.7778 | J11: =J9*J10/3600 -> 2888.8889 | ... N11: =N9*N10/3600 -> 4222.2222 | O11: =SUM(C11:N11) -> 35666.667
A12: Total productive hours required | B12: hours | C12: =C8+C11 -> 8800 | D12: =D8+D11 -> 9755.5556 | E12: =E8+E11 -> 7716.6667 | F12: =F8+F11 -> 8347.2222 | G12: =G8+G11 -> 8866.6667 | H12: =H8+H11 -> 9794.4444 | I12: =I8+I11 -> 10944.444 | J12: =J8+J11 -> 11463.889 | ... N12: =N8+N11 -> 14430.556 | O12: =SUM(C12:N12) -> 132612.5
A13: 2. NET PRODUCTIVE HOURS PER AGENT FTE
A14: Paid hours per FTE | B14: hours | C14: =Assumptions!$C$12 -> 176 | D14: =Assumptions!$C$12 -> 176 | E14: =Assumptions!$C$12 -> 176 | F14: =Assumptions!$C$12 -> 176 | G14: =Assumptions!$C$12 -> 176 | H14: =Assumptions!$C$12 -> 176 | I14: =Assumptions!$C$12 -> 176 | J14: =Assumptions!$C$12 -> 176 | ... N14: =Assumptions!$C$12 -> 176 | O14: =AVERAGE(C14:N14) -> 176
A15: Shrinkage | B15: % | C15: =Assumptions!$C$11 -> 0.3 | D15: =Assumptions!$C$11 -> 0.3 | E15: =Assumptions!$C$11 -> 0.3 | F15: =Assumptions!$C$11 -> 0.3 | G15: =Assumptions!$C$11 -> 0.3 | H15: =Assumptions!$C$11 -> 0.3 | I15: =Assumptions!$C$11 -> 0.3 | J15: =Assumptions!$C$11 -> 0.3 | ... N15: =Assumptions!$C$11 -> 0.3 | O15: =AVERAGE(C15:N15) -> 0.3
A16: Available (logged-in) hours per FTE | B16: hours | C16: =C14*(1-C15) -> 123.2 | D16: =D14*(1-D15) -> 123.2 | E16: =E14*(1-E15) -> 123.2 | F16: =F14*(1-F15) -> 123.2 | G16: =G14*(1-G15) -> 123.2 | H16: =H14*(1-H15) -> 123.2 | I16: =I14*(1-I15) -> 123.2 | J16: =J14*(1-J15) -> 123.2 | ... N16: =N14*(1-N15) -> 123.2 | O16: =AVERAGE(C16:N16) -> 123.2
A17: Occupancy - voice | B17: % | C17: =Assumptions!$C$10 -> 0.78 | D17: =Assumptions!$C$10 -> 0.78 | E17: =Assumptions!$C$10 -> 0.78 | F17: =Assumptions!$C$10 -> 0.78 | G17: =Assumptions!$C$10 -> 0.78 | H17: =Assumptions!$C$10 -> 0.78 | I17: =Assumptions!$C$10 -> 0.78 | J17: =Assumptions!$C$10 -> 0.78 | ... N17: =Assumptions!$C$10 -> 0.78 | O17: =AVERAGE(C17:N17) -> 0.78
A18: Occupancy - tickets | B18: % | C18: =Assumptions!$C$20 -> 0.9 | D18: =Assumptions!$C$20 -> 0.9 | E18: =Assumptions!$C$20 -> 0.9 | F18: =Assumptions!$C$20 -> 0.9 | G18: =Assumptions!$C$20 -> 0.9 | H18: =Assumptions!$C$20 -> 0.9 | I18: =Assumptions!$C$20 -> 0.9 | J18: =Assumptions!$C$20 -> 0.9 | ... N18: =Assumptions!$C$20 -> 0.9 | O18: =AVERAGE(C18:N18) -> 0.9
A19: Net productive hours / FTE - voice | B19: hours | C19: =C16*C17 -> 96.096 | D19: =D16*D17 -> 96.096 | E19: =E16*E17 -> 96.096 | F19: =F16*F17 -> 96.096 | G19: =G16*G17 -> 96.096 | H19: =H16*H17 -> 96.096 | I19: =I16*I17 -> 96.096 | J19: =J16*J17 -> 96.096 | ... N19: =N16*N17 -> 96.096 | O19: =AVERAGE(C19:N19) -> 96.096 | P19: 176 x (1-30%) x 78% = 96.1h
A20: Net productive hours / FTE - tickets | B20: hours | C20: =C16*C18 -> 110.88 | D20: =D16*D18 -> 110.88 | E20: =E16*E18 -> 110.88 | F20: =F16*F18 -> 110.88 | G20: =G16*G18 -> 110.88 | H20: =H16*H18 -> 110.88 | I20: =I16*I18 -> 110.88 | J20: =J16*J18 -> 110.88 | ... N20: =N16*N18 -> 110.88 | O20: =AVERAGE(C20:N20) -> 110.88 | P20: 176 x (1-30%) x 90% = 110.9h
A21: Capacity per voice FTE | B21: calls / month | C21: =C19*3600/C7 -> 4612.608 | D21: =D19*3600/D7 -> 4612.608 | E21: =E19*3600/E7 -> 4612.608 | F21: =F19*3600/F7 -> 4612.608 | G21: =G19*3600/G7 -> 4612.608 | H21: =H19*3600/H7 -> 4612.608 | I21: =I19*3600/I7 -> 4612.608 | J21: =J19*3600/J7 -> 4612.608 | ... N21: =N19*3600/N7 -> 4612.608 | O21: =AVERAGE(C21:N21) -> 4612.608
A22: Capacity per ticket FTE | B22: tickets / month | C22: =C20*3600/C10 -> 9979.2 | D22: =D20*3600/D10 -> 9979.2 | E22: =E20*3600/E10 -> 9979.2 | F22: =F20*3600/F10 -> 9979.2 | G22: =G20*3600/G10 -> 9979.2 | H22: =H20*3600/H10 -> 9979.2 | I22: =I20*3600/I10 -> 9979.2 | J22: =J20*3600/J10 -> 9979.2 | ... N22: =N20*3600/N10 -> 9979.2 | O22: =AVERAGE(C22:N22) -> 9979.2
A23: 3. OVERTIME COVER (3% of productive hours)
A24: OT share of productive hours | B24: % | C24: =Assumptions!$C$21 -> 0.03 | D24: =Assumptions!$C$21 -> 0.03 | E24: =Assumptions!$C$21 -> 0.03 | F24: =Assumptions!$C$21 -> 0.03 | G24: =Assumptions!$C$21 -> 0.03 | H24: =Assumptions!$C$21 -> 0.03 | I24: =Assumptions!$C$21 -> 0.03 | J24: =Assumptions!$C$21 -> 0.03 | ... N24: =Assumptions!$C$21 -> 0.03 | O24: =AVERAGE(C24:N24) -> 0.03
A25: Overtime hours | B25: hours | C25: =C12*C24 -> 264 | D25: =D12*D24 -> 292.66667 | E25: =E12*E24 -> 231.5 | F25: =F12*F24 -> 250.41667 | G25: =G12*G24 -> 266 | H25: =H12*H24 -> 293.83333 | I25: =I12*I24 -> 328.33333 | J25: =J12*J24 -> 343.91667 | ... N25: =N12*N24 -> 432.91667 | O25: =SUM(C25:N25) -> 3978.375 | P25: Assumed 1 OT hour = 1 productive hour
A26: Voice hours covered by rostered FTE | B26: hours | C26: =C8*(1-C24) -> 6272.6667 | D26: =D8*(1-D24) -> 6984 | E26: =E8*(1-E24) -> 5545.1667 | F26: =F8*(1-F24) -> 5941.25 | G26: =G8*(1-G24) -> 6337.3333 | H26: =H8*(1-H24) -> 7129.5 | I26: =I8*(1-I24) -> 7921.6667 | J26: =J8*(1-J24) -> 8317.75 | ... N26: =N8*(1-N24) -> 9902.0833 | O26: =SUM(C26:N26) -> 94037.458
A27: Ticket hours covered by rostered FTE | B27: hours | C27: =C11*(1-C24) -> 2263.3333 | D27: =D11*(1-D24) -> 2478.8889 | E27: =E11*(1-E24) -> 1940 | F27: =F11*(1-F24) -> 2155.5556 | G27: =G11*(1-G24) -> 2263.3333 | H27: =H11*(1-H24) -> 2371.1111 | I27: =I11*(1-I24) -> 2694.4444 | J27: =J11*(1-J24) -> 2802.2222 | ... N27: =N11*(1-N24) -> 4095.5556 | O27: =SUM(C27:N27) -> 34596.667
A28: 4. AGENT FTE REQUIREMENT
A29: Voice agent FTE required | B29: FTE | C29: =C26/C19 -> 65.275003 | D29: =D26/D19 -> 72.677323 | E29: =E26/E19 -> 57.704448 | F29: =F26/F19 -> 61.826195 | G29: =G26/G19 -> 65.947941 | H29: =H26/H19 -> 74.191434 | I29: =I26/I19 -> 82.434926 | J29: =J26/J19 -> 86.556672 | ... N29: =N26/N19 -> 103.04366 | O29: =AVERAGE(C29:N29) -> 81.54819
A30: Ticket agent FTE required | B30: FTE | C30: =C27/C20 -> 20.412458 | D30: =D27/D20 -> 22.356502 | E30: =E27/E20 -> 17.496392 | F30: =F27/F20 -> 19.440436 | G30: =G27/G20 -> 20.412458 | H30: =H27/H20 -> 21.38448 | I30: =I27/I20 -> 24.300545 | J30: =J27/J20 -> 25.272567 | ... N30: =N27/N20 -> 36.936829 | O30: =AVERAGE(C30:N30) -> 26.001583
A31: Total agent FTE required (productive) | B31: FTE | C31: =C29+C30 -> 85.687461 | D31: =D29+D30 -> 95.033824 | E31: =E29+E30 -> 75.200841 | F31: =F29+F30 -> 81.266631 | G31: =G29+G30 -> 86.360399 | H31: =H29+H30 -> 95.575913 | I31: =I29+I30 -> 106.73547 | J31: =J29+J30 -> 111.82924 | ... N31: =N29+N30 -> 139.98049 | O31: =AVERAGE(C31:N31) -> 107.54977
A32: 5. AGENT HEADCOUNT FLOW - no-layoff policy: surplus is released only through attrition
A33: Opening agent headcount | B33: FTE | C33: =C31 -> 85.687461 | D33: =C36 -> 85.687461 | E33: =D36 -> 95.033824 | F33: =E36 -> 91.232471 | G33: =F36 -> 87.583172 | H33: =G36 -> 86.360399 | I33: =H36 -> 95.575913 | J33: =I36 -> 106.73547 | K33: =J36 -> 111.82924 | ... N33: =M36 -> 147.89686 | O33: =C33 -> 85.687461 | P33: Dec-25 exit assumed = Jan-26 requirement
A34: Leavers (attrition) | B34: FTE | C34: =C33*Assumptions!$C$22 -> 3.4274984 | D34: =D33*Assumptions!$C$22 -> 3.4274984 | E34: =E33*Assumptions!$C$22 -> 3.801353 | F34: =F33*Assumptions!$C$22 -> 3.6492988 | G34: =G33*Assumptions!$C$22 -> 3.5033269 | H34: =H33*Assumptions!$C$22 -> 3.454416 | I34: =I33*Assumptions!$C$22 -> 3.8230365 | J34: =J33*Assumptions!$C$22 -> 4.2694189 | ... N34: =N33*Assumptions!$C$22 -> 5.9158742 | O34: =SUM(C34:N34) -> 50.346097
A35: New hires | B35: FTE | C35: =MAX(0,C31-(C33-C34)) -> 3.4274984 | D35: =MAX(0,D31-(D33-D34)) -> 12.773862 | E35: =MAX(0,E31-(E33-E34)) -> 0 | F35: =MAX(0,F31-(F33-F34)) -> 0 | G35: =MAX(0,G31-(G33-G34)) -> 2.2805534 | H35: =MAX(0,H31-(H33-H34)) -> 12.66993 | I35: =MAX(0,I31-(I33-I34)) -> 14.982595 | J35: =MAX(0,J31-(J33-J34)) -> 9.363187 | ... N35: =MAX(0,N31-(N33-N34)) -> 0 | O35: =SUM(C35:N35) -> 106.63962 | P35: Hire only the gap after attrition
A36: Closing agent headcount (on payroll) | B36: FTE | C36: =C33-C34+C35 -> 85.687461 | D36: =D33-D34+D35 -> 95.033824 | E36: =E33-E34+E35 -> 91.232471 | F36: =F33-F34+F35 -> 87.583172 | G36: =G33-G34+G35 -> 86.360399 | H36: =H33-H34+H35 -> 95.575913 | I36: =I33-I34+I35 -> 106.73547 | J36: =J33-J34+J35 -> 111.82924 | ... N36: =N33-N34+N35 -> 141.98098 | O36: =AVERAGE(C36:N36) -> 109.57883
A37: Surplus / idle agent FTE | B37: FTE | C37: =C36-C31 -> 0 | D37: =D36-D31 -> 0 | E37: =E36-E31 -> 16.03163 | F37: =F36-F31 -> 6.3165416 | G37: =G36-G31 -> 0 | H37: =H36-H31 -> 0 | I37: =I36-I31 -> 0 | J37: =J36-J31 -> 0 | ... N37: =N36-N31 -> 2.0004956 | O37: =AVERAGE(C37:N37) -> 2.0290556 | P37: Paid capacity above need (e.g. Mar after Feb peak)
A38: Trainee FTE (non-productive) | B38: FTE | C38: =C35*Assumptions!$C$23 -> 1.7137492 | D38: =D35*Assumptions!$C$23 -> 6.386931 | E38: =E35*Assumptions!$C$23 -> 0 | F38: =F35*Assumptions!$C$23 -> 0 | G38: =G35*Assumptions!$C$23 -> 1.1402767 | H38: =H35*Assumptions!$C$23 -> 6.3349652 | I38: =I35*Assumptions!$C$23 -> 7.4912973 | J38: =J35*Assumptions!$C$23 -> 4.6815935 | ... N38: =N35*Assumptions!$C$23 -> 0 | O38: =AVERAGE(C38:N38) -> 4.4433174
A39: Agent utilisation (required / on payroll) | B39: % | C39: =C31/C36 -> 1 | D39: =D31/D36 -> 1 | E39: =E31/E36 -> 0.82427714 | F39: =F31/F36 -> 0.92787951 | G39: =G31/G36 -> 1 | H39: =H31/H36 -> 1 | I39: =I31/I36 -> 1 | J39: =J31/J36 -> 1 | ... O39: =O31/O36 -> 0.98148314
A40: 6. SUPPORT & MANAGEMENT ROLES (rounded up to whole heads; ratchet - never reduced within the year)
A41: Team leaders (1:15 agents) | B41: HC | C41: =ROUNDUP(C36/Assumptions!$C$13,0) -> 6 | D41: =MAX(C41,ROUNDUP(D36/Assumptions!$C$13,0)) -> 7 | E41: =MAX(D41,ROUNDUP(E36/Assumptions!$C$13,0)) -> 7 | F41: =MAX(E41,ROUNDUP(F36/Assumptions!$C$13,0)) -> 7 | G41: =MAX(F41,ROUNDUP(G36/Assumptions!$C$13,0)) -> 7 | H41: =MAX(G41,ROUNDUP(H36/Assumptions!$C$13,0)) -> 7 | I41: =MAX(H41,ROUNDUP(I36/Assumptions!$C$13,0)) -> 8 | J41: =MAX(I41,ROUNDUP(J36/Assumptions!$C$13,0)) -> 8 | K41: =MAX(J41,ROUNDUP(K36/Assumptions!$C$13,0)) -> 9 | ... N41: =MAX(M41,ROUNDUP(N36/Assumptions!$C$13,0)) -> 10 | O41: =AVERAGE(C41:N41) -> 8 | P41: Ratchet: support roles are not cut within the year
A42: Operations managers (1:6 TLs) | B42: HC | C42: =ROUNDUP(C41/Assumptions!$C$14,0) -> 1 | D42: =MAX(C42,ROUNDUP(D41/Assumptions!$C$14,0)) -> 2 | E42: =MAX(D42,ROUNDUP(E41/Assumptions!$C$14,0)) -> 2 | F42: =MAX(E42,ROUNDUP(F41/Assumptions!$C$14,0)) -> 2 | G42: =MAX(F42,ROUNDUP(G41/Assumptions!$C$14,0)) -> 2 | H42: =MAX(G42,ROUNDUP(H41/Assumptions!$C$14,0)) -> 2 | I42: =MAX(H42,ROUNDUP(I41/Assumptions!$C$14,0)) -> 2 | J42: =MAX(I42,ROUNDUP(J41/Assumptions!$C$14,0)) -> 2 | K42: =MAX(J42,ROUNDUP(K41/Assumptions!$C$14,0)) -> 2 | ... N42: =MAX(M42,ROUNDUP(N41/Assumptions!$C$14,0)) -> 2 | O42: =AVERAGE(C42:N42) -> 1.9166667
A43: Quality analysts (1:40 agents) | B43: HC | C43: =ROUNDUP(C36/Assumptions!$C$15,0) -> 3 | D43: =MAX(C43,ROUNDUP(D36/Assumptions!$C$15,0)) -> 3 | E43: =MAX(D43,ROUNDUP(E36/Assumptions!$C$15,0)) -> 3 | F43: =MAX(E43,ROUNDUP(F36/Assumptions!$C$15,0)) -> 3 | G43: =MAX(F43,ROUNDUP(G36/Assumptions!$C$15,0)) -> 3 | H43: =MAX(G43,ROUNDUP(H36/Assumptions!$C$15,0)) -> 3 | I43: =MAX(H43,ROUNDUP(I36/Assumptions!$C$15,0)) -> 3 | J43: =MAX(I43,ROUNDUP(J36/Assumptions!$C$15,0)) -> 3 | K43: =MAX(J43,ROUNDUP(K36/Assumptions!$C$15,0)) -> 4 | ... N43: =MAX(M43,ROUNDUP(N36/Assumptions!$C$15,0)) -> 4 | O43: =AVERAGE(C43:N43) -> 3.3333333
A44: WFM analysts (1:75) - assumed | B44: HC | C44: =ROUNDUP(C36/Assumptions!$C$24,0) -> 2 | D44: =MAX(C44,ROUNDUP(D36/Assumptions!$C$24,0)) -> 2 | E44: =MAX(D44,ROUNDUP(E36/Assumptions!$C$24,0)) -> 2 | F44: =MAX(E44,ROUNDUP(F36/Assumptions!$C$24,0)) -> 2 | G44: =MAX(F44,ROUNDUP(G36/Assumptions!$C$24,0)) -> 2 | H44: =MAX(G44,ROUNDUP(H36/Assumptions!$C$24,0)) -> 2 | I44: =MAX(H44,ROUNDUP(I36/Assumptions!$C$24,0)) -> 2 | J44: =MAX(I44,ROUNDUP(J36/Assumptions!$C$24,0)) -> 2 | K44: =MAX(J44,ROUNDUP(K36/Assumptions!$C$24,0)) -> 2 | ... N44: =MAX(M44,ROUNDUP(N36/Assumptions!$C$24,0)) -> 2 | O44: =AVERAGE(C44:N44) -> 2
A45: Trainers (1:60) - assumed | B45: HC | C45: =ROUNDUP(C36/Assumptions!$C$25,0) -> 2 | D45: =MAX(C45,ROUNDUP(D36/Assumptions!$C$25,0)) -> 2 | E45: =MAX(D45,ROUNDUP(E36/Assumptions!$C$25,0)) -> 2 | F45: =MAX(E45,ROUNDUP(F36/Assumptions!$C$25,0)) -> 2 | G45: =MAX(F45,ROUNDUP(G36/Assumptions!$C$25,0)) -> 2 | H45: =MAX(G45,ROUNDUP(H36/Assumptions!$C$25,0)) -> 2 | I45: =MAX(H45,ROUNDUP(I36/Assumptions!$C$25,0)) -> 2 | J45: =MAX(I45,ROUNDUP(J36/Assumptions!$C$25,0)) -> 2 | K45: =MAX(J45,ROUNDUP(K36/Assumptions!$C$25,0)) -> 3 | ... N45: =MAX(M45,ROUNDUP(N36/Assumptions!$C$25,0)) -> 3 | O45: =AVERAGE(C45:N45) -> 2.3333333
A46: IT / MIS support (1:75) - assumed | B46: HC | C46: =ROUNDUP(C36/Assumptions!$C$26,0) -> 2 | D46: =MAX(C46,ROUNDUP(D36/Assumptions!$C$26,0)) -> 2 | E46: =MAX(D46,ROUNDUP(E36/Assumptions!$C$26,0)) -> 2 | F46: =MAX(E46,ROUNDUP(F36/Assumptions!$C$26,0)) -> 2 | G46: =MAX(F46,ROUNDUP(G36/Assumptions!$C$26,0)) -> 2 | H46: =MAX(G46,ROUNDUP(H36/Assumptions!$C$26,0)) -> 2 | I46: =MAX(H46,ROUNDUP(I36/Assumptions!$C$26,0)) -> 2 | J46: =MAX(I46,ROUNDUP(J36/Assumptions!$C$26,0)) -> 2 | K46: =MAX(J46,ROUNDUP(K36/Assumptions!$C$26,0)) -> 2 | ... N46: =MAX(M46,ROUNDUP(N36/Assumptions!$C$26,0)) -> 2 | O46: =AVERAGE(C46:N46) -> 2
A47: HR, recruitment & admin (1:75) - assumed | B47: HC | C47: =ROUNDUP(C36/Assumptions!$C$27,0) -> 2 | D47: =MAX(C47,ROUNDUP(D36/Assumptions!$C$27,0)) -> 2 | E47: =MAX(D47,ROUNDUP(E36/Assumptions!$C$27,0)) -> 2 | F47: =MAX(E47,ROUNDUP(F36/Assumptions!$C$27,0)) -> 2 | G47: =MAX(F47,ROUNDUP(G36/Assumptions!$C$27,0)) -> 2 | H47: =MAX(G47,ROUNDUP(H36/Assumptions!$C$27,0)) -> 2 | I47: =MAX(H47,ROUNDUP(I36/Assumptions!$C$27,0)) -> 2 | J47: =MAX(I47,ROUNDUP(J36/Assumptions!$C$27,0)) -> 2 | K47: =MAX(J47,ROUNDUP(K36/Assumptions!$C$27,0)) -> 2 | ... N47: =MAX(M47,ROUNDUP(N36/Assumptions!$C$27,0)) -> 2 | O47: =AVERAGE(C47:N47) -> 2
A48: Site director | B48: HC | C48: =Assumptions!$C$16 -> 1 | D48: =Assumptions!$C$16 -> 1 | E48: =Assumptions!$C$16 -> 1 | F48: =Assumptions!$C$16 -> 1 | G48: =Assumptions!$C$16 -> 1 | H48: =Assumptions!$C$16 -> 1 | I48: =Assumptions!$C$16 -> 1 | J48: =Assumptions!$C$16 -> 1 | ... N48: =Assumptions!$C$16 -> 1 | O48: =AVERAGE(C48:N48) -> 1
A49: Finance / HR business partner | B49: HC | C49: =Assumptions!$C$17 -> 1 | D49: =Assumptions!$C$17 -> 1 | E49: =Assumptions!$C$17 -> 1 | F49: =Assumptions!$C$17 -> 1 | G49: =Assumptions!$C$17 -> 1 | H49: =Assumptions!$C$17 -> 1 | I49: =Assumptions!$C$17 -> 1 | J49: =Assumptions!$C$17 -> 1 | ... N49: =Assumptions!$C$17 -> 1 | O49: =AVERAGE(C49:N49) -> 1
A50: Account managers - assumed | B50: HC | C50: =Assumptions!$C$28 -> 2 | D50: =Assumptions!$C$28 -> 2 | E50: =Assumptions!$C$28 -> 2 | F50: =Assumptions!$C$28 -> 2 | G50: =Assumptions!$C$28 -> 2 | H50: =Assumptions!$C$28 -> 2 | I50: =Assumptions!$C$28 -> 2 | J50: =Assumptions!$C$28 -> 2 | ... N50: =Assumptions!$C$28 -> 2 | O50: =AVERAGE(C50:N50) -> 2
A51: Total support & management | B51: HC | C51: =SUM(C41:C50) -> 22 | D51: =SUM(D41:D50) -> 24 | E51: =SUM(E41:E50) -> 24 | F51: =SUM(F41:F50) -> 24 | G51: =SUM(G41:G50) -> 24 | H51: =SUM(H41:H50) -> 24 | I51: =SUM(I41:I50) -> 25 | J51: =SUM(J41:J50) -> 25 | ... N51: =SUM(N41:N50) -> 29 | O51: =AVERAGE(C51:N51) -> 25.583333
A52: TOTAL HEADCOUNT (agents + support) | B52: FTE | C52: =C36+C51 -> 107.68746 | D52: =D36+D51 -> 119.03382 | E52: =E36+E51 -> 115.23247 | F52: =F36+F51 -> 111.58317 | G52: =G36+G51 -> 110.3604 | H52: =H36+H51 -> 119.57591 | I52: =I36+I51 -> 131.73547 | J52: =J36+J51 -> 136.82924 | ... N52: =N36+N51 -> 170.98098 | O52: =AVERAGE(C52:N52) -> 135.16216
A53: Agents per support FTE | B53: x | C53: =C36/C51 -> 3.8948846 | D53: =D36/D51 -> 3.9597427 | E53: =E36/E51 -> 3.801353 | F53: =F36/F51 -> 3.6492988 | G53: =G36/G51 -> 3.59835 | H53: =H36/H51 -> 3.9823297 | I53: =I36/I51 -> 4.2694189 | J53: =J36/J51 -> 4.4731696 | ... O53: =O36/O51 -> 4.2832116
A54: 7. SEATS & FACILITIES
A55: Agent seats (agents / 1.5) | B55: seats | C55: =C36/Assumptions!$C$29 -> 57.124974 | D55: =D36/Assumptions!$C$29 -> 63.355883 | E55: =E36/Assumptions!$C$29 -> 60.821647 | F55: =F36/Assumptions!$C$29 -> 58.388782 | G55: =G36/Assumptions!$C$29 -> 57.573599 | H55: =H36/Assumptions!$C$29 -> 63.717276 | I55: =I36/Assumptions!$C$29 -> 71.156981 | J55: =J36/Assumptions!$C$29 -> 74.552826 | ... N55: =N36/Assumptions!$C$29 -> 94.653988 | O55: =AVERAGE(C55:N55) -> 73.052553
A56: Support seats (1 per head) | B56: seats | C56: =C51 -> 22 | D56: =D51 -> 24 | E56: =E51 -> 24 | F56: =F51 -> 24 | G56: =G51 -> 24 | H56: =H51 -> 24 | I56: =I51 -> 25 | J56: =J51 -> 25 | ... N56: =N51 -> 29 | O56: =AVERAGE(C56:N56) -> 25.583333
A57: Seats required | B57: seats | C57: =ROUNDUP(C55+C56,0) -> 80 | D57: =ROUNDUP(D55+D56,0) -> 88 | E57: =ROUNDUP(E55+E56,0) -> 85 | F57: =ROUNDUP(F55+F56,0) -> 83 | G57: =ROUNDUP(G55+G56,0) -> 82 | H57: =ROUNDUP(H55+H56,0) -> 88 | I57: =ROUNDUP(I55+I56,0) -> 97 | J57: =ROUNDUP(J55+J56,0) -> 100 | ... N57: =ROUNDUP(N55+N56,0) -> 124 | O57: =MAX(C57:N57) -> 128
A58: Seats leased (FY peak + buffer, fixed) | B58: seats | C58: =ROUNDUP(MAX($C$57:$N$57)*(1+Assumptions!$C$30),0) -> 141 | D58: =ROUNDUP(MAX($C$57:$N$57)*(1+Assumptions!$C$30),0) -> 141 | E58: =ROUNDUP(MAX($C$57:$N$57)*(1+Assumptions!$C$30),0) -> 141 | F58: =ROUNDUP(MAX($C$57:$N$57)*(1+Assumptions!$C$30),0) -> 141 | G58: =ROUNDUP(MAX($C$57:$N$57)*(1+Assumptions!$C$30),0) -> 141 | H58: =ROUNDUP(MAX($C$57:$N$57)*(1+Assumptions!$C$30),0) -> 141 | I58: =ROUNDUP(MAX($C$57:$N$57)*(1+Assumptions!$C$30),0) -> 141 | J58: =ROUNDUP(MAX($C$57:$N$57)*(1+Assumptions!$C$30),0) -> 141 | ... N58: =ROUNDUP(MAX($C$57:$N$57)*(1+Assumptions!$C$30),0) -> 141 | O58: =AVERAGE(C58:N58) -> 141
A59: Seat utilisation | B59: % | C59: =C57/C58 -> 0.56737589 | D59: =D57/D58 -> 0.62411348 | E59: =E57/E58 -> 0.60283688 | F59: =F57/F58 -> 0.58865248 | G59: =G57/G58 -> 0.58156028 | H59: =H57/H58 -> 0.62411348 | I59: =I57/I58 -> 0.68794326 | J59: =J57/J58 -> 0.70921986 | ... N59: =N57/N58 -> 0.87943262 | O59: =AVERAGE(C59:N59) -> 0.70330969

Sheet Erlang_Check
A1: Erlang C cross-check - is 78% voice occupancy consistent with the 80/20 service level?
A2: Bottom-up interval staffing for one month. Select a month in C5. Grid columns J:AH test N = ceiling(A)+k agents; required N is the first that meets 80/20.
B5: Selected month | C5: Nov-26
B6: Calls handled in month | C6: =INDEX(Topline_ExC!$C$13:$N$13,MATCH($C$5,Topline_ExC!$C$4:$N$4,0)) -> 518400
B7: Calendar days | C7: =INDEX(Topline_ExC!$C$7:$N$7,MATCH($C$5,Topline_ExC!$C$4:$N$4,0)) -> 30
B8: Calls per day | C8: =C6/C7 -> 17280
B9: AHT (sec) | C9: =Assumptions!$C$6 -> 75
B10: SL target | C10: =Assumptions!$C$8 -> 0.8
B11: SL threshold (sec) | C11: =Assumptions!$C$9 -> 20
J13: k (N = ceiling(A) + k) -> cell = N if SL(N) >= target else 9999
B14: Hour | C14: % of daily calls | D14: Calls in hour | E14: Traffic A (Erlangs) | F14: Required agents N | G14: SL achieved | H14: Occupancy A/N | J14: 1 | K14: 2 | L14: 3 | M14: 4 | N14: 5 | O14: 6 | P14: 7 | Q14: 8 | R14: 9 | S14: 10 | T14: 11 | U14: 12 | V14: 13 | W14: 14 | X14: 15 | Y14: 16 | Z14: 17 | AA14: 18 | AB14: 19 | AC14: 20 | AD14: 21 | AE14: 22 | AF14: 23 | AG14: 24 | AH14: 25
B15: 08:00-09:00 | C15: 0.04 | D15: =$C$8*C15 -> 691.2 | E15: =D15*$C$9/3600 -> 14.4 | F15: =MIN(J15:AH15) -> 18 | G15: =1-POISSON(F15,E15,FALSE())/(POISSON(F15,E15,FALSE())+(1-E15/F15)*POISSON(F15-1,E15,TRUE()))*EXP(-(F15-E15)*$C$11/$C$9) -> 0.8931881 | H15: =E15/F15 -> 0.8 | J15: =IF(1-POISSON((ROUNDUP($E15,0)+J$14),$E15,FALSE())/(POISSON((ROUNDUP($E15,0)+J$14),$E15,FALSE())+(1-$E15/(ROUNDUP($E15,0)+J$14))*POISSON((ROUNDUP($E15,0)+J$14)-1,$E15,TRUE()))*EXP(-((ROUNDUP($E15,0)+J$14)-$E15)*$C$11/$C$9)>=$C$10,(ROUNDUP($E15,0)+J$14),9999) -> 9999 | K15: =IF(1-POISSON((ROUNDUP($E15,0)+K$14),$E15,FALSE())/(POISSON((ROUNDUP($E15,0)+K$14),$E15,FALSE())+(1-$E15/(ROUNDUP($E15,0)+K$14))*POISSON((ROUNDUP($E15,0)+K$14)-1,$E15,TRUE()))*EXP(-((ROUNDUP($E15,0)+K$14)-$E15)*$C$11/$C$9)>=$C$10,(ROUNDUP($E15,0)+K$14),9999) -> 9999 | L15: =IF(1-POISSON((ROUNDUP($E15,0)+L$14),$E15,FALSE())/(POISSON((ROUNDUP($E15,0)+L$14),$E15,FALSE())+(1-$E15/(ROUNDUP($E15,0)+L$14))*POISSON((ROUNDUP($E15,0)+L$14)-1,$E15,TRUE()))*EXP(-((ROUNDUP($E15,0)+L$14)-$E15)*$C$11/$C$9)>=$C$10,(ROUNDUP($E15,0)+L$14),9999) -> 18 | M15: =IF(1-POISSON((ROUNDUP($E15,0)+M$14),$E15,FALSE())/(POISSON((ROUNDUP($E15,0)+M$14),$E15,FALSE())+(1-$E15/(ROUNDUP($E15,0)+M$14))*POISSON((ROUNDUP($E15,0)+M$14)-1,$E15,TRUE()))*EXP(-((ROUNDUP($E15,0)+M$14)-$E15)*$C$11/$C$9)>=$C$10,(ROUNDUP($E15,0)+M$14),9999) -> 19 | N15: =IF(1-POISSON((ROUNDUP($E15,0)+N$14),$E15,FALSE())/(POISSON((ROUNDUP($E15,0)+N$14),$E15,FALSE())+(1-$E15/(ROUNDUP($E15,0)+N$14))*POISSON((ROUNDUP($E15,0)+N$14)-1,$E15,TRUE()))*EXP(-((ROUNDUP($E15,0)+N$14)-$E15)*$C$11/$C$9)>=$C$10,(ROUNDUP($E15,0)+N$14),9999) -> 20 | O15: =IF(1-POISSON((ROUNDUP($E15,0)+O$14),$E15,FALSE())/(POISSON((ROUNDUP($E15,0)+O$14),$E15,FALSE())+(1-$E15/(ROUNDUP($E15,0)+O$14))*POISSON((ROUNDUP($E15,0)+O$14)-1,$E15,TRUE()))*EXP(-((ROUNDUP($E15,0)+O$14)-$E15)*$C$11/$C$9)>=$C$10,(ROUNDUP($E15,0)+O$14),9999) -> 21 | P15: =IF(1-POISSON((ROUNDUP($E15,0)+P$14),$E15,FALSE())/(POISSON((ROUNDUP($E15,0)+P$14),$E15,FALSE())+(1-$E15/(ROUNDUP($E15,0)+P$14))*POISSON((ROUNDUP($E15,0)+P$14)-1,$E15,TRUE()))*EXP(-((ROUNDUP($E15,0)+P$14)-$E15)*$C$11/$C$9)>=$C$10,(ROUNDUP($E15,0)+P$14),9999) -> 22 | Q15: =IF(1-POISSON((ROUNDUP($E15,0)+Q$14),$E15,FALSE())/(POISSON((ROUNDUP($E15,0)+Q$14),$E15,FALSE())+(1-$E15/(ROUNDUP($E15,0)+Q$14))*POISSON((ROUNDUP($E15,0)+Q$14)-1,$E15,TRUE()))*EXP(-((ROUNDUP($E15,0)+Q$14)-$E15)*$C$11/$C$9)>=$C$10,(ROUNDUP($E15,0)+Q$14),9999) -> 23 | ... AH15: =IF(1-POISSON((ROUNDUP($E15,0)+AH$14),$E15,FALSE())/(POISSON((ROUNDUP($E15,0)+AH$14),$E15,FALSE())+(1-$E15/(ROUNDUP($E15,0)+AH$14))*POISSON((ROUNDUP($E15,0)+AH$14)-1,$E15,TRUE()))*EXP(-((ROUNDUP($E15,0)+AH$14)-$E15)*$C$11/$C$9)>=$C$10,(ROUNDUP($E15,0)+AH$14),9999) -> 40
B16: 09:00-10:00 | C16: 0.05 | D16: =$C$8*C16 -> 864 | E16: =D16*$C$9/3600 -> 18 | F16: =MIN(J16:AH16) -> 21 | G16: =1-POISSON(F16,E16,FALSE())/(POISSON(F16,E16,FALSE())+(1-E16/F16)*POISSON(F16-1,E16,TRUE()))*EXP(-(F16-E16)*$C$11/$C$9) -> 0.82212345 | H16: =E16/F16 -> 0.85714286 | J16: =IF(1-POISSON((ROUNDUP($E16,0)+J$14),$E16,FALSE())/(POISSON((ROUNDUP($E16,0)+J$14),$E16,FALSE())+(1-$E16/(ROUNDUP($E16,0)+J$14))*POISSON((ROUNDUP($E16,0)+J$14)-1,$E16,TRUE()))*EXP(-((ROUNDUP($E16,0)+J$14)-$E16)*$C$11/$C$9)>=$C$10,(ROUNDUP($E16,0)+J$14),9999) -> 9999 | K16: =IF(1-POISSON((ROUNDUP($E16,0)+K$14),$E16,FALSE())/(POISSON((ROUNDUP($E16,0)+K$14),$E16,FALSE())+(1-$E16/(ROUNDUP($E16,0)+K$14))*POISSON((ROUNDUP($E16,0)+K$14)-1,$E16,TRUE()))*EXP(-((ROUNDUP($E16,0)+K$14)-$E16)*$C$11/$C$9)>=$C$10,(ROUNDUP($E16,0)+K$14),9999) -> 9999 | L16: =IF(1-POISSON((ROUNDUP($E16,0)+L$14),$E16,FALSE())/(POISSON((ROUNDUP($E16,0)+L$14),$E16,FALSE())+(1-$E16/(ROUNDUP($E16,0)+L$14))*POISSON((ROUNDUP($E16,0)+L$14)-1,$E16,TRUE()))*EXP(-((ROUNDUP($E16,0)+L$14)-$E16)*$C$11/$C$9)>=$C$10,(ROUNDUP($E16,0)+L$14),9999) -> 21 | M16: =IF(1-POISSON((ROUNDUP($E16,0)+M$14),$E16,FALSE())/(POISSON((ROUNDUP($E16,0)+M$14),$E16,FALSE())+(1-$E16/(ROUNDUP($E16,0)+M$14))*POISSON((ROUNDUP($E16,0)+M$14)-1,$E16,TRUE()))*EXP(-((ROUNDUP($E16,0)+M$14)-$E16)*$C$11/$C$9)>=$C$10,(ROUNDUP($E16,0)+M$14),9999) -> 22 | N16: =IF(1-POISSON((ROUNDUP($E16,0)+N$14),$E16,FALSE())/(POISSON((ROUNDUP($E16,0)+N$14),$E16,FALSE())+(1-$E16/(ROUNDUP($E16,0)+N$14))*POISSON((ROUNDUP($E16,0)+N$14)-1,$E16,TRUE()))*EXP(-((ROUNDUP($E16,0)+N$14)-$E16)*$C$11/$C$9)>=$C$10,(ROUNDUP($E16,0)+N$14),9999) -> 23 | O16: =IF(1-POISSON((ROUNDUP($E16,0)+O$14),$E16,FALSE())/(POISSON((ROUNDUP($E16,0)+O$14),$E16,FALSE())+(1-$E16/(ROUNDUP($E16,0)+O$14))*POISSON((ROUNDUP($E16,0)+O$14)-1,$E16,TRUE()))*EXP(-((ROUNDUP($E16,0)+O$14)-$E16)*$C$11/$C$9)>=$C$10,(ROUNDUP($E16,0)+O$14),9999) -> 24 | P16: =IF(1-POISSON((ROUNDUP($E16,0)+P$14),$E16,FALSE())/(POISSON((ROUNDUP($E16,0)+P$14),$E16,FALSE())+(1-$E16/(ROUNDUP($E16,0)+P$14))*POISSON((ROUNDUP($E16,0)+P$14)-1,$E16,TRUE()))*EXP(-((ROUNDUP($E16,0)+P$14)-$E16)*$C$11/$C$9)>=$C$10,(ROUNDUP($E16,0)+P$14),9999) -> 25 | Q16: =IF(1-POISSON((ROUNDUP($E16,0)+Q$14),$E16,FALSE())/(POISSON((ROUNDUP($E16,0)+Q$14),$E16,FALSE())+(1-$E16/(ROUNDUP($E16,0)+Q$14))*POISSON((ROUNDUP($E16,0)+Q$14)-1,$E16,TRUE()))*EXP(-((ROUNDUP($E16,0)+Q$14)-$E16)*$C$11/$C$9)>=$C$10,(ROUNDUP($E16,0)+Q$14),9999) -> 26 | ... AH16: =IF(1-POISSON((ROUNDUP($E16,0)+AH$14),$E16,FALSE())/(POISSON((ROUNDUP($E16,0)+AH$14),$E16,FALSE())+(1-$E16/(ROUNDUP($E16,0)+AH$14))*POISSON((ROUNDUP($E16,0)+AH$14)-1,$E16,TRUE()))*EXP(-((ROUNDUP($E16,0)+AH$14)-$E16)*$C$11/$C$9)>=$C$10,(ROUNDUP($E16,0)+AH$14),9999) -> 43
B17: 10:00-11:00 | C17: 0.065 | D17: =$C$8*C17 -> 1123.2 | E17: =D17*$C$9/3600 -> 23.4 | F17: =MIN(J17:AH17) -> 27 | G17: =1-POISSON(F17,E17,FALSE())/(POISSON(F17,E17,FALSE())+(1-E17/F17)*POISSON(F17-1,E17,TRUE()))*EXP(-(F17-E17)*$C$11/$C$9) -> 0.85772559 | H17: =E17/F17 -> 0.86666667 | J17: =IF(1-POISSON((ROUNDUP($E17,0)+J$14),$E17,FALSE())/(POISSON((ROUNDUP($E17,0)+J$14),$E17,FALSE())+(1-$E17/(ROUNDUP($E17,0)+J$14))*POISSON((ROUNDUP($E17,0)+J$14)-1,$E17,TRUE()))*EXP(-((ROUNDUP($E17,0)+J$14)-$E17)*$C$11/$C$9)>=$C$10,(ROUNDUP($E17,0)+J$14),9999) -> 9999 | K17: =IF(1-POISSON((ROUNDUP($E17,0)+K$14),$E17,FALSE())/(POISSON((ROUNDUP($E17,0)+K$14),$E17,FALSE())+(1-$E17/(ROUNDUP($E17,0)+K$14))*POISSON((ROUNDUP($E17,0)+K$14)-1,$E17,TRUE()))*EXP(-((ROUNDUP($E17,0)+K$14)-$E17)*$C$11/$C$9)>=$C$10,(ROUNDUP($E17,0)+K$14),9999) -> 9999 | L17: =IF(1-POISSON((ROUNDUP($E17,0)+L$14),$E17,FALSE())/(POISSON((ROUNDUP($E17,0)+L$14),$E17,FALSE())+(1-$E17/(ROUNDUP($E17,0)+L$14))*POISSON((ROUNDUP($E17,0)+L$14)-1,$E17,TRUE()))*EXP(-((ROUNDUP($E17,0)+L$14)-$E17)*$C$11/$C$9)>=$C$10,(ROUNDUP($E17,0)+L$14),9999) -> 27 | M17: =IF(1-POISSON((ROUNDUP($E17,0)+M$14),$E17,FALSE())/(POISSON((ROUNDUP($E17,0)+M$14),$E17,FALSE())+(1-$E17/(ROUNDUP($E17,0)+M$14))*POISSON((ROUNDUP($E17,0)+M$14)-1,$E17,TRUE()))*EXP(-((ROUNDUP($E17,0)+M$14)-$E17)*$C$11/$C$9)>=$C$10,(ROUNDUP($E17,0)+M$14),9999) -> 28 | N17: =IF(1-POISSON((ROUNDUP($E17,0)+N$14),$E17,FALSE())/(POISSON((ROUNDUP($E17,0)+N$14),$E17,FALSE())+(1-$E17/(ROUNDUP($E17,0)+N$14))*POISSON((ROUNDUP($E17,0)+N$14)-1,$E17,TRUE()))*EXP(-((ROUNDUP($E17,0)+N$14)-$E17)*$C$11/$C$9)>=$C$10,(ROUNDUP($E17,0)+N$14),9999) -> 29 | O17: =IF(1-POISSON((ROUNDUP($E17,0)+O$14),$E17,FALSE())/(POISSON((ROUNDUP($E17,0)+O$14),$E17,FALSE())+(1-$E17/(ROUNDUP($E17,0)+O$14))*POISSON((ROUNDUP($E17,0)+O$14)-1,$E17,TRUE()))*EXP(-((ROUNDUP($E17,0)+O$14)-$E17)*$C$11/$C$9)>=$C$10,(ROUNDUP($E17,0)+O$14),9999) -> 30 | P17: =IF(1-POISSON((ROUNDUP($E17,0)+P$14),$E17,FALSE())/(POISSON((ROUNDUP($E17,0)+P$14),$E17,FALSE())+(1-$E17/(ROUNDUP($E17,0)+P$14))*POISSON((ROUNDUP($E17,0)+P$14)-1,$E17,TRUE()))*EXP(-((ROUNDUP($E17,0)+P$14)-$E17)*$C$11/$C$9)>=$C$10,(ROUNDUP($E17,0)+P$14),9999) -> 31 | Q17: =IF(1-POISSON((ROUNDUP($E17,0)+Q$14),$E17,FALSE())/(POISSON((ROUNDUP($E17,0)+Q$14),$E17,FALSE())+(1-$E17/(ROUNDUP($E17,0)+Q$14))*POISSON((ROUNDUP($E17,0)+Q$14)-1,$E17,TRUE()))*EXP(-((ROUNDUP($E17,0)+Q$14)-$E17)*$C$11/$C$9)>=$C$10,(ROUNDUP($E17,0)+Q$14),9999) -> 32 | ... AH17: =IF(1-POISSON((ROUNDUP($E17,0)+AH$14),$E17,FALSE())/(POISSON((ROUNDUP($E17,0)+AH$14),$E17,FALSE())+(1-$E17/(ROUNDUP($E17,0)+AH$14))*POISSON((ROUNDUP($E17,0)+AH$14)-1,$E17,TRUE()))*EXP(-((ROUNDUP($E17,0)+AH$14)-$E17)*$C$11/$C$9)>=$C$10,(ROUNDUP($E17,0)+AH$14),9999) -> 49
B18: 11:00-12:00 | C18: 0.07 | D18: =$C$8*C18 -> 1209.6 | E18: =D18*$C$9/3600 -> 25.2 | F18: =MIN(J18:AH18) -> 29 | G18: =1-POISSON(F18,E18,FALSE())/(POISSON(F18,E18,FALSE())+(1-E18/F18)*POISSON(F18-1,E18,TRUE()))*EXP(-(F18-E18)*$C$11/$C$9) -> 0.86797915 | H18: =E18/F18 -> 0.86896552 | J18: =IF(1-POISSON((ROUNDUP($E18,0)+J$14),$E18,FALSE())/(POISSON((ROUNDUP($E18,0)+J$14),$E18,FALSE())+(1-$E18/(ROUNDUP($E18,0)+J$14))*POISSON((ROUNDUP($E18,0)+J$14)-1,$E18,TRUE()))*EXP(-((ROUNDUP($E18,0)+J$14)-$E18)*$C$11/$C$9)>=$C$10,(ROUNDUP($E18,0)+J$14),9999) -> 9999 | K18: =IF(1-POISSON((ROUNDUP($E18,0)+K$14),$E18,FALSE())/(POISSON((ROUNDUP($E18,0)+K$14),$E18,FALSE())+(1-$E18/(ROUNDUP($E18,0)+K$14))*POISSON((ROUNDUP($E18,0)+K$14)-1,$E18,TRUE()))*EXP(-((ROUNDUP($E18,0)+K$14)-$E18)*$C$11/$C$9)>=$C$10,(ROUNDUP($E18,0)+K$14),9999) -> 9999 | L18: =IF(1-POISSON((ROUNDUP($E18,0)+L$14),$E18,FALSE())/(POISSON((ROUNDUP($E18,0)+L$14),$E18,FALSE())+(1-$E18/(ROUNDUP($E18,0)+L$14))*POISSON((ROUNDUP($E18,0)+L$14)-1,$E18,TRUE()))*EXP(-((ROUNDUP($E18,0)+L$14)-$E18)*$C$11/$C$9)>=$C$10,(ROUNDUP($E18,0)+L$14),9999) -> 29 | M18: =IF(1-POISSON((ROUNDUP($E18,0)+M$14),$E18,FALSE())/(POISSON((ROUNDUP($E18,0)+M$14),$E18,FALSE())+(1-$E18/(ROUNDUP($E18,0)+M$14))*POISSON((ROUNDUP($E18,0)+M$14)-1,$E18,TRUE()))*EXP(-((ROUNDUP($E18,0)+M$14)-$E18)*$C$11/$C$9)>=$C$10,(ROUNDUP($E18,0)+M$14),9999) -> 30 | N18: =IF(1-POISSON((ROUNDUP($E18,0)+N$14),$E18,FALSE())/(POISSON((ROUNDUP($E18,0)+N$14),$E18,FALSE())+(1-$E18/(ROUNDUP($E18,0)+N$14))*POISSON((ROUNDUP($E18,0)+N$14)-1,$E18,TRUE()))*EXP(-((ROUNDUP($E18,0)+N$14)-$E18)*$C$11/$C$9)>=$C$10,(ROUNDUP($E18,0)+N$14),9999) -> 31 | O18: =IF(1-POISSON((ROUNDUP($E18,0)+O$14),$E18,FALSE())/(POISSON((ROUNDUP($E18,0)+O$14),$E18,FALSE())+(1-$E18/(ROUNDUP($E18,0)+O$14))*POISSON((ROUNDUP($E18,0)+O$14)-1,$E18,TRUE()))*EXP(-((ROUNDUP($E18,0)+O$14)-$E18)*$C$11/$C$9)>=$C$10,(ROUNDUP($E18,0)+O$14),9999) -> 32 | P18: =IF(1-POISSON((ROUNDUP($E18,0)+P$14),$E18,FALSE())/(POISSON((ROUNDUP($E18,0)+P$14),$E18,FALSE())+(1-$E18/(ROUNDUP($E18,0)+P$14))*POISSON((ROUNDUP($E18,0)+P$14)-1,$E18,TRUE()))*EXP(-((ROUNDUP($E18,0)+P$14)-$E18)*$C$11/$C$9)>=$C$10,(ROUNDUP($E18,0)+P$14),9999) -> 33 | Q18: =IF(1-POISSON((ROUNDUP($E18,0)+Q$14),$E18,FALSE())/(POISSON((ROUNDUP($E18,0)+Q$14),$E18,FALSE())+(1-$E18/(ROUNDUP($E18,0)+Q$14))*POISSON((ROUNDUP($E18,0)+Q$14)-1,$E18,TRUE()))*EXP(-((ROUNDUP($E18,0)+Q$14)-$E18)*$C$11/$C$9)>=$C$10,(ROUNDUP($E18,0)+Q$14),9999) -> 34 | ... AH18: =IF(1-POISSON((ROUNDUP($E18,0)+AH$14),$E18,FALSE())/(POISSON((ROUNDUP($E18,0)+AH$14),$E18,FALSE())+(1-$E18/(ROUNDUP($E18,0)+AH$14))*POISSON((ROUNDUP($E18,0)+AH$14)-1,$E18,TRUE()))*EXP(-((ROUNDUP($E18,0)+AH$14)-$E18)*$C$11/$C$9)>=$C$10,(ROUNDUP($E18,0)+AH$14),9999) -> 51
B19: 12:00-13:00 | C19: 0.075 | D19: =$C$8*C19 -> 1296 | E19: =D19*$C$9/3600 -> 27 | F19: =MIN(J19:AH19) -> 31 | G19: =1-POISSON(F19,E19,FALSE())/(POISSON(F19,E19,FALSE())+(1-E19/F19)*POISSON(F19-1,E19,TRUE()))*EXP(-(F19-E19)*$C$11/$C$9) -> 0.87749647 | H19: =E19/F19 -> 0.87096774 | J19: =IF(1-POISSON((ROUNDUP($E19,0)+J$14),$E19,FALSE())/(POISSON((ROUNDUP($E19,0)+J$14),$E19,FALSE())+(1-$E19/(ROUNDUP($E19,0)+J$14))*POISSON((ROUNDUP($E19,0)+J$14)-1,$E19,TRUE()))*EXP(-((ROUNDUP($E19,0)+J$14)-$E19)*$C$11/$C$9)>=$C$10,(ROUNDUP($E19,0)+J$14),9999) -> 9999 | K19: =IF(1-POISSON((ROUNDUP($E19,0)+K$14),$E19,FALSE())/(POISSON((ROUNDUP($E19,0)+K$14),$E19,FALSE())+(1-$E19/(ROUNDUP($E19,0)+K$14))*POISSON((ROUNDUP($E19,0)+K$14)-1,$E19,TRUE()))*EXP(-((ROUNDUP($E19,0)+K$14)-$E19)*$C$11/$C$9)>=$C$10,(ROUNDUP($E19,0)+K$14),9999) -> 9999 | L19: =IF(1-POISSON((ROUNDUP($E19,0)+L$14),$E19,FALSE())/(POISSON((ROUNDUP($E19,0)+L$14),$E19,FALSE())+(1-$E19/(ROUNDUP($E19,0)+L$14))*POISSON((ROUNDUP($E19,0)+L$14)-1,$E19,TRUE()))*EXP(-((ROUNDUP($E19,0)+L$14)-$E19)*$C$11/$C$9)>=$C$10,(ROUNDUP($E19,0)+L$14),9999) -> 9999 | M19: =IF(1-POISSON((ROUNDUP($E19,0)+M$14),$E19,FALSE())/(POISSON((ROUNDUP($E19,0)+M$14),$E19,FALSE())+(1-$E19/(ROUNDUP($E19,0)+M$14))*POISSON((ROUNDUP($E19,0)+M$14)-1,$E19,TRUE()))*EXP(-((ROUNDUP($E19,0)+M$14)-$E19)*$C$11/$C$9)>=$C$10,(ROUNDUP($E19,0)+M$14),9999) -> 31 | N19: =IF(1-POISSON((ROUNDUP($E19,0)+N$14),$E19,FALSE())/(POISSON((ROUNDUP($E19,0)+N$14),$E19,FALSE())+(1-$E19/(ROUNDUP($E19,0)+N$14))*POISSON((ROUNDUP($E19,0)+N$14)-1,$E19,TRUE()))*EXP(-((ROUNDUP($E19,0)+N$14)-$E19)*$C$11/$C$9)>=$C$10,(ROUNDUP($E19,0)+N$14),9999) -> 32 | O19: =IF(1-POISSON((ROUNDUP($E19,0)+O$14),$E19,FALSE())/(POISSON((ROUNDUP($E19,0)+O$14),$E19,FALSE())+(1-$E19/(ROUNDUP($E19,0)+O$14))*POISSON((ROUNDUP($E19,0)+O$14)-1,$E19,TRUE()))*EXP(-((ROUNDUP($E19,0)+O$14)-$E19)*$C$11/$C$9)>=$C$10,(ROUNDUP($E19,0)+O$14),9999) -> 33 | P19: =IF(1-POISSON((ROUNDUP($E19,0)+P$14),$E19,FALSE())/(POISSON((ROUNDUP($E19,0)+P$14),$E19,FALSE())+(1-$E19/(ROUNDUP($E19,0)+P$14))*POISSON((ROUNDUP($E19,0)+P$14)-1,$E19,TRUE()))*EXP(-((ROUNDUP($E19,0)+P$14)-$E19)*$C$11/$C$9)>=$C$10,(ROUNDUP($E19,0)+P$14),9999) -> 34 | Q19: =IF(1-POISSON((ROUNDUP($E19,0)+Q$14),$E19,FALSE())/(POISSON((ROUNDUP($E19,0)+Q$14),$E19,FALSE())+(1-$E19/(ROUNDUP($E19,0)+Q$14))*POISSON((ROUNDUP($E19,0)+Q$14)-1,$E19,TRUE()))*EXP(-((ROUNDUP($E19,0)+Q$14)-$E19)*$C$11/$C$9)>=$C$10,(ROUNDUP($E19,0)+Q$14),9999) -> 35 | ... AH19: =IF(1-POISSON((ROUNDUP($E19,0)+AH$14),$E19,FALSE())/(POISSON((ROUNDUP($E19,0)+AH$14),$E19,FALSE())+(1-$E19/(ROUNDUP($E19,0)+AH$14))*POISSON((ROUNDUP($E19,0)+AH$14)-1,$E19,TRUE()))*EXP(-((ROUNDUP($E19,0)+AH$14)-$E19)*$C$11/$C$9)>=$C$10,(ROUNDUP($E19,0)+AH$14),9999) -> 52
B20: 13:00-14:00 | C20: 0.075 | D20: =$C$8*C20 -> 1296 | E20: =D20*$C$9/3600 -> 27 | F20: =MIN(J20:AH20) -> 31 | G20: =1-POISSON(F20,E20,FALSE())/(POISSON(F20,E20,FALSE())+(1-E20/F20)*POISSON(F20-1,E20,TRUE()))*EXP(-(F20-E20)*$C$11/$C$9) -> 0.87749647 | H20: =E20/F20 -> 0.87096774 | J20: =IF(1-POISSON((ROUNDUP($E20,0)+J$14),$E20,FALSE())/(POISSON((ROUNDUP($E20,0)+J$14),$E20,FALSE())+(1-$E20/(ROUNDUP($E20,0)+J$14))*POISSON((ROUNDUP($E20,0)+J$14)-1,$E20,TRUE()))*EXP(-((ROUNDUP($E20,0)+J$14)-$E20)*$C$11/$C$9)>=$C$10,(ROUNDUP($E20,0)+J$14),9999) -> 9999 | K20: =IF(1-POISSON((ROUNDUP($E20,0)+K$14),$E20,FALSE())/(POISSON((ROUNDUP($E20,0)+K$14),$E20,FALSE())+(1-$E20/(ROUNDUP($E20,0)+K$14))*POISSON((ROUNDUP($E20,0)+K$14)-1,$E20,TRUE()))*EXP(-((ROUNDUP($E20,0)+K$14)-$E20)*$C$11/$C$9)>=$C$10,(ROUNDUP($E20,0)+K$14),9999) -> 9999 | L20: =IF(1-POISSON((ROUNDUP($E20,0)+L$14),$E20,FALSE())/(POISSON((ROUNDUP($E20,0)+L$14),$E20,FALSE())+(1-$E20/(ROUNDUP($E20,0)+L$14))*POISSON((ROUNDUP($E20,0)+L$14)-1,$E20,TRUE()))*EXP(-((ROUNDUP($E20,0)+L$14)-$E20)*$C$11/$C$9)>=$C$10,(ROUNDUP($E20,0)+L$14),9999) -> 9999 | M20: =IF(1-POISSON((ROUNDUP($E20,0)+M$14),$E20,FALSE())/(POISSON((ROUNDUP($E20,0)+M$14),$E20,FALSE())+(1-$E20/(ROUNDUP($E20,0)+M$14))*POISSON((ROUNDUP($E20,0)+M$14)-1,$E20,TRUE()))*EXP(-((ROUNDUP($E20,0)+M$14)-$E20)*$C$11/$C$9)>=$C$10,(ROUNDUP($E20,0)+M$14),9999) -> 31 | N20: =IF(1-POISSON((ROUNDUP($E20,0)+N$14),$E20,FALSE())/(POISSON((ROUNDUP($E20,0)+N$14),$E20,FALSE())+(1-$E20/(ROUNDUP($E20,0)+N$14))*POISSON((ROUNDUP($E20,0)+N$14)-1,$E20,TRUE()))*EXP(-((ROUNDUP($E20,0)+N$14)-$E20)*$C$11/$C$9)>=$C$10,(ROUNDUP($E20,0)+N$14),9999) -> 32 | O20: =IF(1-POISSON((ROUNDUP($E20,0)+O$14),$E20,FALSE())/(POISSON((ROUNDUP($E20,0)+O$14),$E20,FALSE())+(1-$E20/(ROUNDUP($E20,0)+O$14))*POISSON((ROUNDUP($E20,0)+O$14)-1,$E20,TRUE()))*EXP(-((ROUNDUP($E20,0)+O$14)-$E20)*$C$11/$C$9)>=$C$10,(ROUNDUP($E20,0)+O$14),9999) -> 33 | P20: =IF(1-POISSON((ROUNDUP($E20,0)+P$14),$E20,FALSE())/(POISSON((ROUNDUP($E20,0)+P$14),$E20,FALSE())+(1-$E20/(ROUNDUP($E20,0)+P$14))*POISSON((ROUNDUP($E20,0)+P$14)-1,$E20,TRUE()))*EXP(-((ROUNDUP($E20,0)+P$14)-$E20)*$C$11/$C$9)>=$C$10,(ROUNDUP($E20,0)+P$14),9999) -> 34 | Q20: =IF(1-POISSON((ROUNDUP($E20,0)+Q$14),$E20,FALSE())/(POISSON((ROUNDUP($E20,0)+Q$14),$E20,FALSE())+(1-$E20/(ROUNDUP($E20,0)+Q$14))*POISSON((ROUNDUP($E20,0)+Q$14)-1,$E20,TRUE()))*EXP(-((ROUNDUP($E20,0)+Q$14)-$E20)*$C$11/$C$9)>=$C$10,(ROUNDUP($E20,0)+Q$14),9999) -> 35 | ... AH20: =IF(1-POISSON((ROUNDUP($E20,0)+AH$14),$E20,FALSE())/(POISSON((ROUNDUP($E20,0)+AH$14),$E20,FALSE())+(1-$E20/(ROUNDUP($E20,0)+AH$14))*POISSON((ROUNDUP($E20,0)+AH$14)-1,$E20,TRUE()))*EXP(-((ROUNDUP($E20,0)+AH$14)-$E20)*$C$11/$C$9)>=$C$10,(ROUNDUP($E20,0)+AH$14),9999) -> 52
B21: 14:00-15:00 | C21: 0.065 | D21: =$C$8*C21 -> 1123.2 | E21: =D21*$C$9/3600 -> 23.4 | F21: =MIN(J21:AH21) -> 27 | G21: =1-POISSON(F21,E21,FALSE())/(POISSON(F21,E21,FALSE())+(1-E21/F21)*POISSON(F21-1,E21,TRUE()))*EXP(-(F21-E21)*$C$11/$C$9) -> 0.85772559 | H21: =E21/F21 -> 0.86666667 | J21: =IF(1-POISSON((ROUNDUP($E21,0)+J$14),$E21,FALSE())/(POISSON((ROUNDUP($E21,0)+J$14),$E21,FALSE())+(1-$E21/(ROUNDUP($E21,0)+J$14))*POISSON((ROUNDUP($E21,0)+J$14)-1,$E21,TRUE()))*EXP(-((ROUNDUP($E21,0)+J$14)-$E21)*$C$11/$C$9)>=$C$10,(ROUNDUP($E21,0)+J$14),9999) -> 9999 | K21: =IF(1-POISSON((ROUNDUP($E21,0)+K$14),$E21,FALSE())/(POISSON((ROUNDUP($E21,0)+K$14),$E21,FALSE())+(1-$E21/(ROUNDUP($E21,0)+K$14))*POISSON((ROUNDUP($E21,0)+K$14)-1,$E21,TRUE()))*EXP(-((ROUNDUP($E21,0)+K$14)-$E21)*$C$11/$C$9)>=$C$10,(ROUNDUP($E21,0)+K$14),9999) -> 9999 | L21: =IF(1-POISSON((ROUNDUP($E21,0)+L$14),$E21,FALSE())/(POISSON((ROUNDUP($E21,0)+L$14),$E21,FALSE())+(1-$E21/(ROUNDUP($E21,0)+L$14))*POISSON((ROUNDUP($E21,0)+L$14)-1,$E21,TRUE()))*EXP(-((ROUNDUP($E21,0)+L$14)-$E21)*$C$11/$C$9)>=$C$10,(ROUNDUP($E21,0)+L$14),9999) -> 27 | M21: =IF(1-POISSON((ROUNDUP($E21,0)+M$14),$E21,FALSE())/(POISSON((ROUNDUP($E21,0)+M$14),$E21,FALSE())+(1-$E21/(ROUNDUP($E21,0)+M$14))*POISSON((ROUNDUP($E21,0)+M$14)-1,$E21,TRUE()))*EXP(-((ROUNDUP($E21,0)+M$14)-$E21)*$C$11/$C$9)>=$C$10,(ROUNDUP($E21,0)+M$14),9999) -> 28 | N21: =IF(1-POISSON((ROUNDUP($E21,0)+N$14),$E21,FALSE())/(POISSON((ROUNDUP($E21,0)+N$14),$E21,FALSE())+(1-$E21/(ROUNDUP($E21,0)+N$14))*POISSON((ROUNDUP($E21,0)+N$14)-1,$E21,TRUE()))*EXP(-((ROUNDUP($E21,0)+N$14)-$E21)*$C$11/$C$9)>=$C$10,(ROUNDUP($E21,0)+N$14),9999) -> 29 | O21: =IF(1-POISSON((ROUNDUP($E21,0)+O$14),$E21,FALSE())/(POISSON((ROUNDUP($E21,0)+O$14),$E21,FALSE())+(1-$E21/(ROUNDUP($E21,0)+O$14))*POISSON((ROUNDUP($E21,0)+O$14)-1,$E21,TRUE()))*EXP(-((ROUNDUP($E21,0)+O$14)-$E21)*$C$11/$C$9)>=$C$10,(ROUNDUP($E21,0)+O$14),9999) -> 30 | P21: =IF(1-POISSON((ROUNDUP($E21,0)+P$14),$E21,FALSE())/(POISSON((ROUNDUP($E21,0)+P$14),$E21,FALSE())+(1-$E21/(ROUNDUP($E21,0)+P$14))*POISSON((ROUNDUP($E21,0)+P$14)-1,$E21,TRUE()))*EXP(-((ROUNDUP($E21,0)+P$14)-$E21)*$C$11/$C$9)>=$C$10,(ROUNDUP($E21,0)+P$14),9999) -> 31 | Q21: =IF(1-POISSON((ROUNDUP($E21,0)+Q$14),$E21,FALSE())/(POISSON((ROUNDUP($E21,0)+Q$14),$E21,FALSE())+(1-$E21/(ROUNDUP($E21,0)+Q$14))*POISSON((ROUNDUP($E21,0)+Q$14)-1,$E21,TRUE()))*EXP(-((ROUNDUP($E21,0)+Q$14)-$E21)*$C$11/$C$9)>=$C$10,(ROUNDUP($E21,0)+Q$14),9999) -> 32 | ... AH21: =IF(1-POISSON((ROUNDUP($E21,0)+AH$14),$E21,FALSE())/(POISSON((ROUNDUP($E21,0)+AH$14),$E21,FALSE())+(1-$E21/(ROUNDUP($E21,0)+AH$14))*POISSON((ROUNDUP($E21,0)+AH$14)-1,$E21,TRUE()))*EXP(-((ROUNDUP($E21,0)+AH$14)-$E21)*$C$11/$C$9)>=$C$10,(ROUNDUP($E21,0)+AH$14),9999) -> 49
B22: 15:00-16:00 | C22: 0.06 | D22: =$C$8*C22 -> 1036.8 | E22: =D22*$C$9/3600 -> 21.6 | F22: =MIN(J22:AH22) -> 25 | G22: =1-POISSON(F22,E22,FALSE())/(POISSON(F22,E22,FALSE())+(1-E22/F22)*POISSON(F22-1,E22,TRUE()))*EXP(-(F22-E22)*$C$11/$C$9) -> 0.84669057 | H22: =E22/F22 -> 0.864 | J22: =IF(1-POISSON((ROUNDUP($E22,0)+J$14),$E22,FALSE())/(POISSON((ROUNDUP($E22,0)+J$14),$E22,FALSE())+(1-$E22/(ROUNDUP($E22,0)+J$14))*POISSON((ROUNDUP($E22,0)+J$14)-1,$E22,TRUE()))*EXP(-((ROUNDUP($E22,0)+J$14)-$E22)*$C$11/$C$9)>=$C$10,(ROUNDUP($E22,0)+J$14),9999) -> 9999 | K22: =IF(1-POISSON((ROUNDUP($E22,0)+K$14),$E22,FALSE())/(POISSON((ROUNDUP($E22,0)+K$14),$E22,FALSE())+(1-$E22/(ROUNDUP($E22,0)+K$14))*POISSON((ROUNDUP($E22,0)+K$14)-1,$E22,TRUE()))*EXP(-((ROUNDUP($E22,0)+K$14)-$E22)*$C$11/$C$9)>=$C$10,(ROUNDUP($E22,0)+K$14),9999) -> 9999 | L22: =IF(1-POISSON((ROUNDUP($E22,0)+L$14),$E22,FALSE())/(POISSON((ROUNDUP($E22,0)+L$14),$E22,FALSE())+(1-$E22/(ROUNDUP($E22,0)+L$14))*POISSON((ROUNDUP($E22,0)+L$14)-1,$E22,TRUE()))*EXP(-((ROUNDUP($E22,0)+L$14)-$E22)*$C$11/$C$9)>=$C$10,(ROUNDUP($E22,0)+L$14),9999) -> 25 | M22: =IF(1-POISSON((ROUNDUP($E22,0)+M$14),$E22,FALSE())/(POISSON((ROUNDUP($E22,0)+M$14),$E22,FALSE())+(1-$E22/(ROUNDUP($E22,0)+M$14))*POISSON((ROUNDUP($E22,0)+M$14)-1,$E22,TRUE()))*EXP(-((ROUNDUP($E22,0)+M$14)-$E22)*$C$11/$C$9)>=$C$10,(ROUNDUP($E22,0)+M$14),9999) -> 26 | N22: =IF(1-POISSON((ROUNDUP($E22,0)+N$14),$E22,FALSE())/(POISSON((ROUNDUP($E22,0)+N$14),$E22,FALSE())+(1-$E22/(ROUNDUP($E22,0)+N$14))*POISSON((ROUNDUP($E22,0)+N$14)-1,$E22,TRUE()))*EXP(-((ROUNDUP($E22,0)+N$14)-$E22)*$C$11/$C$9)>=$C$10,(ROUNDUP($E22,0)+N$14),9999) -> 27 | O22: =IF(1-POISSON((ROUNDUP($E22,0)+O$14),$E22,FALSE())/(POISSON((ROUNDUP($E22,0)+O$14),$E22,FALSE())+(1-$E22/(ROUNDUP($E22,0)+O$14))*POISSON((ROUNDUP($E22,0)+O$14)-1,$E22,TRUE()))*EXP(-((ROUNDUP($E22,0)+O$14)-$E22)*$C$11/$C$9)>=$C$10,(ROUNDUP($E22,0)+O$14),9999) -> 28 | P22: =IF(1-POISSON((ROUNDUP($E22,0)+P$14),$E22,FALSE())/(POISSON((ROUNDUP($E22,0)+P$14),$E22,FALSE())+(1-$E22/(ROUNDUP($E22,0)+P$14))*POISSON((ROUNDUP($E22,0)+P$14)-1,$E22,TRUE()))*EXP(-((ROUNDUP($E22,0)+P$14)-$E22)*$C$11/$C$9)>=$C$10,(ROUNDUP($E22,0)+P$14),9999) -> 29 | Q22: =IF(1-POISSON((ROUNDUP($E22,0)+Q$14),$E22,FALSE())/(POISSON((ROUNDUP($E22,0)+Q$14),$E22,FALSE())+(1-$E22/(ROUNDUP($E22,0)+Q$14))*POISSON((ROUNDUP($E22,0)+Q$14)-1,$E22,TRUE()))*EXP(-((ROUNDUP($E22,0)+Q$14)-$E22)*$C$11/$C$9)>=$C$10,(ROUNDUP($E22,0)+Q$14),9999) -> 30 | ... AH22: =IF(1-POISSON((ROUNDUP($E22,0)+AH$14),$E22,FALSE())/(POISSON((ROUNDUP($E22,0)+AH$14),$E22,FALSE())+(1-$E22/(ROUNDUP($E22,0)+AH$14))*POISSON((ROUNDUP($E22,0)+AH$14)-1,$E22,TRUE()))*EXP(-((ROUNDUP($E22,0)+AH$14)-$E22)*$C$11/$C$9)>=$C$10,(ROUNDUP($E22,0)+AH$14),9999) -> 47
B23: 16:00-17:00 | C23: 0.06 | D23: =$C$8*C23 -> 1036.8 | E23: =D23*$C$9/3600 -> 21.6 | F23: =MIN(J23:AH23) -> 25 | G23: =1-POISSON(F23,E23,FALSE())/(POISSON(F23,E23,FALSE())+(1-E23/F23)*POISSON(F23-1,E23,TRUE()))*EXP(-(F23-E23)*$C$11/$C$9) -> 0.84669057 | H23: =E23/F23 -> 0.864 | J23: =IF(1-POISSON((ROUNDUP($E23,0)+J$14),$E23,FALSE())/(POISSON((ROUNDUP($E23,0)+J$14),$E23,FALSE())+(1-$E23/(ROUNDUP($E23,0)+J$14))*POISSON((ROUNDUP($E23,0)+J$14)-1,$E23,TRUE()))*EXP(-((ROUNDUP($E23,0)+J$14)-$E23)*$C$11/$C$9)>=$C$10,(ROUNDUP($E23,0)+J$14),9999) -> 9999 | K23: =IF(1-POISSON((ROUNDUP($E23,0)+K$14),$E23,FALSE())/(POISSON((ROUNDUP($E23,0)+K$14),$E23,FALSE())+(1-$E23/(ROUNDUP($E23,0)+K$14))*POISSON((ROUNDUP($E23,0)+K$14)-1,$E23,TRUE()))*EXP(-((ROUNDUP($E23,0)+K$14)-$E23)*$C$11/$C$9)>=$C$10,(ROUNDUP($E23,0)+K$14),9999) -> 9999 | L23: =IF(1-POISSON((ROUNDUP($E23,0)+L$14),$E23,FALSE())/(POISSON((ROUNDUP($E23,0)+L$14),$E23,FALSE())+(1-$E23/(ROUNDUP($E23,0)+L$14))*POISSON((ROUNDUP($E23,0)+L$14)-1,$E23,TRUE()))*EXP(-((ROUNDUP($E23,0)+L$14)-$E23)*$C$11/$C$9)>=$C$10,(ROUNDUP($E23,0)+L$14),9999) -> 25 | M23: =IF(1-POISSON((ROUNDUP($E23,0)+M$14),$E23,FALSE())/(POISSON((ROUNDUP($E23,0)+M$14),$E23,FALSE())+(1-$E23/(ROUNDUP($E23,0)+M$14))*POISSON((ROUNDUP($E23,0)+M$14)-1,$E23,TRUE()))*EXP(-((ROUNDUP($E23,0)+M$14)-$E23)*$C$11/$C$9)>=$C$10,(ROUNDUP($E23,0)+M$14),9999) -> 26 | N23: =IF(1-POISSON((ROUNDUP($E23,0)+N$14),$E23,FALSE())/(POISSON((ROUNDUP($E23,0)+N$14),$E23,FALSE())+(1-$E23/(ROUNDUP($E23,0)+N$14))*POISSON((ROUNDUP($E23,0)+N$14)-1,$E23,TRUE()))*EXP(-((ROUNDUP($E23,0)+N$14)-$E23)*$C$11/$C$9)>=$C$10,(ROUNDUP($E23,0)+N$14),9999) -> 27 | O23: =IF(1-POISSON((ROUNDUP($E23,0)+O$14),$E23,FALSE())/(POISSON((ROUNDUP($E23,0)+O$14),$E23,FALSE())+(1-$E23/(ROUNDUP($E23,0)+O$14))*POISSON((ROUNDUP($E23,0)+O$14)-1,$E23,TRUE()))*EXP(-((ROUNDUP($E23,0)+O$14)-$E23)*$C$11/$C$9)>=$C$10,(ROUNDUP($E23,0)+O$14),9999) -> 28 | P23: =IF(1-POISSON((ROUNDUP($E23,0)+P$14),$E23,FALSE())/(POISSON((ROUNDUP($E23,0)+P$14),$E23,FALSE())+(1-$E23/(ROUNDUP($E23,0)+P$14))*POISSON((ROUNDUP($E23,0)+P$14)-1,$E23,TRUE()))*EXP(-((ROUNDUP($E23,0)+P$14)-$E23)*$C$11/$C$9)>=$C$10,(ROUNDUP($E23,0)+P$14),9999) -> 29 | Q23: =IF(1-POISSON((ROUNDUP($E23,0)+Q$14),$E23,FALSE())/(POISSON((ROUNDUP($E23,0)+Q$14),$E23,FALSE())+(1-$E23/(ROUNDUP($E23,0)+Q$14))*POISSON((ROUNDUP($E23,0)+Q$14)-1,$E23,TRUE()))*EXP(-((ROUNDUP($E23,0)+Q$14)-$E23)*$C$11/$C$9)>=$C$10,(ROUNDUP($E23,0)+Q$14),9999) -> 30 | ... AH23: =IF(1-POISSON((ROUNDUP($E23,0)+AH$14),$E23,FALSE())/(POISSON((ROUNDUP($E23,0)+AH$14),$E23,FALSE())+(1-$E23/(ROUNDUP($E23,0)+AH$14))*POISSON((ROUNDUP($E23,0)+AH$14)-1,$E23,TRUE()))*EXP(-((ROUNDUP($E23,0)+AH$14)-$E23)*$C$11/$C$9)>=$C$10,(ROUNDUP($E23,0)+AH$14),9999) -> 47
B24: 17:00-18:00 | C24: 0.065 | D24: =$C$8*C24 -> 1123.2 | E24: =D24*$C$9/3600 -> 23.4 | F24: =MIN(J24:AH24) -> 27 | G24: =1-POISSON(F24,E24,FALSE())/(POISSON(F24,E24,FALSE())+(1-E24/F24)*POISSON(F24-1,E24,TRUE()))*EXP(-(F24-E24)*$C$11/$C$9) -> 0.85772559 | H24: =E24/F24 -> 0.86666667 | J24: =IF(1-POISSON((ROUNDUP($E24,0)+J$14),$E24,FALSE())/(POISSON((ROUNDUP($E24,0)+J$14),$E24,FALSE())+(1-$E24/(ROUNDUP($E24,0)+J$14))*POISSON((ROUNDUP($E24,0)+J$14)-1,$E24,TRUE()))*EXP(-((ROUNDUP($E24,0)+J$14)-$E24)*$C$11/$C$9)>=$C$10,(ROUNDUP($E24,0)+J$14),9999) -> 9999 | K24: =IF(1-POISSON((ROUNDUP($E24,0)+K$14),$E24,FALSE())/(POISSON((ROUNDUP($E24,0)+K$14),$E24,FALSE())+(1-$E24/(ROUNDUP($E24,0)+K$14))*POISSON((ROUNDUP($E24,0)+K$14)-1,$E24,TRUE()))*EXP(-((ROUNDUP($E24,0)+K$14)-$E24)*$C$11/$C$9)>=$C$10,(ROUNDUP($E24,0)+K$14),9999) -> 9999 | L24: =IF(1-POISSON((ROUNDUP($E24,0)+L$14),$E24,FALSE())/(POISSON((ROUNDUP($E24,0)+L$14),$E24,FALSE())+(1-$E24/(ROUNDUP($E24,0)+L$14))*POISSON((ROUNDUP($E24,0)+L$14)-1,$E24,TRUE()))*EXP(-((ROUNDUP($E24,0)+L$14)-$E24)*$C$11/$C$9)>=$C$10,(ROUNDUP($E24,0)+L$14),9999) -> 27 | M24: =IF(1-POISSON((ROUNDUP($E24,0)+M$14),$E24,FALSE())/(POISSON((ROUNDUP($E24,0)+M$14),$E24,FALSE())+(1-$E24/(ROUNDUP($E24,0)+M$14))*POISSON((ROUNDUP($E24,0)+M$14)-1,$E24,TRUE()))*EXP(-((ROUNDUP($E24,0)+M$14)-$E24)*$C$11/$C$9)>=$C$10,(ROUNDUP($E24,0)+M$14),9999) -> 28 | N24: =IF(1-POISSON((ROUNDUP($E24,0)+N$14),$E24,FALSE())/(POISSON((ROUNDUP($E24,0)+N$14),$E24,FALSE())+(1-$E24/(ROUNDUP($E24,0)+N$14))*POISSON((ROUNDUP($E24,0)+N$14)-1,$E24,TRUE()))*EXP(-((ROUNDUP($E24,0)+N$14)-$E24)*$C$11/$C$9)>=$C$10,(ROUNDUP($E24,0)+N$14),9999) -> 29 | O24: =IF(1-POISSON((ROUNDUP($E24,0)+O$14),$E24,FALSE())/(POISSON((ROUNDUP($E24,0)+O$14),$E24,FALSE())+(1-$E24/(ROUNDUP($E24,0)+O$14))*POISSON((ROUNDUP($E24,0)+O$14)-1,$E24,TRUE()))*EXP(-((ROUNDUP($E24,0)+O$14)-$E24)*$C$11/$C$9)>=$C$10,(ROUNDUP($E24,0)+O$14),9999) -> 30 | P24: =IF(1-POISSON((ROUNDUP($E24,0)+P$14),$E24,FALSE())/(POISSON((ROUNDUP($E24,0)+P$14),$E24,FALSE())+(1-$E24/(ROUNDUP($E24,0)+P$14))*POISSON((ROUNDUP($E24,0)+P$14)-1,$E24,TRUE()))*EXP(-((ROUNDUP($E24,0)+P$14)-$E24)*$C$11/$C$9)>=$C$10,(ROUNDUP($E24,0)+P$14),9999) -> 31 | Q24: =IF(1-POISSON((ROUNDUP($E24,0)+Q$14),$E24,FALSE())/(POISSON((ROUNDUP($E24,0)+Q$14),$E24,FALSE())+(1-$E24/(ROUNDUP($E24,0)+Q$14))*POISSON((ROUNDUP($E24,0)+Q$14)-1,$E24,TRUE()))*EXP(-((ROUNDUP($E24,0)+Q$14)-$E24)*$C$11/$C$9)>=$C$10,(ROUNDUP($E24,0)+Q$14),9999) -> 32 | ... AH24: =IF(1-POISSON((ROUNDUP($E24,0)+AH$14),$E24,FALSE())/(POISSON((ROUNDUP($E24,0)+AH$14),$E24,FALSE())+(1-$E24/(ROUNDUP($E24,0)+AH$14))*POISSON((ROUNDUP($E24,0)+AH$14)-1,$E24,TRUE()))*EXP(-((ROUNDUP($E24,0)+AH$14)-$E24)*$C$11/$C$9)>=$C$10,(ROUNDUP($E24,0)+AH$14),9999) -> 49
B25: 18:00-19:00 | C25: 0.07 | D25: =$C$8*C25 -> 1209.6 | E25: =D25*$C$9/3600 -> 25.2 | F25: =MIN(J25:AH25) -> 29 | G25: =1-POISSON(F25,E25,FALSE())/(POISSON(F25,E25,FALSE())+(1-E25/F25)*POISSON(F25-1,E25,TRUE()))*EXP(-(F25-E25)*$C$11/$C$9) -> 0.86797915 | H25: =E25/F25 -> 0.86896552 | J25: =IF(1-POISSON((ROUNDUP($E25,0)+J$14),$E25,FALSE())/(POISSON((ROUNDUP($E25,0)+J$14),$E25,FALSE())+(1-$E25/(ROUNDUP($E25,0)+J$14))*POISSON((ROUNDUP($E25,0)+J$14)-1,$E25,TRUE()))*EXP(-((ROUNDUP($E25,0)+J$14)-$E25)*$C$11/$C$9)>=$C$10,(ROUNDUP($E25,0)+J$14),9999) -> 9999 | K25: =IF(1-POISSON((ROUNDUP($E25,0)+K$14),$E25,FALSE())/(POISSON((ROUNDUP($E25,0)+K$14),$E25,FALSE())+(1-$E25/(ROUNDUP($E25,0)+K$14))*POISSON((ROUNDUP($E25,0)+K$14)-1,$E25,TRUE()))*EXP(-((ROUNDUP($E25,0)+K$14)-$E25)*$C$11/$C$9)>=$C$10,(ROUNDUP($E25,0)+K$14),9999) -> 9999 | L25: =IF(1-POISSON((ROUNDUP($E25,0)+L$14),$E25,FALSE())/(POISSON((ROUNDUP($E25,0)+L$14),$E25,FALSE())+(1-$E25/(ROUNDUP($E25,0)+L$14))*POISSON((ROUNDUP($E25,0)+L$14)-1,$E25,TRUE()))*EXP(-((ROUNDUP($E25,0)+L$14)-$E25)*$C$11/$C$9)>=$C$10,(ROUNDUP($E25,0)+L$14),9999) -> 29 | M25: =IF(1-POISSON((ROUNDUP($E25,0)+M$14),$E25,FALSE())/(POISSON((ROUNDUP($E25,0)+M$14),$E25,FALSE())+(1-$E25/(ROUNDUP($E25,0)+M$14))*POISSON((ROUNDUP($E25,0)+M$14)-1,$E25,TRUE()))*EXP(-((ROUNDUP($E25,0)+M$14)-$E25)*$C$11/$C$9)>=$C$10,(ROUNDUP($E25,0)+M$14),9999) -> 30 | N25: =IF(1-POISSON((ROUNDUP($E25,0)+N$14),$E25,FALSE())/(POISSON((ROUNDUP($E25,0)+N$14),$E25,FALSE())+(1-$E25/(ROUNDUP($E25,0)+N$14))*POISSON((ROUNDUP($E25,0)+N$14)-1,$E25,TRUE()))*EXP(-((ROUNDUP($E25,0)+N$14)-$E25)*$C$11/$C$9)>=$C$10,(ROUNDUP($E25,0)+N$14),9999) -> 31 | O25: =IF(1-POISSON((ROUNDUP($E25,0)+O$14),$E25,FALSE())/(POISSON((ROUNDUP($E25,0)+O$14),$E25,FALSE())+(1-$E25/(ROUNDUP($E25,0)+O$14))*POISSON((ROUNDUP($E25,0)+O$14)-1,$E25,TRUE()))*EXP(-((ROUNDUP($E25,0)+O$14)-$E25)*$C$11/$C$9)>=$C$10,(ROUNDUP($E25,0)+O$14),9999) -> 32 | P25: =IF(1-POISSON((ROUNDUP($E25,0)+P$14),$E25,FALSE())/(POISSON((ROUNDUP($E25,0)+P$14),$E25,FALSE())+(1-$E25/(ROUNDUP($E25,0)+P$14))*POISSON((ROUNDUP($E25,0)+P$14)-1,$E25,TRUE()))*EXP(-((ROUNDUP($E25,0)+P$14)-$E25)*$C$11/$C$9)>=$C$10,(ROUNDUP($E25,0)+P$14),9999) -> 33 | Q25: =IF(1-POISSON((ROUNDUP($E25,0)+Q$14),$E25,FALSE())/(POISSON((ROUNDUP($E25,0)+Q$14),$E25,FALSE())+(1-$E25/(ROUNDUP($E25,0)+Q$14))*POISSON((ROUNDUP($E25,0)+Q$14)-1,$E25,TRUE()))*EXP(-((ROUNDUP($E25,0)+Q$14)-$E25)*$C$11/$C$9)>=$C$10,(ROUNDUP($E25,0)+Q$14),9999) -> 34 | ... AH25: =IF(1-POISSON((ROUNDUP($E25,0)+AH$14),$E25,FALSE())/(POISSON((ROUNDUP($E25,0)+AH$14),$E25,FALSE())+(1-$E25/(ROUNDUP($E25,0)+AH$14))*POISSON((ROUNDUP($E25,0)+AH$14)-1,$E25,TRUE()))*EXP(-((ROUNDUP($E25,0)+AH$14)-$E25)*$C$11/$C$9)>=$C$10,(ROUNDUP($E25,0)+AH$14),9999) -> 51
B26: 19:00-20:00 | C26: 0.075 | D26: =$C$8*C26 -> 1296 | E26: =D26*$C$9/3600 -> 27 | F26: =MIN(J26:AH26) -> 31 | G26: =1-POISSON(F26,E26,FALSE())/(POISSON(F26,E26,FALSE())+(1-E26/F26)*POISSON(F26-1,E26,TRUE()))*EXP(-(F26-E26)*$C$11/$C$9) -> 0.87749647 | H26: =E26/F26 -> 0.87096774 | J26: =IF(1-POISSON((ROUNDUP($E26,0)+J$14),$E26,FALSE())/(POISSON((ROUNDUP($E26,0)+J$14),$E26,FALSE())+(1-$E26/(ROUNDUP($E26,0)+J$14))*POISSON((ROUNDUP($E26,0)+J$14)-1,$E26,TRUE()))*EXP(-((ROUNDUP($E26,0)+J$14)-$E26)*$C$11/$C$9)>=$C$10,(ROUNDUP($E26,0)+J$14),9999) -> 9999 | K26: =IF(1-POISSON((ROUNDUP($E26,0)+K$14),$E26,FALSE())/(POISSON((ROUNDUP($E26,0)+K$14),$E26,FALSE())+(1-$E26/(ROUNDUP($E26,0)+K$14))*POISSON((ROUNDUP($E26,0)+K$14)-1,$E26,TRUE()))*EXP(-((ROUNDUP($E26,0)+K$14)-$E26)*$C$11/$C$9)>=$C$10,(ROUNDUP($E26,0)+K$14),9999) -> 9999 | L26: =IF(1-POISSON((ROUNDUP($E26,0)+L$14),$E26,FALSE())/(POISSON((ROUNDUP($E26,0)+L$14),$E26,FALSE())+(1-$E26/(ROUNDUP($E26,0)+L$14))*POISSON((ROUNDUP($E26,0)+L$14)-1,$E26,TRUE()))*EXP(-((ROUNDUP($E26,0)+L$14)-$E26)*$C$11/$C$9)>=$C$10,(ROUNDUP($E26,0)+L$14),9999) -> 9999 | M26: =IF(1-POISSON((ROUNDUP($E26,0)+M$14),$E26,FALSE())/(POISSON((ROUNDUP($E26,0)+M$14),$E26,FALSE())+(1-$E26/(ROUNDUP($E26,0)+M$14))*POISSON((ROUNDUP($E26,0)+M$14)-1,$E26,TRUE()))*EXP(-((ROUNDUP($E26,0)+M$14)-$E26)*$C$11/$C$9)>=$C$10,(ROUNDUP($E26,0)+M$14),9999) -> 31 | N26: =IF(1-POISSON((ROUNDUP($E26,0)+N$14),$E26,FALSE())/(POISSON((ROUNDUP($E26,0)+N$14),$E26,FALSE())+(1-$E26/(ROUNDUP($E26,0)+N$14))*POISSON((ROUNDUP($E26,0)+N$14)-1,$E26,TRUE()))*EXP(-((ROUNDUP($E26,0)+N$14)-$E26)*$C$11/$C$9)>=$C$10,(ROUNDUP($E26,0)+N$14),9999) -> 32 | O26: =IF(1-POISSON((ROUNDUP($E26,0)+O$14),$E26,FALSE())/(POISSON((ROUNDUP($E26,0)+O$14),$E26,FALSE())+(1-$E26/(ROUNDUP($E26,0)+O$14))*POISSON((ROUNDUP($E26,0)+O$14)-1,$E26,TRUE()))*EXP(-((ROUNDUP($E26,0)+O$14)-$E26)*$C$11/$C$9)>=$C$10,(ROUNDUP($E26,0)+O$14),9999) -> 33 | P26: =IF(1-POISSON((ROUNDUP($E26,0)+P$14),$E26,FALSE())/(POISSON((ROUNDUP($E26,0)+P$14),$E26,FALSE())+(1-$E26/(ROUNDUP($E26,0)+P$14))*POISSON((ROUNDUP($E26,0)+P$14)-1,$E26,TRUE()))*EXP(-((ROUNDUP($E26,0)+P$14)-$E26)*$C$11/$C$9)>=$C$10,(ROUNDUP($E26,0)+P$14),9999) -> 34 | Q26: =IF(1-POISSON((ROUNDUP($E26,0)+Q$14),$E26,FALSE())/(POISSON((ROUNDUP($E26,0)+Q$14),$E26,FALSE())+(1-$E26/(ROUNDUP($E26,0)+Q$14))*POISSON((ROUNDUP($E26,0)+Q$14)-1,$E26,TRUE()))*EXP(-((ROUNDUP($E26,0)+Q$14)-$E26)*$C$11/$C$9)>=$C$10,(ROUNDUP($E26,0)+Q$14),9999) -> 35 | ... AH26: =IF(1-POISSON((ROUNDUP($E26,0)+AH$14),$E26,FALSE())/(POISSON((ROUNDUP($E26,0)+AH$14),$E26,FALSE())+(1-$E26/(ROUNDUP($E26,0)+AH$14))*POISSON((ROUNDUP($E26,0)+AH$14)-1,$E26,TRUE()))*EXP(-((ROUNDUP($E26,0)+AH$14)-$E26)*$C$11/$C$9)>=$C$10,(ROUNDUP($E26,0)+AH$14),9999) -> 52
... B30: 23:00-24:00 | C30: 0.04 | D30: =$C$8*C30 -> 691.2 | E30: =D30*$C$9/3600 -> 14.4 | F30: =MIN(J30:AH30) -> 18 | G30: =1-POISSON(F30,E30,FALSE())/(POISSON(F30,E30,FALSE())+(1-E30/F30)*POISSON(F30-1,E30,TRUE()))*EXP(-(F30-E30)*$C$11/$C$9) -> 0.8931881 | H30: =E30/F30 -> 0.8 | J30: =IF(1-POISSON((ROUNDUP($E30,0)+J$14),$E30,FALSE())/(POISSON((ROUNDUP($E30,0)+J$14),$E30,FALSE())+(1-$E30/(ROUNDUP($E30,0)+J$14))*POISSON((ROUNDUP($E30,0)+J$14)-1,$E30,TRUE()))*EXP(-((ROUNDUP($E30,0)+J$14)-$E30)*$C$11/$C$9)>=$C$10,(ROUNDUP($E30,0)+J$14),9999) -> 9999 | K30: =IF(1-POISSON((ROUNDUP($E30,0)+K$14),$E30,FALSE())/(POISSON((ROUNDUP($E30,0)+K$14),$E30,FALSE())+(1-$E30/(ROUNDUP($E30,0)+K$14))*POISSON((ROUNDUP($E30,0)+K$14)-1,$E30,TRUE()))*EXP(-((ROUNDUP($E30,0)+K$14)-$E30)*$C$11/$C$9)>=$C$10,(ROUNDUP($E30,0)+K$14),9999) -> 9999 | L30: =IF(1-POISSON((ROUNDUP($E30,0)+L$14),$E30,FALSE())/(POISSON((ROUNDUP($E30,0)+L$14),$E30,FALSE())+(1-$E30/(ROUNDUP($E30,0)+L$14))*POISSON((ROUNDUP($E30,0)+L$14)-1,$E30,TRUE()))*EXP(-((ROUNDUP($E30,0)+L$14)-$E30)*$C$11/$C$9)>=$C$10,(ROUNDUP($E30,0)+L$14),9999) -> 18 | M30: =IF(1-POISSON((ROUNDUP($E30,0)+M$14),$E30,FALSE())/(POISSON((ROUNDUP($E30,0)+M$14),$E30,FALSE())+(1-$E30/(ROUNDUP($E30,0)+M$14))*POISSON((ROUNDUP($E30,0)+M$14)-1,$E30,TRUE()))*EXP(-((ROUNDUP($E30,0)+M$14)-$E30)*$C$11/$C$9)>=$C$10,(ROUNDUP($E30,0)+M$14),9999) -> 19 | N30: =IF(1-POISSON((ROUNDUP($E30,0)+N$14),$E30,FALSE())/(POISSON((ROUNDUP($E30,0)+N$14),$E30,FALSE())+(1-$E30/(ROUNDUP($E30,0)+N$14))*POISSON((ROUNDUP($E30,0)+N$14)-1,$E30,TRUE()))*EXP(-((ROUNDUP($E30,0)+N$14)-$E30)*$C$11/$C$9)>=$C$10,(ROUNDUP($E30,0)+N$14),9999) -> 20 | O30: =IF(1-POISSON((ROUNDUP($E30,0)+O$14),$E30,FALSE())/(POISSON((ROUNDUP($E30,0)+O$14),$E30,FALSE())+(1-$E30/(ROUNDUP($E30,0)+O$14))*POISSON((ROUNDUP($E30,0)+O$14)-1,$E30,TRUE()))*EXP(-((ROUNDUP($E30,0)+O$14)-$E30)*$C$11/$C$9)>=$C$10,(ROUNDUP($E30,0)+O$14),9999) -> 21 | P30: =IF(1-POISSON((ROUNDUP($E30,0)+P$14),$E30,FALSE())/(POISSON((ROUNDUP($E30,0)+P$14),$E30,FALSE())+(1-$E30/(ROUNDUP($E30,0)+P$14))*POISSON((ROUNDUP($E30,0)+P$14)-1,$E30,TRUE()))*EXP(-((ROUNDUP($E30,0)+P$14)-$E30)*$C$11/$C$9)>=$C$10,(ROUNDUP($E30,0)+P$14),9999) -> 22 | Q30: =IF(1-POISSON((ROUNDUP($E30,0)+Q$14),$E30,FALSE())/(POISSON((ROUNDUP($E30,0)+Q$14),$E30,FALSE())+(1-$E30/(ROUNDUP($E30,0)+Q$14))*POISSON((ROUNDUP($E30,0)+Q$14)-1,$E30,TRUE()))*EXP(-((ROUNDUP($E30,0)+Q$14)-$E30)*$C$11/$C$9)>=$C$10,(ROUNDUP($E30,0)+Q$14),9999) -> 23 | ... AH30: =IF(1-POISSON((ROUNDUP($E30,0)+AH$14),$E30,FALSE())/(POISSON((ROUNDUP($E30,0)+AH$14),$E30,FALSE())+(1-$E30/(ROUNDUP($E30,0)+AH$14))*POISSON((ROUNDUP($E30,0)+AH$14)-1,$E30,TRUE()))*EXP(-((ROUNDUP($E30,0)+AH$14)-$E30)*$C$11/$C$9)>=$C$10,(ROUNDUP($E30,0)+AH$14),9999) -> 40
B31: Day total | C31: =SUM(C15:C30) -> 1 | D31: =SUM(D15:D30) -> 17280 | E31: =SUM(E15:E30) -> 360 | F31: =SUM(F15:F30) -> 418 | H31: =E31/F31 -> 0.86124402
B33: Erlang agent-hours on phones per day (sum of N) | C33: =F31 -> 418
B34: + schedule inefficiency allowance | C34: =F31*Assumptions!$C$32 -> 20.9
B35: Erlang-implied logged-in hours per day | C35: =C33+C34 -> 438.9
B36: Model logged-in voice hours per day (workload / 78%) | C36: =C6*C9/3600/Assumptions!$C$10/C7 -> 461.53846
B37: Erlang-implied occupancy (incl. schedule allowance) | C37: =E31/C35 -> 0.8202324
B38: Model occupancy assumption | C38: =Assumptions!$C$10 -> 0.78
B39: Model headroom vs Erlang need (+ = model staffs more) | C39: =C36/C35-1 -> 0.051579999
B41: Reading: at Helix volumes (25-35 Erlangs in peak hours) Erlang C needs only ~80-86% occupancy-equivalent staffing, so 78% is a prudent, slightly conservative planning rate. The gap is the prize for intraday scheduling / part-time peak shifts (Cost Program #3). Intraday profile is assumed (e-commerce/food-delivery shape with lunch and dinner peaks).

Sheet Costs
A1: Cost build - full cost stack
A2: People, recruitment & attrition, technology & telephony, facilities, management and corporate overhead. mln IRT.
A4: Line item | B4: Unit | C4: Jan-26 | D4: Feb-26 | E4: Mar-26 | F4: Apr-26 | G4: May-26 | H4: Jun-26 | I4: Jul-26 | J4: Aug-26 | K4: Sep-26 | L4: Oct-26 | M4: Nov-26 | N4: Dec-26 | O4: FY26 | P4: Basis / note
A5: INDICES
A6: Wage index | B6: index | C6: =Topline_ExC!C8 -> 1 | D6: =Topline_ExC!D8 -> 1 | E6: =Topline_ExC!E8 -> 1 | F6: =Topline_ExC!F8 -> 1.25 | G6: =Topline_ExC!G8 -> 1.25 | H6: =Topline_ExC!H8 -> 1.25 | I6: =Topline_ExC!I8 -> 1.25 | J6: =Topline_ExC!J8 -> 1.25 | ... N6: =Topline_ExC!N8 -> 1.25 | O6: =AVERAGE(C6:N6) -> 1.1875
A7: Non-payroll cost index | B7: index | C7: =Topline_ExC!C9 -> 1 | D7: =Topline_ExC!D9 -> 1 | E7: =Topline_ExC!E9 -> 1 | F7: =Topline_ExC!F9 -> 1.15 | G7: =Topline_ExC!G9 -> 1.15 | H7: =Topline_ExC!H9 -> 1.15 | I7: =Topline_ExC!I9 -> 1.15 | J7: =Topline_ExC!J9 -> 1.15 | ... N7: =Topline_ExC!N9 -> 1.15 | O7: =AVERAGE(C7:N7) -> 1.1125
A8: LOADED COST PER HEAD (gross x 1.22 on-costs x wage index) - mln IRT / month
A9: Agent | B9: mln / FTE | C9: =Assumptions!$C$34*(1+Assumptions!$C$40)*C6 -> 61 | D9: =Assumptions!$C$34*(1+Assumptions!$C$40)*D6 -> 61 | E9: =Assumptions!$C$34*(1+Assumptions!$C$40)*E6 -> 61 | F9: =Assumptions!$C$34*(1+Assumptions!$C$40)*F6 -> 76.25 | G9: =Assumptions!$C$34*(1+Assumptions!$C$40)*G6 -> 76.25 | H9: =Assumptions!$C$34*(1+Assumptions!$C$40)*H6 -> 76.25 | I9: =Assumptions!$C$34*(1+Assumptions!$C$40)*I6 -> 76.25 | J9: =Assumptions!$C$34*(1+Assumptions!$C$40)*J6 -> 76.25 | ... N9: =Assumptions!$C$34*(1+Assumptions!$C$40)*N6 -> 76.25 | O9: =AVERAGE(C9:N9) -> 72.4375
A10: Team leader | B10: mln / FTE | C10: =Assumptions!$C$35*(1+Assumptions!$C$40)*C6 -> 122 | D10: =Assumptions!$C$35*(1+Assumptions!$C$40)*D6 -> 122 | E10: =Assumptions!$C$35*(1+Assumptions!$C$40)*E6 -> 122 | F10: =Assumptions!$C$35*(1+Assumptions!$C$40)*F6 -> 152.5 | G10: =Assumptions!$C$35*(1+Assumptions!$C$40)*G6 -> 152.5 | H10: =Assumptions!$C$35*(1+Assumptions!$C$40)*H6 -> 152.5 | I10: =Assumptions!$C$35*(1+Assumptions!$C$40)*I6 -> 152.5 | J10: =Assumptions!$C$35*(1+Assumptions!$C$40)*J6 -> 152.5 | ... N10: =Assumptions!$C$35*(1+Assumptions!$C$40)*N6 -> 152.5 | O10: =AVERAGE(C10:N10) -> 144.875
A11: Quality analyst | B11: mln / FTE | C11: =Assumptions!$C$36*(1+Assumptions!$C$40)*C6 -> 48.8 | D11: =Assumptions!$C$36*(1+Assumptions!$C$40)*D6 -> 48.8 | E11: =Assumptions!$C$36*(1+Assumptions!$C$40)*E6 -> 48.8 | F11: =Assumptions!$C$36*(1+Assumptions!$C$40)*F6 -> 61 | G11: =Assumptions!$C$36*(1+Assumptions!$C$40)*G6 -> 61 | H11: =Assumptions!$C$36*(1+Assumptions!$C$40)*H6 -> 61 | I11: =Assumptions!$C$36*(1+Assumptions!$C$40)*I6 -> 61 | J11: =Assumptions!$C$36*(1+Assumptions!$C$40)*J6 -> 61 | ... N11: =Assumptions!$C$36*(1+Assumptions!$C$40)*N6 -> 61 | O11: =AVERAGE(C11:N11) -> 57.95
A12: Operations manager | B12: mln / FTE | C12: =Assumptions!$C$37*(1+Assumptions!$C$40)*C6 -> 183 | D12: =Assumptions!$C$37*(1+Assumptions!$C$40)*D6 -> 183 | E12: =Assumptions!$C$37*(1+Assumptions!$C$40)*E6 -> 183 | F12: =Assumptions!$C$37*(1+Assumptions!$C$40)*F6 -> 228.75 | G12: =Assumptions!$C$37*(1+Assumptions!$C$40)*G6 -> 228.75 | H12: =Assumptions!$C$37*(1+Assumptions!$C$40)*H6 -> 228.75 | I12: =Assumptions!$C$37*(1+Assumptions!$C$40)*I6 -> 228.75 | J12: =Assumptions!$C$37*(1+Assumptions!$C$40)*J6 -> 228.75 | ... N12: =Assumptions!$C$37*(1+Assumptions!$C$40)*N6 -> 228.75 | O12: =AVERAGE(C12:N12) -> 217.3125
A13: WFM analyst | B13: mln / FTE | C13: =Assumptions!$C$45*(1+Assumptions!$C$40)*C6 -> 85.4 | D13: =Assumptions!$C$45*(1+Assumptions!$C$40)*D6 -> 85.4 | E13: =Assumptions!$C$45*(1+Assumptions!$C$40)*E6 -> 85.4 | F13: =Assumptions!$C$45*(1+Assumptions!$C$40)*F6 -> 106.75 | G13: =Assumptions!$C$45*(1+Assumptions!$C$40)*G6 -> 106.75 | H13: =Assumptions!$C$45*(1+Assumptions!$C$40)*H6 -> 106.75 | I13: =Assumptions!$C$45*(1+Assumptions!$C$40)*I6 -> 106.75 | J13: =Assumptions!$C$45*(1+Assumptions!$C$40)*J6 -> 106.75 | ... N13: =Assumptions!$C$45*(1+Assumptions!$C$40)*N6 -> 106.75 | O13: =AVERAGE(C13:N13) -> 101.4125
A14: Trainer | B14: mln / FTE | C14: =Assumptions!$C$46*(1+Assumptions!$C$40)*C6 -> 73.2 | D14: =Assumptions!$C$46*(1+Assumptions!$C$40)*D6 -> 73.2 | E14: =Assumptions!$C$46*(1+Assumptions!$C$40)*E6 -> 73.2 | F14: =Assumptions!$C$46*(1+Assumptions!$C$40)*F6 -> 91.5 | G14: =Assumptions!$C$46*(1+Assumptions!$C$40)*G6 -> 91.5 | H14: =Assumptions!$C$46*(1+Assumptions!$C$40)*H6 -> 91.5 | I14: =Assumptions!$C$46*(1+Assumptions!$C$40)*I6 -> 91.5 | J14: =Assumptions!$C$46*(1+Assumptions!$C$40)*J6 -> 91.5 | ... N14: =Assumptions!$C$46*(1+Assumptions!$C$40)*N6 -> 91.5 | O14: =AVERAGE(C14:N14) -> 86.925
A15: IT / MIS support | B15: mln / FTE | C15: =Assumptions!$C$47*(1+Assumptions!$C$40)*C6 -> 97.6 | D15: =Assumptions!$C$47*(1+Assumptions!$C$40)*D6 -> 97.6 | E15: =Assumptions!$C$47*(1+Assumptions!$C$40)*E6 -> 97.6 | F15: =Assumptions!$C$47*(1+Assumptions!$C$40)*F6 -> 122 | G15: =Assumptions!$C$47*(1+Assumptions!$C$40)*G6 -> 122 | H15: =Assumptions!$C$47*(1+Assumptions!$C$40)*H6 -> 122 | I15: =Assumptions!$C$47*(1+Assumptions!$C$40)*I6 -> 122 | J15: =Assumptions!$C$47*(1+Assumptions!$C$40)*J6 -> 122 | ... N15: =Assumptions!$C$47*(1+Assumptions!$C$40)*N6 -> 122 | O15: =AVERAGE(C15:N15) -> 115.9
A16: HR / recruitment / admin | B16: mln / FTE | C16: =Assumptions!$C$48*(1+Assumptions!$C$40)*C6 -> 54.9 | D16: =Assumptions!$C$48*(1+Assumptions!$C$40)*D6 -> 54.9 | E16: =Assumptions!$C$48*(1+Assumptions!$C$40)*E6 -> 54.9 | F16: =Assumptions!$C$48*(1+Assumptions!$C$40)*F6 -> 68.625 | G16: =Assumptions!$C$48*(1+Assumptions!$C$40)*G6 -> 68.625 | H16: =Assumptions!$C$48*(1+Assumptions!$C$40)*H6 -> 68.625 | I16: =Assumptions!$C$48*(1+Assumptions!$C$40)*I6 -> 68.625 | J16: =Assumptions!$C$48*(1+Assumptions!$C$40)*J6 -> 68.625 | ... N16: =Assumptions!$C$48*(1+Assumptions!$C$40)*N6 -> 68.625 | O16: =AVERAGE(C16:N16) -> 65.19375
A17: Site director | B17: mln / FTE | C17: =Assumptions!$C$38*(1+Assumptions!$C$40)*C6 -> 244 | D17: =Assumptions!$C$38*(1+Assumptions!$C$40)*D6 -> 244 | E17: =Assumptions!$C$38*(1+Assumptions!$C$40)*E6 -> 244 | F17: =Assumptions!$C$38*(1+Assumptions!$C$40)*F6 -> 305 | G17: =Assumptions!$C$38*(1+Assumptions!$C$40)*G6 -> 305 | H17: =Assumptions!$C$38*(1+Assumptions!$C$40)*H6 -> 305 | I17: =Assumptions!$C$38*(1+Assumptions!$C$40)*I6 -> 305 | J17: =Assumptions!$C$38*(1+Assumptions!$C$40)*J6 -> 305 | ... N17: =Assumptions!$C$38*(1+Assumptions!$C$40)*N6 -> 305 | O17: =AVERAGE(C17:N17) -> 289.75
A18: Finance / HR BP | B18: mln / FTE | C18: =Assumptions!$C$39*(1+Assumptions!$C$40)*C6 -> 183 | D18: =Assumptions!$C$39*(1+Assumptions!$C$40)*D6 -> 183 | E18: =Assumptions!$C$39*(1+Assumptions!$C$40)*E6 -> 183 | F18: =Assumptions!$C$39*(1+Assumptions!$C$40)*F6 -> 228.75 | G18: =Assumptions!$C$39*(1+Assumptions!$C$40)*G6 -> 228.75 | H18: =Assumptions!$C$39*(1+Assumptions!$C$40)*H6 -> 228.75 | I18: =Assumptions!$C$39*(1+Assumptions!$C$40)*I6 -> 228.75 | J18: =Assumptions!$C$39*(1+Assumptions!$C$40)*J6 -> 228.75 | ... N18: =Assumptions!$C$39*(1+Assumptions!$C$40)*N6 -> 228.75 | O18: =AVERAGE(C18:N18) -> 217.3125
A19: Account manager | B19: mln / FTE | C19: =Assumptions!$C$49*(1+Assumptions!$C$40)*C6 -> 146.4 | D19: =Assumptions!$C$49*(1+Assumptions!$C$40)*D6 -> 146.4 | E19: =Assumptions!$C$49*(1+Assumptions!$C$40)*E6 -> 146.4 | F19: =Assumptions!$C$49*(1+Assumptions!$C$40)*F6 -> 183 | G19: =Assumptions!$C$49*(1+Assumptions!$C$40)*G6 -> 183 | H19: =Assumptions!$C$49*(1+Assumptions!$C$40)*H6 -> 183 | I19: =Assumptions!$C$49*(1+Assumptions!$C$40)*I6 -> 183 | J19: =Assumptions!$C$49*(1+Assumptions!$C$40)*J6 -> 183 | ... N19: =Assumptions!$C$49*(1+Assumptions!$C$40)*N6 -> 183 | O19: =AVERAGE(C19:N19) -> 173.85
A20: Overtime - loaded cost per hour | B20: mln / hour | C20: =Assumptions!$C$43*(1+Assumptions!$C$40)*C6 -> 0.61 | D20: =Assumptions!$C$43*(1+Assumptions!$C$40)*D6 -> 0.61 | E20: =Assumptions!$C$43*(1+Assumptions!$C$40)*E6 -> 0.61 | F20: =Assumptions!$C$43*(1+Assumptions!$C$40)*F6 -> 0.7625 | G20: =Assumptions!$C$43*(1+Assumptions!$C$40)*G6 -> 0.7625 | H20: =Assumptions!$C$43*(1+Assumptions!$C$40)*H6 -> 0.7625 | I20: =Assumptions!$C$43*(1+Assumptions!$C$40)*I6 -> 0.7625 | J20: =Assumptions!$C$43*(1+Assumptions!$C$40)*J6 -> 0.7625 | ... N20: =Assumptions!$C$43*(1+Assumptions!$C$40)*N6 -> 0.7625 | O20: =AVERAGE(C20:N20) -> 0.724375
A21: 1. FRONT-LINE PEOPLE COST - mln IRT
A22: Agent payroll - productive requirement | B22: mln IRT | C22: =Capacity_ExD!C31*C9 -> 5226.9351 | D22: =Capacity_ExD!D31*D9 -> 5797.0633 | E22: =Capacity_ExD!E31*E9 -> 4587.2513 | F22: =Capacity_ExD!F31*F9 -> 6196.5806 | G22: =Capacity_ExD!G31*G9 -> 6584.9804 | H22: =Capacity_ExD!H31*H9 -> 7287.6634 | I22: =Capacity_ExD!I31*I9 -> 8138.5797 | J22: =Capacity_ExD!J31*J9 -> 8526.9795 | ... N22: =Capacity_ExD!N31*N9 -> 10673.512 | O22: =SUM(C22:N22) -> 94505.23 | P22: Required FTE x loaded cost
A23: Agent payroll - surplus / idle capacity | B23: mln IRT | C23: =Capacity_ExD!C37*C9 -> 0 | D23: =Capacity_ExD!D37*D9 -> 0 | E23: =Capacity_ExD!E37*E9 -> 977.92945 | F23: =Capacity_ExD!F37*F9 -> 481.6363 | G23: =Capacity_ExD!G37*G9 -> 0 | H23: =Capacity_ExD!H37*H9 -> 0 | I23: =Capacity_ExD!I37*I9 -> 0 | J23: =Capacity_ExD!J37*J9 -> 0 | ... N23: =Capacity_ExD!N37*N9 -> 152.53779 | O23: =SUM(C23:N23) -> 1612.1035 | P23: Cost of the no-layoff policy
A24: Overtime | B24: mln IRT | C24: =Capacity_ExD!C25*C20 -> 161.04 | D24: =Capacity_ExD!D25*D20 -> 178.52667 | E24: =Capacity_ExD!E25*E20 -> 141.215 | F24: =Capacity_ExD!F25*F20 -> 190.94271 | G24: =Capacity_ExD!G25*G20 -> 202.825 | H24: =Capacity_ExD!H25*H20 -> 224.04792 | I24: =Capacity_ExD!I25*I20 -> 250.35417 | J24: =Capacity_ExD!J25*J20 -> 262.23646 | ... N24: =Capacity_ExD!N25*N20 -> 330.09896 | O24: =SUM(C24:N24) -> 2913.3155
A25: Team leaders | B25: mln IRT | C25: =Capacity_ExD!C41*C10 -> 732 | D25: =Capacity_ExD!D41*D10 -> 854 | E25: =Capacity_ExD!E41*E10 -> 854 | F25: =Capacity_ExD!F41*F10 -> 1067.5 | G25: =Capacity_ExD!G41*G10 -> 1067.5 | H25: =Capacity_ExD!H41*H10 -> 1067.5 | I25: =Capacity_ExD!I41*I10 -> 1220 | J25: =Capacity_ExD!J41*J10 -> 1220 | ... N25: =Capacity_ExD!N41*N10 -> 1525 | O25: =SUM(C25:N25) -> 14030
A26: Quality analysts | B26: mln IRT | C26: =Capacity_ExD!C43*C11 -> 146.4 | D26: =Capacity_ExD!D43*D11 -> 146.4 | E26: =Capacity_ExD!E43*E11 -> 146.4 | F26: =Capacity_ExD!F43*F11 -> 183 | G26: =Capacity_ExD!G43*G11 -> 183 | H26: =Capacity_ExD!H43*H11 -> 183 | I26: =Capacity_ExD!I43*I11 -> 183 | J26: =Capacity_ExD!J43*J11 -> 183 | ... N26: =Capacity_ExD!N43*N11 -> 244 | O26: =SUM(C26:N26) -> 2330.2
A27: Total front-line people cost | B27: mln IRT | C27: =SUM(C22:C26) -> 6266.3751 | D27: =SUM(D22:D26) -> 6975.9899 | E27: =SUM(E22:E26) -> 6706.7957 | F27: =SUM(F22:F26) -> 8119.6596 | G27: =SUM(G22:G26) -> 8038.3054 | H27: =SUM(H22:H26) -> 8762.2113 | I27: =SUM(I22:I26) -> 9791.9339 | J27: =SUM(J22:J26) -> 10192.216 | ... N27: =SUM(N22:N26) -> 12925.149 | O27: =SUM(C27:N27) -> 115390.85
A28: 2. OPERATIONS SUPPORT & MANAGEMENT - mln IRT
A29: Operations managers | B29: mln IRT | C29: =Capacity_ExD!C42*C12 -> 183 | D29: =Capacity_ExD!D42*D12 -> 366 | E29: =Capacity_ExD!E42*E12 -> 366 | F29: =Capacity_ExD!F42*F12 -> 457.5 | G29: =Capacity_ExD!G42*G12 -> 457.5 | H29: =Capacity_ExD!H42*H12 -> 457.5 | I29: =Capacity_ExD!I42*I12 -> 457.5 | J29: =Capacity_ExD!J42*J12 -> 457.5 | ... N29: =Capacity_ExD!N42*N12 -> 457.5 | O29: =SUM(C29:N29) -> 5032.5
A30: Workforce management | B30: mln IRT | C30: =Capacity_ExD!C44*C13 -> 170.8 | D30: =Capacity_ExD!D44*D13 -> 170.8 | E30: =Capacity_ExD!E44*E13 -> 170.8 | F30: =Capacity_ExD!F44*F13 -> 213.5 | G30: =Capacity_ExD!G44*G13 -> 213.5 | H30: =Capacity_ExD!H44*H13 -> 213.5 | I30: =Capacity_ExD!I44*I13 -> 213.5 | J30: =Capacity_ExD!J44*J13 -> 213.5 | ... N30: =Capacity_ExD!N44*N13 -> 213.5 | O30: =SUM(C30:N30) -> 2433.9
A31: Training team | B31: mln IRT | C31: =Capacity_ExD!C45*C14 -> 146.4 | D31: =Capacity_ExD!D45*D14 -> 146.4 | E31: =Capacity_ExD!E45*E14 -> 146.4 | F31: =Capacity_ExD!F45*F14 -> 183 | G31: =Capacity_ExD!G45*G14 -> 183 | H31: =Capacity_ExD!H45*H14 -> 183 | I31: =Capacity_ExD!I45*I14 -> 183 | J31: =Capacity_ExD!J45*J14 -> 183 | ... N31: =Capacity_ExD!N45*N14 -> 274.5 | O31: =SUM(C31:N31) -> 2452.2
A32: IT / MIS support | B32: mln IRT | C32: =Capacity_ExD!C46*C15 -> 195.2 | D32: =Capacity_ExD!D46*D15 -> 195.2 | E32: =Capacity_ExD!E46*E15 -> 195.2 | F32: =Capacity_ExD!F46*F15 -> 244 | G32: =Capacity_ExD!G46*G15 -> 244 | H32: =Capacity_ExD!H46*H15 -> 244 | I32: =Capacity_ExD!I46*I15 -> 244 | J32: =Capacity_ExD!J46*J15 -> 244 | ... N32: =Capacity_ExD!N46*N15 -> 244 | O32: =SUM(C32:N32) -> 2781.6
A33: HR, recruitment & admin team | B33: mln IRT | C33: =Capacity_ExD!C47*C16 -> 109.8 | D33: =Capacity_ExD!D47*D16 -> 109.8 | E33: =Capacity_ExD!E47*E16 -> 109.8 | F33: =Capacity_ExD!F47*F16 -> 137.25 | G33: =Capacity_ExD!G47*G16 -> 137.25 | H33: =Capacity_ExD!H47*H16 -> 137.25 | I33: =Capacity_ExD!I47*I16 -> 137.25 | J33: =Capacity_ExD!J47*J16 -> 137.25 | ... N33: =Capacity_ExD!N47*N16 -> 137.25 | O33: =SUM(C33:N33) -> 1564.65
A34: Site leadership (director + finance/HR BP) | B34: mln IRT | C34: =Capacity_ExD!C48*C17+Capacity_ExD!C49*C18 -> 427 | D34: =Capacity_ExD!D48*D17+Capacity_ExD!D49*D18 -> 427 | E34: =Capacity_ExD!E48*E17+Capacity_ExD!E49*E18 -> 427 | F34: =Capacity_ExD!F48*F17+Capacity_ExD!F49*F18 -> 533.75 | G34: =Capacity_ExD!G48*G17+Capacity_ExD!G49*G18 -> 533.75 | H34: =Capacity_ExD!H48*H17+Capacity_ExD!H49*H18 -> 533.75 | I34: =Capacity_ExD!I48*I17+Capacity_ExD!I49*I18 -> 533.75 | J34: =Capacity_ExD!J48*J17+Capacity_ExD!J49*J18 -> 533.75 | ... N34: =Capacity_ExD!N48*N17+Capacity_ExD!N49*N18 -> 533.75 | O34: =SUM(C34:N34) -> 6084.75
A35: Account management | B35: mln IRT | C35: =Capacity_ExD!C50*C19 -> 292.8 | D35: =Capacity_ExD!D50*D19 -> 292.8 | E35: =Capacity_ExD!E50*E19 -> 292.8 | F35: =Capacity_ExD!F50*F19 -> 366 | G35: =Capacity_ExD!G50*G19 -> 366 | H35: =Capacity_ExD!H50*H19 -> 366 | I35: =Capacity_ExD!I50*I19 -> 366 | J35: =Capacity_ExD!J50*J19 -> 366 | ... N35: =Capacity_ExD!N50*N19 -> 366 | O35: =SUM(C35:N35) -> 4172.4
A36: Total support & management | B36: mln IRT | C36: =SUM(C29:C35) -> 1525 | D36: =SUM(D29:D35) -> 1708 | E36: =SUM(E29:E35) -> 1708 | F36: =SUM(F29:F35) -> 2135 | G36: =SUM(G29:G35) -> 2135 | H36: =SUM(H29:H35) -> 2135 | I36: =SUM(I29:I35) -> 2135 | J36: =SUM(J29:J35) -> 2135 | ... N36: =SUM(N29:N35) -> 2226.5 | O36: =SUM(C36:N36) -> 24522
A37: 3. RECRUITMENT & ATTRITION - mln IRT
A38: Recruitment cost (hires x cost/hire) | B38: mln IRT | C38: =Capacity_ExD!C35*Assumptions!$C$50*C7 -> 20.564991 | D38: =Capacity_ExD!D35*Assumptions!$C$50*D7 -> 76.643172 | E38: =Capacity_ExD!E35*Assumptions!$C$50*E7 -> 0 | F38: =Capacity_ExD!F35*Assumptions!$C$50*F7 -> 0 | G38: =Capacity_ExD!G35*Assumptions!$C$50*G7 -> 15.735818 | H38: =Capacity_ExD!H35*Assumptions!$C$50*H7 -> 87.42252 | I38: =Capacity_ExD!I35*Assumptions!$C$50*I7 -> 103.3799 | J38: =Capacity_ExD!J35*Assumptions!$C$50*J7 -> 64.60599 | ... N38: =Capacity_ExD!N35*Assumptions!$C$50*N7 -> 0 | O38: =SUM(C38:N38) -> 721.23214
A39: New-hire training - paid non-productive time | B39: mln IRT | C39: =Capacity_ExD!C38*C9 -> 104.5387 | D39: =Capacity_ExD!D38*D9 -> 389.60279 | E39: =Capacity_ExD!E38*E9 -> 0 | F39: =Capacity_ExD!F38*F9 -> 0 | G39: =Capacity_ExD!G38*G9 -> 86.946097 | H39: =Capacity_ExD!H38*H9 -> 483.0411 | I39: =Capacity_ExD!I38*I9 -> 571.21142 | J39: =Capacity_ExD!J38*J9 -> 356.9715 | ... N39: =Capacity_ExD!N38*N9 -> 0 | O39: =SUM(C39:N39) -> 3942.1001 | P39: Hires x 0.5 month x loaded agent cost
A40: Total recruitment & attrition | B40: mln IRT | C40: =C38+C39 -> 125.10369 | D40: =D38+D39 -> 466.24596 | E40: =E38+E39 -> 0 | F40: =F38+F39 -> 0 | G40: =G38+G39 -> 102.68192 | H40: =H38+H39 -> 570.46362 | I40: =I38+I39 -> 674.59132 | J40: =J38+J39 -> 421.57749 | ... N40: =N38+N39 -> 0 | O40: =SUM(C40:N40) -> 4663.3322
A41: 4. TECHNOLOGY & TELEPHONY - mln IRT
A42: Telephony - variable (per handled call) | B42: mln IRT | C42: =Topline_ExC!C16*Assumptions!$C$53*C7/1000000 -> 124.16 | D42: =Topline_ExC!D16*Assumptions!$C$53*D7/1000000 -> 138.24 | E42: =Topline_ExC!E16*Assumptions!$C$53*E7/1000000 -> 109.76 | F42: =Topline_ExC!F16*Assumptions!$C$53*F7/1000000 -> 135.24 | G42: =Topline_ExC!G16*Assumptions!$C$53*G7/1000000 -> 144.256 | H42: =Topline_ExC!H16*Assumptions!$C$53*H7/1000000 -> 162.288 | I42: =Topline_ExC!I16*Assumptions!$C$53*I7/1000000 -> 180.32 | J42: =Topline_ExC!J16*Assumptions!$C$53*J7/1000000 -> 189.336 | ... N42: =Topline_ExC!N16*Assumptions!$C$53*N7/1000000 -> 225.4 | O42: =SUM(C42:N42) -> 2084.74
A43: Telephony - fixed (numbers, trunks) | B43: mln IRT | C43: =Assumptions!$C$54*C7 -> 50 | D43: =Assumptions!$C$54*D7 -> 50 | E43: =Assumptions!$C$54*E7 -> 50 | F43: =Assumptions!$C$54*F7 -> 57.5 | G43: =Assumptions!$C$54*G7 -> 57.5 | H43: =Assumptions!$C$54*H7 -> 57.5 | I43: =Assumptions!$C$54*I7 -> 57.5 | J43: =Assumptions!$C$54*J7 -> 57.5 | ... N43: =Assumptions!$C$54*N7 -> 57.5 | O43: =SUM(C43:N43) -> 667.5
A44: Messaging / e-mail platform (per ticket) | B44: mln IRT | C44: =Topline_ExC!C17*Assumptions!$C$55*C7/1000000 -> 21 | D44: =Topline_ExC!D17*Assumptions!$C$55*D7/1000000 -> 23 | E44: =Topline_ExC!E17*Assumptions!$C$55*E7/1000000 -> 18 | F44: =Topline_ExC!F17*Assumptions!$C$55*F7/1000000 -> 23 | G44: =Topline_ExC!G17*Assumptions!$C$55*G7/1000000 -> 24.15 | H44: =Topline_ExC!H17*Assumptions!$C$55*H7/1000000 -> 25.3 | I44: =Topline_ExC!I17*Assumptions!$C$55*I7/1000000 -> 28.75 | J44: =Topline_ExC!J17*Assumptions!$C$55*J7/1000000 -> 29.9 | ... N44: =Topline_ExC!N17*Assumptions!$C$55*N7/1000000 -> 43.7 | O44: =SUM(C44:N44) -> 359.85
A45: Contact-centre platform licences (per agent) | B45: mln IRT | C45: =Capacity_ExD!C36*Assumptions!$C$51*C7 -> 214.21865 | D45: =Capacity_ExD!D36*Assumptions!$C$51*D7 -> 237.58456 | E45: =Capacity_ExD!E36*Assumptions!$C$51*E7 -> 228.08118 | F45: =Capacity_ExD!F36*Assumptions!$C$51*F7 -> 251.80162 | G45: =Capacity_ExD!G36*Assumptions!$C$51*G7 -> 248.28615 | H45: =Capacity_ExD!H36*Assumptions!$C$51*H7 -> 274.78075 | I45: =Capacity_ExD!I36*Assumptions!$C$51*I7 -> 306.86448 | J45: =Capacity_ExD!J36*Assumptions!$C$51*J7 -> 321.50906 | ... N45: =Capacity_ExD!N36*Assumptions!$C$51*N7 -> 408.19532 | O45: =SUM(C45:N45) -> 3678.4869
A46: IT infrastructure (fixed) | B46: mln IRT | C46: =Assumptions!$C$52*C7 -> 150 | D46: =Assumptions!$C$52*D7 -> 150 | E46: =Assumptions!$C$52*E7 -> 150 | F46: =Assumptions!$C$52*F7 -> 172.5 | G46: =Assumptions!$C$52*G7 -> 172.5 | H46: =Assumptions!$C$52*H7 -> 172.5 | I46: =Assumptions!$C$52*I7 -> 172.5 | J46: =Assumptions!$C$52*J7 -> 172.5 | ... N46: =Assumptions!$C$52*N7 -> 172.5 | O46: =SUM(C46:N46) -> 2002.5
A47: Total technology & telephony | B47: mln IRT | C47: =SUM(C42:C46) -> 559.37865 | D47: =SUM(D42:D46) -> 598.82456 | E47: =SUM(E42:E46) -> 555.84118 | F47: =SUM(F42:F46) -> 640.04162 | G47: =SUM(G42:G46) -> 646.69215 | H47: =SUM(H42:H46) -> 692.36875 | I47: =SUM(I42:I46) -> 745.93448 | J47: =SUM(J42:J46) -> 770.74506 | ... N47: =SUM(N42:N46) -> 907.29532 | O47: =SUM(C47:N47) -> 8793.0769
A48: 5. FACILITIES - mln IRT
A49: Lease (seats leased x rate; fixed contract) | B49: mln IRT | C49: =Capacity_ExD!C58*Assumptions!$C$56 -> 1128 | D49: =Capacity_ExD!D58*Assumptions!$C$56 -> 1128 | E49: =Capacity_ExD!E58*Assumptions!$C$56 -> 1128 | F49: =Capacity_ExD!F58*Assumptions!$C$56 -> 1128 | G49: =Capacity_ExD!G58*Assumptions!$C$56 -> 1128 | H49: =Capacity_ExD!H58*Assumptions!$C$56 -> 1128 | I49: =Capacity_ExD!I58*Assumptions!$C$56 -> 1128 | J49: =Capacity_ExD!J58*Assumptions!$C$56 -> 1128 | ... N49: =Capacity_ExD!N58*Assumptions!$C$56 -> 1128 | O49: =SUM(C49:N49) -> 13536
A50: Utilities, cleaning, security (seats used) | B50: mln IRT | C50: =Capacity_ExD!C57*Assumptions!$C$57*C7 -> 160 | D50: =Capacity_ExD!D57*Assumptions!$C$57*D7 -> 176 | E50: =Capacity_ExD!E57*Assumptions!$C$57*E7 -> 170 | F50: =Capacity_ExD!F57*Assumptions!$C$57*F7 -> 190.9 | G50: =Capacity_ExD!G57*Assumptions!$C$57*G7 -> 188.6 | H50: =Capacity_ExD!H57*Assumptions!$C$57*H7 -> 202.4 | I50: =Capacity_ExD!I57*Assumptions!$C$57*I7 -> 223.1 | J50: =Capacity_ExD!J57*Assumptions!$C$57*J7 -> 230 | ... N50: =Capacity_ExD!N57*Assumptions!$C$57*N7 -> 285.2 | O50: =SUM(C50:N50) -> 2661.1
A51: Total facilities | B51: mln IRT | C51: =C49+C50 -> 1288 | D51: =D49+D50 -> 1304 | E51: =E49+E50 -> 1298 | F51: =F49+F50 -> 1318.9 | G51: =G49+G50 -> 1316.6 | H51: =H49+H50 -> 1330.4 | I51: =I49+I50 -> 1351.1 | J51: =J49+J50 -> 1358 | ... N51: =N49+N50 -> 1413.2 | O51: =SUM(C51:N51) -> 16197.1
A52: 6. CORPORATE OVERHEAD & G&A - mln IRT
A53: Corporate overhead allocation (3% of revenue) | B53: mln IRT | C53: =Topline_ExC!C30*Assumptions!$C$61 -> 405.084 | D53: =Topline_ExC!D30*Assumptions!$C$61 -> 444.09936 | E53: =Topline_ExC!E30*Assumptions!$C$61 -> 355.224 | F53: =Topline_ExC!F30*Assumptions!$C$61 -> 384.24 | G53: =Topline_ExC!G30*Assumptions!$C$61 -> 408.156 | H53: =Topline_ExC!H30*Assumptions!$C$61 -> 450.888 | I53: =Topline_ExC!I30*Assumptions!$C$61 -> 503.82 | J53: =Topline_ExC!J30*Assumptions!$C$61 -> 527.736 | ... N53: =Topline_ExC!N30*Assumptions!$C$61 -> 664.2 | O53: =SUM(C53:N53) -> 6121.9224
A54: Other G&A (per employee) | B54: mln IRT | C54: =Capacity_ExD!C52*Assumptions!$C$62*C7 -> 107.68746 | D54: =Capacity_ExD!D52*Assumptions!$C$62*D7 -> 119.03382 | E54: =Capacity_ExD!E52*Assumptions!$C$62*E7 -> 115.23247 | F54: =Capacity_ExD!F52*Assumptions!$C$62*F7 -> 128.32065 | G54: =Capacity_ExD!G52*Assumptions!$C$62*G7 -> 126.91446 | H54: =Capacity_ExD!H52*Assumptions!$C$62*H7 -> 137.5123 | I54: =Capacity_ExD!I52*Assumptions!$C$62*I7 -> 151.49579 | J54: =Capacity_ExD!J52*Assumptions!$C$62*J7 -> 157.35363 | ... N54: =Capacity_ExD!N52*Assumptions!$C$62*N7 -> 196.62813 | O54: =SUM(C54:N54) -> 1813.9448
A55: Total corporate overhead & G&A | B55: mln IRT | C55: =C53+C54 -> 512.77146 | D55: =D53+D54 -> 563.13318 | E55: =E53+E54 -> 470.45647 | F55: =F53+F54 -> 512.56065 | G55: =G53+G54 -> 535.07046 | H55: =H53+H54 -> 588.4003 | I55: =I53+I54 -> 655.31579 | J55: =J53+J54 -> 685.08963 | ... N55: =N53+N54 -> 860.82813 | O55: =SUM(C55:N55) -> 7935.8672
A56: TOTAL OPERATING COST (pre-D&A) | B56: mln IRT | C56: =C27+C36+C40+C47+C51+C55 -> 10276.629 | D56: =D27+D36+D40+D47+D51+D55 -> 11616.194 | E56: =E27+E36+E40+E47+E51+E55 -> 10739.093 | F56: =F27+F36+F40+F47+F51+F55 -> 12726.162 | G56: =G27+G36+G40+G47+G51+G55 -> 12774.35 | H56: =H27+H36+H40+H47+H51+H55 -> 14078.844 | I56: =I27+I36+I40+I47+I51+I55 -> 15353.875 | J56: =J27+J36+J40+J47+J51+J55 -> 15562.628 | ... N56: =N27+N36+N40+N47+N51+N55 -> 18332.972 | O56: =SUM(C56:N56) -> 177502.23
A57: 7. DEPRECIATION - mln IRT
A58: Depreciation (seats leased x capex / life) | B58: mln IRT | C58: =Capacity_ExD!C58*Assumptions!$C$59/Assumptions!$C$60 -> 313.33333 | D58: =Capacity_ExD!D58*Assumptions!$C$59/Assumptions!$C$60 -> 313.33333 | E58: =Capacity_ExD!E58*Assumptions!$C$59/Assumptions!$C$60 -> 313.33333 | F58: =Capacity_ExD!F58*Assumptions!$C$59/Assumptions!$C$60 -> 313.33333 | G58: =Capacity_ExD!G58*Assumptions!$C$59/Assumptions!$C$60 -> 313.33333 | H58: =Capacity_ExD!H58*Assumptions!$C$59/Assumptions!$C$60 -> 313.33333 | I58: =Capacity_ExD!I58*Assumptions!$C$59/Assumptions!$C$60 -> 313.33333 | J58: =Capacity_ExD!J58*Assumptions!$C$59/Assumptions!$C$60 -> 313.33333 | ... N58: =Capacity_ExD!N58*Assumptions!$C$59/Assumptions!$C$60 -> 313.33333 | O58: =SUM(C58:N58) -> 3760 | P58: All leased seats equipped; 3-year refresh cycle
A59: MEMO - COST STACK MIX
A60: People cost (all payroll incl. OT & training) | B60: mln IRT | C60: =C27+C36+C39 -> 7895.9138 | D60: =D27+D36+D39 -> 9073.5927 | E60: =E27+E36+E39 -> 8414.7957 | F60: =F27+F36+F39 -> 10254.66 | G60: =G27+G36+G39 -> 10260.252 | H60: =H27+H36+H39 -> 11380.252 | I60: =I27+I36+I39 -> 12498.145 | J60: =J27+J36+J39 -> 12684.187 | ... N60: =N27+N36+N39 -> 15151.649 | O60: =SUM(C60:N60) -> 143854.95
A61: People cost % of total operating cost | B61: % | C61: =C60/C56 -> 0.76833696 | D61: =D60/D56 -> 0.78111583 | E61: =E60/E56 -> 0.78356668 | F61: =F60/F56 -> 0.80579359 | G61: =G60/G56 -> 0.80319167 | H61: =H60/H56 -> 0.80832293 | I61: =I60/I56 -> 0.8140059 | J61: =J60/J56 -> 0.81504148 | ... O61: =O60/O56 -> 0.81044026

Sheet PnL_ExE
A1: Exhibit E - Profit & Loss, January-December 2026
A2: mln IRT. Costs shown negative. Column B = cost owner (PIC) for monthly variance reviews.
A4: Line item | B4: PIC / owner | C4: Jan-26 | D4: Feb-26 | E4: Mar-26 | F4: Apr-26 | G4: May-26 | H4: Jun-26 | I4: Jul-26 | J4: Aug-26 | K4: Sep-26 | L4: Oct-26 | M4: Nov-26 | N4: Dec-26 | O4: FY26 | P4: Basis / note
A5: REVENUE
A6: Call revenue | B6: Commercial | C6: =Topline_ExC!C27 -> 9932.8 | D6: =Topline_ExC!D27 -> 11059.2 | E6: =Topline_ExC!E27 -> 8780.8 | F6: =Topline_ExC!F27 -> 9408 | G6: =Topline_ExC!G27 -> 10035.2 | H6: =Topline_ExC!H27 -> 11289.6 | I6: =Topline_ExC!I27 -> 12544 | J6: =Topline_ExC!J27 -> 13171.2 | ... N6: =Topline_ExC!N27 -> 15680 | O6: =SUM(C6:N6) -> 148908.8
A7: Ticket revenue | B7: Commercial | C7: =Topline_ExC!C28 -> 3570 | D7: =Topline_ExC!D28 -> 3910 | E7: =Topline_ExC!E28 -> 3060 | F7: =Topline_ExC!F28 -> 3400 | G7: =Topline_ExC!G28 -> 3570 | H7: =Topline_ExC!H28 -> 3740 | I7: =Topline_ExC!I28 -> 4250 | J7: =Topline_ExC!J28 -> 4420 | ... N7: =Topline_ExC!N28 -> 6460 | O7: =SUM(C7:N7) -> 54570
A8: Other / one-off fees (net of service credits) | B8: Commercial | C8: =Topline_ExC!C29 -> 0 | D8: =Topline_ExC!D29 -> -165.888 | E8: =Topline_ExC!E29 -> 0 | F8: =Topline_ExC!F29 -> 0 | G8: =Topline_ExC!G29 -> 0 | H8: =Topline_ExC!H29 -> 0 | I8: =Topline_ExC!I29 -> 0 | J8: =Topline_ExC!J29 -> 0 | ... N8: =Topline_ExC!N29 -> 0 | O8: =SUM(C8:N8) -> 585.28
A9: Total revenue | C9: =SUM(C6:C8) -> 13502.8 | D9: =SUM(D6:D8) -> 14803.312 | E9: =SUM(E6:E8) -> 11840.8 | F9: =SUM(F6:F8) -> 12808 | G9: =SUM(G6:G8) -> 13605.2 | H9: =SUM(H6:H8) -> 15029.6 | I9: =SUM(I6:I8) -> 16794 | J9: =SUM(J6:J8) -> 17591.2 | ... N9: =SUM(N6:N8) -> 22140 | O9: =SUM(C9:N9) -> 204064.08
A10: COST OF SERVICE (direct delivery)
A11: Agent payroll - productive | B11: Operations | C11: =-Costs!C22 -> -5226.9351 | D11: =-Costs!D22 -> -5797.0633 | E11: =-Costs!E22 -> -4587.2513 | F11: =-Costs!F22 -> -6196.5806 | G11: =-Costs!G22 -> -6584.9804 | H11: =-Costs!H22 -> -7287.6634 | I11: =-Costs!I22 -> -8138.5797 | J11: =-Costs!J22 -> -8526.9795 | ... N11: =-Costs!N22 -> -10673.512 | O11: =SUM(C11:N11) -> -94505.23
A12: Agent payroll - surplus / idle capacity | B12: WFM | C12: =-Costs!C23 -> 0 | D12: =-Costs!D23 -> 0 | E12: =-Costs!E23 -> -977.92945 | F12: =-Costs!F23 -> -481.6363 | G12: =-Costs!G23 -> 0 | H12: =-Costs!H23 -> 0 | I12: =-Costs!I23 -> 0 | J12: =-Costs!J23 -> 0 | ... N12: =-Costs!N23 -> -152.53779 | O12: =SUM(C12:N12) -> -1612.1035
A13: Overtime | B13: WFM | C13: =-Costs!C24 -> -161.04 | D13: =-Costs!D24 -> -178.52667 | E13: =-Costs!E24 -> -141.215 | F13: =-Costs!F24 -> -190.94271 | G13: =-Costs!G24 -> -202.825 | H13: =-Costs!H24 -> -224.04792 | I13: =-Costs!I24 -> -250.35417 | J13: =-Costs!J24 -> -262.23646 | ... N13: =-Costs!N24 -> -330.09896 | O13: =SUM(C13:N13) -> -2913.3155
A14: Team leaders | B14: Operations | C14: =-Costs!C25 -> -732 | D14: =-Costs!D25 -> -854 | E14: =-Costs!E25 -> -854 | F14: =-Costs!F25 -> -1067.5 | G14: =-Costs!G25 -> -1067.5 | H14: =-Costs!H25 -> -1067.5 | I14: =-Costs!I25 -> -1220 | J14: =-Costs!J25 -> -1220 | ... N14: =-Costs!N25 -> -1525 | O14: =SUM(C14:N14) -> -14030
A15: Quality assurance | B15: Quality | C15: =-Costs!C26 -> -146.4 | D15: =-Costs!D26 -> -146.4 | E15: =-Costs!E26 -> -146.4 | F15: =-Costs!F26 -> -183 | G15: =-Costs!G26 -> -183 | H15: =-Costs!H26 -> -183 | I15: =-Costs!I26 -> -183 | J15: =-Costs!J26 -> -183 | ... N15: =-Costs!N26 -> -244 | O15: =SUM(C15:N15) -> -2330.2
A16: Telephony & messaging | B16: IT | C16: =-(Costs!C42+Costs!C43+Costs!C44) -> -195.16 | D16: =-(Costs!D42+Costs!D43+Costs!D44) -> -211.24 | E16: =-(Costs!E42+Costs!E43+Costs!E44) -> -177.76 | F16: =-(Costs!F42+Costs!F43+Costs!F44) -> -215.74 | G16: =-(Costs!G42+Costs!G43+Costs!G44) -> -225.906 | H16: =-(Costs!H42+Costs!H43+Costs!H44) -> -245.088 | I16: =-(Costs!I42+Costs!I43+Costs!I44) -> -266.57 | J16: =-(Costs!J42+Costs!J43+Costs!J44) -> -276.736 | ... N16: =-(Costs!N42+Costs!N43+Costs!N44) -> -326.6 | O16: =SUM(C16:N16) -> -3112.09
A17: Contact-centre platform licences | B17: IT | C17: =-Costs!C45 -> -214.21865 | D17: =-Costs!D45 -> -237.58456 | E17: =-Costs!E45 -> -228.08118 | F17: =-Costs!F45 -> -251.80162 | G17: =-Costs!G45 -> -248.28615 | H17: =-Costs!H45 -> -274.78075 | I17: =-Costs!I45 -> -306.86448 | J17: =-Costs!J45 -> -321.50906 | ... N17: =-Costs!N45 -> -408.19532 | O17: =SUM(C17:N17) -> -3678.4869
A18: Total cost of service | C18: =SUM(C11:C17) -> -6675.7538 | D18: =SUM(D11:D17) -> -7424.8145 | E18: =SUM(E11:E17) -> -7112.6369 | F18: =SUM(F11:F17) -> -8587.2012 | G18: =SUM(G11:G17) -> -8512.4976 | H18: =SUM(H11:H17) -> -9282.0801 | I18: =SUM(I11:I17) -> -10365.368 | J18: =SUM(J11:J17) -> -10790.461 | ... N18: =SUM(N11:N17) -> -13659.944 | O18: =SUM(C18:N18) -> -122181.43
A19: GROSS PROFIT | C19: =C9+C18 -> 6827.0462 | D19: =D9+D18 -> 7378.4975 | E19: =E9+E18 -> 4728.1631 | F19: =F9+F18 -> 4220.7988 | G19: =G9+G18 -> 5092.7024 | H19: =H9+H18 -> 5747.5199 | I19: =I9+I18 -> 6428.6317 | J19: =J9+J18 -> 6800.739 | ... N19: =N9+N18 -> 8480.0558 | O19: =SUM(C19:N19) -> 81882.654
A20: Gross margin % | B20: % | C20: =IFERROR(C19/C9,0) -> 0.50560226 | D20: =IFERROR(D19/D9,0) -> 0.49843559 | E20: =IFERROR(E19/E9,0) -> 0.39931112 | F20: =IFERROR(F19/F9,0) -> 0.32954394 | G20: =IFERROR(G19/G9,0) -> 0.37432029 | H20: =IFERROR(H19/H9,0) -> 0.38241337 | I20: =IFERROR(I19/I9,0) -> 0.38279336 | J20: =IFERROR(J19/J9,0) -> 0.38659892 | ... O20: =IFERROR(O19/O9,0) -> 0.40125952
A21: OPERATING EXPENSES (indirect)
A22: Operations management | B22: Operations | C22: =-Costs!C29 -> -183 | D22: =-Costs!D29 -> -366 | E22: =-Costs!E29 -> -366 | F22: =-Costs!F29 -> -457.5 | G22: =-Costs!G29 -> -457.5 | H22: =-Costs!H29 -> -457.5 | I22: =-Costs!I29 -> -457.5 | J22: =-Costs!J29 -> -457.5 | ... N22: =-Costs!N29 -> -457.5 | O22: =SUM(C22:N22) -> -5032.5
A23: Workforce management | B23: WFM | C23: =-Costs!C30 -> -170.8 | D23: =-Costs!D30 -> -170.8 | E23: =-Costs!E30 -> -170.8 | F23: =-Costs!F30 -> -213.5 | G23: =-Costs!G30 -> -213.5 | H23: =-Costs!H30 -> -213.5 | I23: =-Costs!I30 -> -213.5 | J23: =-Costs!J30 -> -213.5 | ... N23: =-Costs!N30 -> -213.5 | O23: =SUM(C23:N23) -> -2433.9
A24: Training team | B24: Training | C24: =-Costs!C31 -> -146.4 | D24: =-Costs!D31 -> -146.4 | E24: =-Costs!E31 -> -146.4 | F24: =-Costs!F31 -> -183 | G24: =-Costs!G31 -> -183 | H24: =-Costs!H31 -> -183 | I24: =-Costs!I31 -> -183 | J24: =-Costs!J31 -> -183 | ... N24: =-Costs!N31 -> -274.5 | O24: =SUM(C24:N24) -> -2452.2
A25: IT / MIS support staff | B25: IT | C25: =-Costs!C32 -> -195.2 | D25: =-Costs!D32 -> -195.2 | E25: =-Costs!E32 -> -195.2 | F25: =-Costs!F32 -> -244 | G25: =-Costs!G32 -> -244 | H25: =-Costs!H32 -> -244 | I25: =-Costs!I32 -> -244 | J25: =-Costs!J32 -> -244 | ... N25: =-Costs!N32 -> -244 | O25: =SUM(C25:N25) -> -2781.6
A26: HR, recruitment & admin staff | B26: HR | C26: =-Costs!C33 -> -109.8 | D26: =-Costs!D33 -> -109.8 | E26: =-Costs!E33 -> -109.8 | F26: =-Costs!F33 -> -137.25 | G26: =-Costs!G33 -> -137.25 | H26: =-Costs!H33 -> -137.25 | I26: =-Costs!I33 -> -137.25 | J26: =-Costs!J33 -> -137.25 | ... N26: =-Costs!N33 -> -137.25 | O26: =SUM(C26:N26) -> -1564.65
A27: Recruitment & new-hire training (attrition) | B27: HR | C27: =-Costs!C40 -> -125.10369 | D27: =-Costs!D40 -> -466.24596 | E27: =-Costs!E40 -> 0 | F27: =-Costs!F40 -> 0 | G27: =-Costs!G40 -> -102.68192 | H27: =-Costs!H40 -> -570.46362 | I27: =-Costs!I40 -> -674.59132 | J27: =-Costs!J40 -> -421.57749 | ... N27: =-Costs!N40 -> 0 | O27: =SUM(C27:N27) -> -4663.3322
A28: Facilities (lease + utilities) | B28: Admin | C28: =-Costs!C51 -> -1288 | D28: =-Costs!D51 -> -1304 | E28: =-Costs!E51 -> -1298 | F28: =-Costs!F51 -> -1318.9 | G28: =-Costs!G51 -> -1316.6 | H28: =-Costs!H51 -> -1330.4 | I28: =-Costs!I51 -> -1351.1 | J28: =-Costs!J51 -> -1358 | ... N28: =-Costs!N51 -> -1413.2 | O28: =SUM(C28:N28) -> -16197.1
A29: IT infrastructure | B29: IT | C29: =-Costs!C46 -> -150 | D29: =-Costs!D46 -> -150 | E29: =-Costs!E46 -> -150 | F29: =-Costs!F46 -> -172.5 | G29: =-Costs!G46 -> -172.5 | H29: =-Costs!H46 -> -172.5 | I29: =-Costs!I46 -> -172.5 | J29: =-Costs!J46 -> -172.5 | ... N29: =-Costs!N46 -> -172.5 | O29: =SUM(C29:N29) -> -2002.5
A30: Site leadership | B30: Site director | C30: =-Costs!C34 -> -427 | D30: =-Costs!D34 -> -427 | E30: =-Costs!E34 -> -427 | F30: =-Costs!F34 -> -533.75 | G30: =-Costs!G34 -> -533.75 | H30: =-Costs!H34 -> -533.75 | I30: =-Costs!I34 -> -533.75 | J30: =-Costs!J34 -> -533.75 | ... N30: =-Costs!N34 -> -533.75 | O30: =SUM(C30:N30) -> -6084.75
A31: Account management | B31: Commercial | C31: =-Costs!C35 -> -292.8 | D31: =-Costs!D35 -> -292.8 | E31: =-Costs!E35 -> -292.8 | F31: =-Costs!F35 -> -366 | G31: =-Costs!G35 -> -366 | H31: =-Costs!H35 -> -366 | I31: =-Costs!I35 -> -366 | J31: =-Costs!J35 -> -366 | ... N31: =-Costs!N35 -> -366 | O31: =SUM(C31:N31) -> -4172.4
A32: Corporate overhead allocation | B32: Finance | C32: =-Costs!C53 -> -405.084 | D32: =-Costs!D53 -> -444.09936 | E32: =-Costs!E53 -> -355.224 | F32: =-Costs!F53 -> -384.24 | G32: =-Costs!G53 -> -408.156 | H32: =-Costs!H53 -> -450.888 | I32: =-Costs!I53 -> -503.82 | J32: =-Costs!J53 -> -527.736 | ... N32: =-Costs!N53 -> -664.2 | O32: =SUM(C32:N32) -> -6121.9224
A33: Other G&A | B33: Finance | C33: =-Costs!C54 -> -107.68746 | D33: =-Costs!D54 -> -119.03382 | E33: =-Costs!E54 -> -115.23247 | F33: =-Costs!F54 -> -128.32065 | G33: =-Costs!G54 -> -126.91446 | H33: =-Costs!H54 -> -137.5123 | I33: =-Costs!I54 -> -151.49579 | J33: =-Costs!J54 -> -157.35363 | ... N33: =-Costs!N54 -> -196.62813 | O33: =SUM(C33:N33) -> -1813.9448
A34: Total operating expenses | C34: =SUM(C22:C33) -> -3600.8752 | D34: =SUM(D22:D33) -> -4191.3791 | E34: =SUM(E22:E33) -> -3626.4565 | F34: =SUM(F22:F33) -> -4138.9606 | G34: =SUM(G22:G33) -> -4261.8524 | H34: =SUM(H22:H33) -> -4796.7639 | I34: =SUM(I22:I33) -> -4988.5071 | J34: =SUM(J22:J33) -> -4772.1671 | ... N34: =SUM(N22:N33) -> -4673.0281 | O34: =SUM(C34:N34) -> -55320.799
A35: EBITDA | C35: =C19+C34 -> 3226.1711 | D35: =D19+D34 -> 3187.1184 | E35: =E19+E34 -> 1101.7066 | F35: =F19+F34 -> 81.838129 | G35: =G19+G34 -> 830.85007 | H35: =H19+H34 -> 950.75603 | I35: =I19+I34 -> 1440.1246 | J35: =J19+J34 -> 2028.5719 | ... N35: =N19+N34 -> 3807.0277 | O35: =SUM(C35:N35) -> 26561.855
A36: EBITDA margin % | B36: % | C36: =IFERROR(C35/C9,0) -> 0.23892608 | D36: =IFERROR(D35/D9,0) -> 0.21529765 | E36: =IFERROR(E35/E9,0) -> 0.093043258 | F36: =IFERROR(F35/F9,0) -> 0.0063896103 | G36: =IFERROR(G35/G9,0) -> 0.061068567 | H36: =IFERROR(H35/H9,0) -> 0.063258904 | I36: =IFERROR(I35/I9,0) -> 0.085752325 | J36: =IFERROR(J35/J9,0) -> 0.11531742 | ... O36: =IFERROR(O35/O9,0) -> 0.13016428
A37: Depreciation & amortisation | B37: Finance | C37: =-Costs!C58 -> -313.33333 | D37: =-Costs!D58 -> -313.33333 | E37: =-Costs!E58 -> -313.33333 | F37: =-Costs!F58 -> -313.33333 | G37: =-Costs!G58 -> -313.33333 | H37: =-Costs!H58 -> -313.33333 | I37: =-Costs!I58 -> -313.33333 | J37: =-Costs!J58 -> -313.33333 | ... N37: =-Costs!N58 -> -313.33333 | O37: =SUM(C37:N37) -> -3760
A38: EBIT | C38: =C35+C37 -> 2912.8378 | D38: =D35+D37 -> 2873.785 | E38: =E35+E37 -> 788.37327 | F38: =F35+F37 -> -231.4952 | G38: =G35+G37 -> 517.51673 | H38: =H35+H37 -> 637.4227 | I38: =I35+I37 -> 1126.7912 | J38: =J35+J37 -> 1715.2385 | ... N38: =N35+N37 -> 3493.6944 | O38: =SUM(C38:N38) -> 22801.855
A39: Net finance cost | B39: Finance | C39: =-Assumptions!$C$63 -> 0 | D39: =-Assumptions!$C$63 -> 0 | E39: =-Assumptions!$C$63 -> 0 | F39: =-Assumptions!$C$63 -> 0 | G39: =-Assumptions!$C$63 -> 0 | H39: =-Assumptions!$C$63 -> 0 | I39: =-Assumptions!$C$63 -> 0 | J39: =-Assumptions!$C$63 -> 0 | ... N39: =-Assumptions!$C$63 -> 0 | O39: =SUM(C39:N39) -> 0
A40: Profit before tax | C40: =C38+C39 -> 2912.8378 | D40: =D38+D39 -> 2873.785 | E40: =E38+E39 -> 788.37327 | F40: =F38+F39 -> -231.4952 | G40: =G38+G39 -> 517.51673 | H40: =H38+H39 -> 637.4227 | I40: =I38+I39 -> 1126.7912 | J40: =J38+J39 -> 1715.2385 | ... N40: =N38+N39 -> 3493.6944 | O40: =SUM(C40:N40) -> 22801.855
A41: Income tax (22%) | B41: Finance | C41: =-C40*Assumptions!$C$18 -> -640.82431 | D41: =-D40*Assumptions!$C$18 -> -632.2327 | E41: =-E40*Assumptions!$C$18 -> -173.44212 | F41: =-F40*Assumptions!$C$18 -> 50.928945 | G41: =-G40*Assumptions!$C$18 -> -113.85368 | H41: =-H40*Assumptions!$C$18 -> -140.23299 | I41: =-I40*Assumptions!$C$18 -> -247.89407 | J41: =-J40*Assumptions!$C$18 -> -377.35247 | ... N41: =-N40*Assumptions!$C$18 -> -768.61276 | O41: =SUM(C41:N41) -> -5016.408 | P41: Monthly accrual; loss months create a credit used within FY
A42: NET PROFIT | C42: =C40+C41 -> 2272.0135 | D42: =D40+D41 -> 2241.5523 | E42: =E40+E41 -> 614.93115 | F42: =F40+F41 -> -180.56626 | G42: =G40+G41 -> 403.66305 | H42: =H40+H41 -> 497.1897 | I42: =I40+I41 -> 878.89715 | J42: =J40+J41 -> 1337.886 | ... N42: =N40+N41 -> 2725.0816 | O42: =SUM(C42:N42) -> 17785.447
A43: Net margin % | B43: % | C43: =IFERROR(C42/C9,0) -> 0.16826239 | D43: =IFERROR(D42/D9,0) -> 0.15142235 | E43: =IFERROR(E42/E9,0) -> 0.051933244 | F43: =IFERROR(F42/F9,0) -> -0.014097928 | G43: =IFERROR(G42/G9,0) -> 0.029669762 | H43: =IFERROR(H42/H9,0) -> 0.033080701 | I43: =IFERROR(I42/I9,0) -> 0.052333997 | J43: =IFERROR(J42/J9,0) -> 0.07605428 | ... O43: =IFERROR(O42/O9,0) -> 0.087156184
A45: KPIs
A46: Calls handled (billable) | B46: # | C46: =Topline_ExC!C16 -> 310400 | D46: =Topline_ExC!D16 -> 345600 | E46: =Topline_ExC!E16 -> 274400 | F46: =Topline_ExC!F16 -> 294000 | G46: =Topline_ExC!G16 -> 313600 | H46: =Topline_ExC!H16 -> 352800 | I46: =Topline_ExC!I16 -> 392000 | J46: =Topline_ExC!J16 -> 411600 | ... N46: =Topline_ExC!N16 -> 490000 | O46: =SUM(C46:N46) -> 4653400
A47: Tickets handled (billable) | B47: # | C47: =Topline_ExC!C17 -> 210000 | D47: =Topline_ExC!D17 -> 230000 | E47: =Topline_ExC!E17 -> 180000 | F47: =Topline_ExC!F17 -> 200000 | G47: =Topline_ExC!G17 -> 210000 | H47: =Topline_ExC!H17 -> 220000 | I47: =Topline_ExC!I17 -> 250000 | J47: =Topline_ExC!J17 -> 260000 | ... N47: =Topline_ExC!N17 -> 380000 | O47: =SUM(C47:N47) -> 3210000
A48: Agent FTE required | B48: FTE | C48: =Capacity_ExD!C31 -> 85.687461 | D48: =Capacity_ExD!D31 -> 95.033824 | E48: =Capacity_ExD!E31 -> 75.200841 | F48: =Capacity_ExD!F31 -> 81.266631 | G48: =Capacity_ExD!G31 -> 86.360399 | H48: =Capacity_ExD!H31 -> 95.575913 | I48: =Capacity_ExD!I31 -> 106.73547 | J48: =Capacity_ExD!J31 -> 111.82924 | ... N48: =Capacity_ExD!N31 -> 139.98049 | O48: =AVERAGE(C48:N48) -> 107.54977
A49: Agent headcount on payroll | B49: FTE | C49: =Capacity_ExD!C36 -> 85.687461 | D49: =Capacity_ExD!D36 -> 95.033824 | E49: =Capacity_ExD!E36 -> 91.232471 | F49: =Capacity_ExD!F36 -> 87.583172 | G49: =Capacity_ExD!G36 -> 86.360399 | H49: =Capacity_ExD!H36 -> 95.575913 | I49: =Capacity_ExD!I36 -> 106.73547 | J49: =Capacity_ExD!J36 -> 111.82924 | ... N49: =Capacity_ExD!N36 -> 141.98098 | O49: =AVERAGE(C49:N49) -> 109.57883
A50: Total headcount | B50: FTE | C50: =Capacity_ExD!C52 -> 107.68746 | D50: =Capacity_ExD!D52 -> 119.03382 | E50: =Capacity_ExD!E52 -> 115.23247 | F50: =Capacity_ExD!F52 -> 111.58317 | G50: =Capacity_ExD!G52 -> 110.3604 | H50: =Capacity_ExD!H52 -> 119.57591 | I50: =Capacity_ExD!I52 -> 131.73547 | J50: =Capacity_ExD!J52 -> 136.82924 | ... N50: =Capacity_ExD!N52 -> 170.98098 | O50: =AVERAGE(C50:N50) -> 135.16216
A51: Blended cost per contact (pre-D&A) | B51: IRT | C51: =-(C18+C34)*1000000/(C46+C47) -> 19747.557 | D51: =-(D18+D34)*1000000/(D46+D47) -> 20181.017 | E51: =-(E18+E34)*1000000/(E46+E47) -> 23633.568 | F51: =-(F18+F34)*1000000/(F46+F47) -> 25761.461 | G51: =-(G18+G34)*1000000/(G46+G47) -> 24397.154 | H51: =-(H18+H34)*1000000/(H46+H47) -> 24578.987 | I51: =-(I18+I34)*1000000/(I46+I47) -> 23915.694 | J51: =-(J18+J34)*1000000/(J46+J47) -> 23172.466 | ... O51: =-(O18+O34)*1000000/(O46+O47) -> 22573.216
A52: Blended revenue per contact | B52: IRT | C52: =C9*1000000/(C46+C47) -> 25946.964 | D52: =D9*1000000/(D46+D47) -> 25718.054 | E52: =E9*1000000/(E46+E47) -> 26058.099 | F52: =F9*1000000/(F46+F47) -> 25927.126 | G52: =G9*1000000/(G46+G47) -> 25983.957 | H52: =H9*1000000/(H46+H47) -> 26238.827 | I52: =I9*1000000/(I46+I47) -> 26158.879 | J52: =J9*1000000/(J46+J47) -> 26192.972 | ... O52: =O9*1000000/(O46+O47) -> 25951.125
A53: Revenue per agent on payroll | B53: mln IRT | C53: =C9/C49 -> 157.58198 | D53: =D9/D49 -> 155.76888 | E53: =E9/E49 -> 129.78712 | F53: =F9/F49 -> 146.23814 | G53: =G9/G49 -> 157.5398 | H53: =H9/H49 -> 157.25301 | I53: =I9/I49 -> 157.34226 | J53: =J9/J49 -> 157.30412 | ... N53: =N9/N49 -> 155.93638 | O53: =O9/12/O49 -> 155.18819 | P53: FY = monthly average
A54: People cost % revenue | B54: % | C54: =Costs!C60/C9 -> 0.58476122 | D54: =Costs!D60/D9 -> 0.61294342 | E54: =Costs!E60/E9 -> 0.71066108 | F54: =Costs!F60/F9 -> 0.80064488 | G54: =Costs!G60/G9 -> 0.75414191 | H54: =Costs!H60/H9 -> 0.75718931 | I54: =Costs!I60/I9 -> 0.74420301 | J54: =Costs!J60/J9 -> 0.721053 | ... O54: =Costs!O60/O9 -> 0.70494988
A55: Idle-capacity cost % revenue | B55: % | C55: =-C12/C9 -> 0 | D55: =-D12/D9 -> 0 | E55: =-E12/E9 -> 0.082589813 | F55: =-F12/F9 -> 0.037604333 | G55: =-G12/G9 -> 0 | H55: =-H12/H9 -> 0 | I55: =-I12/I9 -> 0 | J55: =-J12/J9 -> 0 | ... O55: =-O12/O9 -> 0.0078999868

Sheet UnitEcon
A1: Unit economics - revenue, cost and contribution per call vs per ticket
A2: Activity-based allocation: agent cost by channel FTE share, OT by workload hours, telephony to voice, messaging to tickets; overheads by FTE share.
A4: Line item | B4: Unit | C4: Jan-26 | D4: Feb-26 | E4: Mar-26 | F4: Apr-26 | G4: May-26 | H4: Jun-26 | I4: Jul-26 | J4: Aug-26 | K4: Sep-26 | L4: Oct-26 | M4: Nov-26 | N4: Dec-26 | O4: FY26 | P4: Basis / note
A5: ALLOCATION KEYS
A6: Voice share of agent FTE | B6: % | C6: =Capacity_ExD!C29/Capacity_ExD!C31 -> 0.7617801 | D6: =Capacity_ExD!D29/Capacity_ExD!D31 -> 0.76475216 | E6: =Capacity_ExD!E29/Capacity_ExD!E31 -> 0.76733781 | F6: =Capacity_ExD!F29/Capacity_ExD!F31 -> 0.76078206 | G6: =Capacity_ExD!G29/Capacity_ExD!G31 -> 0.76363636 | H6: =Capacity_ExD!H29/Capacity_ExD!H31 -> 0.7762566 | I6: =Capacity_ExD!I29/Capacity_ExD!I31 -> 0.77232925 | J6: =Capacity_ExD!J29/Capacity_ExD!J31 -> 0.77400752 | ... N6: =Capacity_ExD!N29/Capacity_ExD!N31 -> 0.73612873 | O6: =AVERAGE(C6:N6) -> 0.76024182
A7: Ticket share of agent FTE | B7: % | C7: =1-C6 -> 0.2382199 | D7: =1-D6 -> 0.23524784 | E7: =1-E6 -> 0.23266219 | F7: =1-F6 -> 0.23921794 | G7: =1-G6 -> 0.23636364 | H7: =1-H6 -> 0.2237434 | I7: =1-I6 -> 0.22767075 | J7: =1-J6 -> 0.22599248 | ... N7: =1-N6 -> 0.26387127 | O7: =AVERAGE(C7:N7) -> 0.23975818
A8: Voice share of workload hours | B8: % | C8: =Capacity_ExD!C8/Capacity_ExD!C12 -> 0.73484848 | D8: =Capacity_ExD!D8/Capacity_ExD!D12 -> 0.738041 | E8: =Capacity_ExD!E8/Capacity_ExD!E12 -> 0.74082073 | F8: =Capacity_ExD!F8/Capacity_ExD!F12 -> 0.73377704 | G8: =Capacity_ExD!G8/Capacity_ExD!G12 -> 0.73684211 | H8: =Capacity_ExD!H8/Capacity_ExD!H12 -> 0.75042541 | I8: =Capacity_ExD!I8/Capacity_ExD!I12 -> 0.74619289 | J8: =Capacity_ExD!J8/Capacity_ExD!J12 -> 0.74800097 | ... N8: =Capacity_ExD!N8/Capacity_ExD!N12 -> 0.70741097 | O8: =AVERAGE(C8:N8) -> 0.73322295
A9: Ticket share of workload hours | B9: % | C9: =1-C8 -> 0.26515152 | D9: =1-D8 -> 0.261959 | E9: =1-E8 -> 0.25917927 | F9: =1-F8 -> 0.26622296 | G9: =1-G8 -> 0.26315789 | H9: =1-H8 -> 0.24957459 | I9: =1-I8 -> 0.25380711 | J9: =1-J8 -> 0.25199903 | ... N9: =1-N8 -> 0.29258903 | O9: =AVERAGE(C9:N9) -> 0.26677705
A10: VOICE (per handled call)
A11: Revenue | B11: mln IRT | C11: =Topline_ExC!C27 -> 9932.8 | D11: =Topline_ExC!D27 -> 11059.2 | E11: =Topline_ExC!E27 -> 8780.8 | F11: =Topline_ExC!F27 -> 9408 | G11: =Topline_ExC!G27 -> 10035.2 | H11: =Topline_ExC!H27 -> 11289.6 | I11: =Topline_ExC!I27 -> 12544 | J11: =Topline_ExC!J27 -> 13171.2 | ... N11: =Topline_ExC!N27 -> 15680 | O11: =SUM(C11:N11) -> 148908.8
A12: (-) Agent labour (productive + idle), by FTE share | B12: mln IRT | C12: =-(Costs!C22+Costs!C23)*C6 -> -3981.7752 | D12: =-(Costs!D22+Costs!D23)*D6 -> -4433.3167 | E12: =-(Costs!E22+Costs!E23)*E6 -> -4270.3736 | F12: =-(Costs!F22+Costs!F23)*F6 -> -5080.6676 | G12: =-(Costs!G22+Costs!G23)*G6 -> -5028.5305 | H12: =-(Costs!H22+Costs!H23)*H6 -> -5657.0968 | I12: =-(Costs!I22+Costs!I23)*I6 -> -6285.6631 | J12: =-(Costs!J22+Costs!J23)*J6 -> -6599.9463 | ... N12: =-(Costs!N22+Costs!N23)*N6 -> -7969.3664 | O12: =SUM(C12:N12) -> -72861.938
A13: (-) Overtime, by workload-hour share | B13: mln IRT | C13: =-Costs!C24*C8 -> -118.34 | D13: =-Costs!D24*D8 -> -131.76 | E13: =-Costs!E24*E8 -> -104.615 | F13: =-Costs!F24*F8 -> -140.10938 | G13: =-Costs!G24*G8 -> -149.45 | H13: =-Costs!H24*H8 -> -168.13125 | I13: =-Costs!I24*I8 -> -186.8125 | J13: =-Costs!J24*J8 -> -196.15312 | ... N13: =-Costs!N24*N8 -> -233.51562 | O13: =SUM(C13:N13) -> -2128.9572
A14: (-) Channel cost (telephony / messaging) | B14: mln IRT | C14: =-(Costs!C42+Costs!C43) -> -174.16 | D14: =-(Costs!D42+Costs!D43) -> -188.24 | E14: =-(Costs!E42+Costs!E43) -> -159.76 | F14: =-(Costs!F42+Costs!F43) -> -192.74 | G14: =-(Costs!G42+Costs!G43) -> -201.756 | H14: =-(Costs!H42+Costs!H43) -> -219.788 | I14: =-(Costs!I42+Costs!I43) -> -237.82 | J14: =-(Costs!J42+Costs!J43) -> -246.836 | ... N14: =-(Costs!N42+Costs!N43) -> -282.9 | O14: =SUM(C14:N14) -> -2752.24
A15: CM1 - contribution after direct delivery | B15: mln IRT | C15: =SUM(C11:C14) -> 5658.5248 | D15: =SUM(D11:D14) -> 6305.8833 | E15: =SUM(E11:E14) -> 4246.0514 | F15: =SUM(F11:F14) -> 3994.483 | G15: =SUM(G11:G14) -> 4655.4635 | H15: =SUM(H11:H14) -> 5244.5839 | I15: =SUM(I11:I14) -> 5833.7044 | J15: =SUM(J11:J14) -> 6128.2646 | ... N15: =SUM(N11:N14) -> 7194.218 | O15: =SUM(C15:N15) -> 71165.665
A16: (-) Supervision, QA, ops support, recruitment, licences | B16: mln IRT | C16: =-(Costs!C25+Costs!C26+Costs!C36-Costs!C34-Costs!C35+Costs!C40+Costs!C45)*C6 -> -1541.022 | D16: =-(Costs!D25+Costs!D26+Costs!D36-Costs!D34-Costs!D35+Costs!D40+Costs!D45)*D6 -> -2059.0421 | E16: =-(Costs!E25+Costs!E26+Costs!E36-Costs!E34-Costs!E35+Costs!E40+Costs!E45)*E6 -> -1700.9433 | F16: =-(Costs!F25+Costs!F26+Costs!F36-Costs!F34-Costs!F35+Costs!F40+Costs!F45)*F6 -> -2082.6802 | G16: =-(Costs!G25+Costs!G26+Costs!G36-Costs!G34-Costs!G35+Costs!G40+Costs!G45)*G6 -> -2166.2211 | H16: =-(Costs!H25+Costs!H26+Costs!H36-Costs!H34-Costs!H35+Costs!H40+Costs!H45)*H6 -> -2585.7064 | I16: =-(Costs!I25+Costs!I26+Costs!I36-Costs!I34-Costs!I35+Costs!I40+Costs!I45)*I6 -> -2795.6047 | J16: =-(Costs!J25+Costs!J26+Costs!J36-Costs!J34-Costs!J35+Costs!J40+Costs!J45)*J6 -> -2617.1799 | ... N16: =-(Costs!N25+Costs!N26+Costs!N36-Costs!N34-Costs!N35+Costs!N40+Costs!N45)*N6 -> -2579.3548 | O16: =SUM(C16:N16) -> -29579.072
A17: CM2 - contribution after semi-variable cost | B17: mln IRT | C17: =C15+C16 -> 4117.5028 | D17: =D15+D16 -> 4246.8413 | E17: =E15+E16 -> 2545.1081 | F17: =F15+F16 -> 1911.8029 | G17: =G15+G16 -> 2489.2424 | H17: =H15+H16 -> 2658.8776 | I17: =I15+I16 -> 3038.0997 | J17: =J15+J16 -> 3511.0847 | ... N17: =N15+N16 -> 4614.8632 | O17: =SUM(C17:N17) -> 41586.593
A18: (-) Fixed overhead (facilities, IT infra, site, AM, corporate) | B18: mln IRT | C18: =-(Costs!C51+Costs!C46+Costs!C34+Costs!C35+Costs!C55)*C6 -> -2034.3882 | D18: =-(Costs!D51+Costs!D46+Costs!D34+Costs!D35+Costs!D55)*D6 -> -2093.0756 | E18: =-(Costs!E51+Costs!E46+Costs!E34+Costs!E35+Costs!E55)*E6 -> -2024.4339 | F18: =-(Costs!F51+Costs!F46+Costs!F34+Costs!F35+Costs!F55)*F6 -> -2209.091 | G18: =-(Costs!G51+Costs!G46+Costs!G34+Costs!G35+Costs!G55)*G6 -> -2232.812 | H18: =-(Costs!H51+Costs!H46+Costs!H34+Costs!H35+Costs!H55)*H6 -> -2321.8225 | I18: =-(Costs!I51+Costs!I46+Costs!I34+Costs!I35+Costs!I55)*I6 -> -2377.7436 | J18: =-(Costs!J51+Costs!J46+Costs!J34+Costs!J35+Costs!J55)*J6 -> -2411.2963 | ... N18: =-(Costs!N51+Costs!N46+Costs!N34+Costs!N35+Costs!N55)*N6 -> -2463.2915 | O18: =SUM(C18:N18) -> -27644.021
A19: EBITDA contribution | B19: mln IRT | C19: =C17+C18 -> 2083.1146 | D19: =D17+D18 -> 2153.7657 | E19: =E17+E18 -> 520.6742 | F19: =F17+F18 -> -297.28809 | G19: =G17+G18 -> 256.43045 | H19: =H17+H18 -> 337.05504 | I19: =I17+I18 -> 660.35609 | J19: =J17+J18 -> 1099.7884 | ... N19: =N17+N18 -> 2151.5717 | O19: =SUM(C19:N19) -> 13942.571
A20: Billable volume | B20: # | C20: =Topline_ExC!C16 -> 310400 | D20: =Topline_ExC!D16 -> 345600 | E20: =Topline_ExC!E16 -> 274400 | F20: =Topline_ExC!F16 -> 294000 | G20: =Topline_ExC!G16 -> 313600 | H20: =Topline_ExC!H16 -> 352800 | I20: =Topline_ExC!I16 -> 392000 | J20: =Topline_ExC!J16 -> 411600 | ... N20: =Topline_ExC!N16 -> 490000 | O20: =SUM(C20:N20) -> 4653400
A21: CM1 per contact | B21: IRT | C21: =C15*1000000/C20 -> 18229.784 | D21: =D15*1000000/D20 -> 18246.19 | E21: =E15*1000000/E20 -> 15473.948 | F21: =F15*1000000/F20 -> 13586.677 | G21: =G15*1000000/G20 -> 14845.228 | H21: =H15*1000000/H20 -> 14865.601 | I21: =I15*1000000/I20 -> 14881.899 | J21: =J15*1000000/J20 -> 14888.884 | ... O21: =O15*1000000/O20 -> 15293.262
A22: CM2 per contact | B22: IRT | C22: =C17*1000000/C20 -> 13265.151 | D22: =D17*1000000/D20 -> 12288.314 | E22: =E17*1000000/E20 -> 9275.1754 | F22: =F17*1000000/F20 -> 6502.7309 | G22: =G17*1000000/G20 -> 7937.6353 | H22: =H17*1000000/H20 -> 7536.5011 | I22: =I17*1000000/I20 -> 7750.2544 | J22: =J17*1000000/J20 -> 8530.332 | ... O22: =O17*1000000/O20 -> 8936.8188
A23: EBITDA per contact | B23: IRT | C23: =C19*1000000/C20 -> 6711.0652 | D23: =D19*1000000/D20 -> 6231.9609 | E23: =E19*1000000/E20 -> 1897.5007 | F23: =F19*1000000/F20 -> -1011.184 | G23: =G19*1000000/G20 -> 817.69914 | H23: =H19*1000000/H20 -> 955.37142 | I23: =I19*1000000/I20 -> 1684.5819 | J23: =J19*1000000/J20 -> 2671.9834 | ... O23: =O19*1000000/O20 -> 2996.2117
A24: EBITDA margin | B24: % | C24: =C19/C11 -> 0.20972079 | D24: =D19/D11 -> 0.19474878 | E24: =E19/E11 -> 0.059296897 | F24: =F19/F11 -> -0.0315995 | G24: =G19/G11 -> 0.025553098 | H24: =H19/H11 -> 0.029855357 | I24: =I19/I11 -> 0.052643183 | J24: =J19/J11 -> 0.083499481 | ... O24: =O19/O11 -> 0.093631615
A25: TICKETS (per handled ticket)
A26: Revenue | B26: mln IRT | C26: =Topline_ExC!C28 -> 3570 | D26: =Topline_ExC!D28 -> 3910 | E26: =Topline_ExC!E28 -> 3060 | F26: =Topline_ExC!F28 -> 3400 | G26: =Topline_ExC!G28 -> 3570 | H26: =Topline_ExC!H28 -> 3740 | I26: =Topline_ExC!I28 -> 4250 | J26: =Topline_ExC!J28 -> 4420 | ... N26: =Topline_ExC!N28 -> 6460 | O26: =SUM(C26:N26) -> 54570
A27: (-) Agent labour (productive + idle), by FTE share | B27: mln IRT | C27: =-(Costs!C22+Costs!C23)*C7 -> -1245.1599 | D27: =-(Costs!D22+Costs!D23)*D7 -> -1363.7466 | E27: =-(Costs!E22+Costs!E23)*E7 -> -1294.8072 | F27: =-(Costs!F22+Costs!F23)*F7 -> -1597.5493 | G27: =-(Costs!G22+Costs!G23)*G7 -> -1556.4499 | H27: =-(Costs!H22+Costs!H23)*H7 -> -1630.5666 | I27: =-(Costs!I22+Costs!I23)*I7 -> -1852.9166 | J27: =-(Costs!J22+Costs!J23)*J7 -> -1927.0332 | ... N27: =-(Costs!N22+Costs!N23)*N7 -> -2856.6835 | O27: =SUM(C27:N27) -> -23255.396
A28: (-) Overtime, by workload-hour share | B28: mln IRT | C28: =-Costs!C24*C9 -> -42.7 | D28: =-Costs!D24*D9 -> -46.766667 | E28: =-Costs!E24*E9 -> -36.6 | F28: =-Costs!F24*F9 -> -50.833333 | G28: =-Costs!G24*G9 -> -53.375 | H28: =-Costs!H24*H9 -> -55.916667 | I28: =-Costs!I24*I9 -> -63.541667 | J28: =-Costs!J24*J9 -> -66.083333 | ... N28: =-Costs!N24*N9 -> -96.583333 | O28: =SUM(C28:N28) -> -784.35833
A29: (-) Channel cost (telephony / messaging) | B29: mln IRT | C29: =-Costs!C44 -> -21 | D29: =-Costs!D44 -> -23 | E29: =-Costs!E44 -> -18 | F29: =-Costs!F44 -> -23 | G29: =-Costs!G44 -> -24.15 | H29: =-Costs!H44 -> -25.3 | I29: =-Costs!I44 -> -28.75 | J29: =-Costs!J44 -> -29.9 | ... N29: =-Costs!N44 -> -43.7 | O29: =SUM(C29:N29) -> -359.85
A30: CM1 - contribution after direct delivery | B30: mln IRT | C30: =SUM(C26:C29) -> 2261.1401 | D30: =SUM(D26:D29) -> 2476.4867 | E30: =SUM(E26:E29) -> 1710.5928 | F30: =SUM(F26:F29) -> 1728.6174 | G30: =SUM(G26:G29) -> 1936.0251 | H30: =SUM(H26:H29) -> 2028.2168 | I30: =SUM(I26:I29) -> 2304.7918 | J30: =SUM(J26:J29) -> 2396.9834 | ... N30: =SUM(N26:N29) -> 3463.0331 | O30: =SUM(C30:N30) -> 30170.396
A31: (-) Supervision, QA, ops support, recruitment, licences | B31: mln IRT | C31: =-(Costs!C25+Costs!C26+Costs!C36-Costs!C34-Costs!C35+Costs!C40+Costs!C45)*C7 -> -481.90035 | D31: =-(Costs!D25+Costs!D26+Costs!D36-Costs!D34-Costs!D35+Costs!D40+Costs!D45)*D7 -> -633.38845 | E31: =-(Costs!E25+Costs!E26+Costs!E36-Costs!E34-Costs!E35+Costs!E40+Costs!E45)*E7 -> -515.7379 | F31: =-(Costs!F25+Costs!F26+Costs!F36-Costs!F34-Costs!F35+Costs!F40+Costs!F45)*F7 -> -654.87146 | G31: =-(Costs!G25+Costs!G26+Costs!G36-Costs!G34-Costs!G35+Costs!G40+Costs!G45)*G7 -> -670.497 | H31: =-(Costs!H25+Costs!H26+Costs!H36-Costs!H34-Costs!H35+Costs!H40+Costs!H45)*H7 -> -745.288 | I31: =-(Costs!I25+Costs!I26+Costs!I36-Costs!I34-Costs!I35+Costs!I40+Costs!I45)*I7 -> -824.10115 | J31: =-(Costs!J25+Costs!J26+Costs!J36-Costs!J34-Costs!J35+Costs!J40+Costs!J45)*J7 -> -764.15663 | ... N31: =-(Costs!N25+Costs!N26+Costs!N36-Costs!N34-Costs!N35+Costs!N40+Costs!N45)*N7 -> -924.5905 | O31: =SUM(C31:N31) -> -9387.7971
A32: CM2 - contribution after semi-variable cost | B32: mln IRT | C32: =C30+C31 -> 1779.2397 | D32: =D30+D31 -> 1843.0983 | E32: =E30+E31 -> 1194.8549 | F32: =F30+F31 -> 1073.7459 | G32: =G30+G31 -> 1265.5281 | H32: =H30+H31 -> 1282.9288 | I32: =I30+I31 -> 1480.6906 | J32: =J30+J31 -> 1632.8268 | ... N32: =N30+N31 -> 2538.4426 | O32: =SUM(C32:N32) -> 20782.599
A33: (-) Fixed overhead (facilities, IT infra, site, AM, corporate) | B33: mln IRT | C33: =-(Costs!C51+Costs!C46+Costs!C34+Costs!C35+Costs!C55)*C7 -> -636.18325 | D33: =-(Costs!D51+Costs!D46+Costs!D34+Costs!D35+Costs!D55)*D7 -> -643.85761 | E33: =-(Costs!E51+Costs!E46+Costs!E34+Costs!E35+Costs!E55)*E7 -> -613.82253 | F33: =-(Costs!F51+Costs!F46+Costs!F34+Costs!F35+Costs!F55)*F7 -> -694.61968 | G33: =-(Costs!G51+Costs!G46+Costs!G34+Costs!G35+Costs!G55)*G7 -> -691.10847 | H33: =-(Costs!H51+Costs!H46+Costs!H34+Costs!H35+Costs!H55)*H7 -> -669.22776 | I33: =-(Costs!I51+Costs!I46+Costs!I34+Costs!I35+Costs!I55)*I7 -> -700.92216 | J33: =-(Costs!J51+Costs!J46+Costs!J34+Costs!J35+Costs!J55)*J7 -> -704.04332 | ... N33: =-(Costs!N51+Costs!N46+Costs!N34+Costs!N35+Costs!N55)*N7 -> -882.98666 | O33: =SUM(C33:N33) -> -8748.5957
A34: EBITDA contribution | B34: mln IRT | C34: =C32+C33 -> 1143.0565 | D34: =D32+D33 -> 1199.2407 | E34: =E32+E33 -> 581.03241 | F34: =F32+F33 -> 379.12622 | G34: =G32+G33 -> 574.41962 | H34: =H32+H33 -> 613.70099 | I34: =I32+I33 -> 779.76846 | J34: =J32+J33 -> 928.78349 | ... N34: =N32+N33 -> 1655.456 | O34: =SUM(C34:N34) -> 12034.003
A35: Billable volume | B35: # | C35: =Topline_ExC!C17 -> 210000 | D35: =Topline_ExC!D17 -> 230000 | E35: =Topline_ExC!E17 -> 180000 | F35: =Topline_ExC!F17 -> 200000 | G35: =Topline_ExC!G17 -> 210000 | H35: =Topline_ExC!H17 -> 220000 | I35: =Topline_ExC!I17 -> 250000 | J35: =Topline_ExC!J17 -> 260000 | ... N35: =Topline_ExC!N17 -> 380000 | O35: =SUM(C35:N35) -> 3210000
A36: CM1 per contact | B36: IRT | C36: =C30*1000000/C35 -> 10767.334 | D36: =D30*1000000/D35 -> 10767.334 | E36: =E30*1000000/E35 -> 9503.2936 | F36: =F30*1000000/F35 -> 8643.0868 | G36: =G30*1000000/G35 -> 9219.1671 | H36: =H30*1000000/H35 -> 9219.1671 | I36: =I30*1000000/I35 -> 9219.1671 | J36: =J30*1000000/J35 -> 9219.1671 | ... O36: =O30*1000000/O35 -> 9398.8773
A37: CM2 per contact | B37: IRT | C37: =C32*1000000/C35 -> 8472.5701 | D37: =D32*1000000/D35 -> 8013.4708 | E37: =E32*1000000/E35 -> 6638.083 | F37: =F32*1000000/F35 -> 5368.7295 | G37: =G32*1000000/G35 -> 6026.3242 | H37: =H32*1000000/H35 -> 5831.4943 | I37: =I32*1000000/I35 -> 5922.7625 | J37: =J32*1000000/J35 -> 6280.1031 | ... O37: =O32*1000000/O35 -> 6474.3299
A38: EBITDA per contact | B38: IRT | C38: =C34*1000000/C35 -> 5443.126 | D38: =D34*1000000/D35 -> 5214.0899 | E38: =E34*1000000/E35 -> 3227.9578 | F38: =F34*1000000/F35 -> 1895.6311 | G38: =G34*1000000/G35 -> 2735.3315 | H38: =H34*1000000/H35 -> 2789.55 | I38: =I34*1000000/I35 -> 3119.0738 | J38: =J34*1000000/J35 -> 3572.2442 | ... O38: =O34*1000000/O35 -> 3748.9106
A39: EBITDA margin | B39: % | C39: =C34/C26 -> 0.32018388 | D39: =D34/D26 -> 0.30671117 | E39: =E34/E26 -> 0.18987987 | F39: =F34/F26 -> 0.11150771 | G39: =G34/G26 -> 0.16090185 | H39: =H34/H26 -> 0.16409117 | I39: =I34/I26 -> 0.18347493 | J39: =J34/J26 -> 0.21013201 | ... O39: =O34/O26 -> 0.22052415
A40: RECONCILIATION TO P&L
A41: Other / one-off fees (not allocated) | B41: mln IRT | C41: =Topline_ExC!C29 -> 0 | D41: =Topline_ExC!D29 -> -165.888 | E41: =Topline_ExC!E29 -> 0 | F41: =Topline_ExC!F29 -> 0 | G41: =Topline_ExC!G29 -> 0 | H41: =Topline_ExC!H29 -> 0 | I41: =Topline_ExC!I29 -> 0 | J41: =Topline_ExC!J29 -> 0 | ... N41: =Topline_ExC!N29 -> 0 | O41: =SUM(C41:N41) -> 585.28
A42: Sum: voice + tickets + other | B42: mln IRT | C42: =C19+C34+C41 -> 3226.1711 | D42: =D19+D34+D41 -> 3187.1184 | E42: =E19+E34+E41 -> 1101.7066 | F42: =F19+F34+F41 -> 81.838129 | G42: =G19+G34+G41 -> 830.85007 | H42: =H19+H34+H41 -> 950.75603 | I42: =I19+I34+I41 -> 1440.1246 | J42: =J19+J34+J41 -> 2028.5719 | ... N42: =N19+N34+N41 -> 3807.0277 | O42: =SUM(C42:N42) -> 26561.855
A43: EBITDA per P&L | B43: mln IRT | C43: =PnL_ExE!C35 -> 3226.1711 | D43: =PnL_ExE!D35 -> 3187.1184 | E43: =PnL_ExE!E35 -> 1101.7066 | F43: =PnL_ExE!F35 -> 81.838129 | G43: =PnL_ExE!G35 -> 830.85007 | H43: =PnL_ExE!H35 -> 950.75603 | I43: =PnL_ExE!I35 -> 1440.1246 | J43: =PnL_ExE!J35 -> 2028.5719 | ... N43: =PnL_ExE!N35 -> 3807.0277 | O43: =SUM(C43:N43) -> 26561.855
A44: Check (should be 0) | B44: mln IRT | C44: =ROUND(C42-C43,3) -> 0 | D44: =ROUND(D42-D43,3) -> 0 | E44: =ROUND(E42-E43,3) -> 0 | F44: =ROUND(F42-F43,3) -> 0 | G44: =ROUND(G42-G43,3) -> 0 | H44: =ROUND(H42-H43,3) -> 0 | I44: =ROUND(I42-I43,3) -> 0 | J44: =ROUND(J42-J43,3) -> 0 | ... N44: =ROUND(N42-N43,3) -> 0 | O44: =SUM(C44:N44) -> 0
A46: FY26 UNIT ECONOMICS SUMMARY | C46: Call | D46: Ticket | E46: Ticket vs call
A47: Billable volume | B47: # | C47: =$O$20 -> 4653400 | D47: =$O$35 -> 3210000
A48: AHT | B48: sec | C48: =Assumptions!$C$6 -> 75 | D48: =Assumptions!$C$7 -> 40
A49: Revenue per contact (price) | B49: IRT | C49: =$O$11*1000000/C47 -> 32000 | D49: =$O$26*1000000/D47 -> 17000 | E49: =IFERROR(D49/C49-1,0) -> -0.46875
A50: Direct delivery cost per contact (agent labour, OT, channel) | B50: IRT | C50: =($O$11-$O$15)*1000000/C47 -> 16706.738 | D50: =($O$26-$O$30)*1000000/D47 -> 7601.1227 | E50: =IFERROR(D50/C50-1,0) -> -0.54502652
A51: Fully-loaded cost per contact (pre-D&A) | B51: IRT | C51: =($O$11-$O$19)*1000000/C47 -> 29003.788 | D51: =($O$26-$O$34)*1000000/D47 -> 13251.089 | E51: =IFERROR(D51/C51-1,0) -> -0.54312557
A52: CM1 per contact (after direct delivery) | B52: IRT | C52: =$O$21 -> 15293.262 | D52: =$O$36 -> 9398.8773 | E52: =IFERROR(D52/C52-1,0) -> -0.38542364
A53: CM2 per contact (after semi-variable) | B53: IRT | C53: =$O$22 -> 8936.8188 | D53: =$O$37 -> 6474.3299 | E53: =IFERROR(D53/C53-1,0) -> -0.27554424
A54: EBITDA per contact (fully loaded) | B54: IRT | C54: =$O$23 -> 2996.2117 | D54: =$O$38 -> 3748.9106 | E54: =IFERROR(D54/C54-1,0) -> 0.25121688
A55: CM1 margin | B55: % | C55: =$O$15/$O$11 -> 0.47791443 | D55: =$O$30/$O$26 -> 0.55287513 | E55: =D55-C55 -> 0.074960698 | F55: pp
A56: EBITDA margin | B56: % | C56: =$O$24 -> 0.093631615 | D56: =$O$39 -> 0.22052415 | E56: =D56-C56 -> 0.12689254 | F56: pp
A57: Revenue per handle-second | B57: IRT / sec | C57: =C49/C48 -> 426.66667 | D57: =D49/D48 -> 425 | E57: =IFERROR(D57/C57-1,0) -> -0.00390625
A58: Fully-loaded cost per handle-second | B58: IRT / sec | C58: =C51/C48 -> 386.71718 | D58: =D51/D48 -> 331.27723 | E58: =IFERROR(D58/C58-1,0) -> -0.14336044
A59: Net productive hours per agent FTE | B59: hours | C59: =Capacity_ExD!$O$19 -> 96.096 | D59: =Capacity_ExD!$O$20 -> 110.88 | E59: =IFERROR(D59/C59-1,0) -> 0.15384615
A60: Contacts per agent FTE per month | B60: # | C60: =Capacity_ExD!$O$21 -> 4612.608 | D60: =Capacity_ExD!$O$22 -> 9979.2 | E60: =IFERROR(D60/C60-1,0) -> 1.1634615
A61: EBITDA per agent FTE-month | B61: mln IRT | C61: =$O$19/(Capacity_ExD!$O$29*12) -> 14.247783 | D61: =$O$34/(Capacity_ExD!$O$30*12) -> 38.568174 | E61: =IFERROR(D61/C61-1,0) -> 1.7069596
A63: Verdict | C63: =IF(D56>C56,"TICKETS are the more profitable line","CALLS are the more profitable line") -> TICKETS are the more profitable line
A64: Why (FY26): both lines are priced at ~425 IRT per handle-second, so the difference is entirely on the cost side -
A65: 1) Occupancy: tickets are worked from a backlog (90%) while voice must keep Erlang slack for 80/20 (78%) -> ~15% more paid agent time per handle-second on voice.
A66: 2) Channel cost: telephony ~590 IRT per call (incl. fixed trunks) vs ~110 IRT per ticket for messaging.
A67: 3) Risk: voice carries service-credit exposure (Feb / Nov at 4% abandonment) and peak-hour staffing; tickets can be smoothed across hours.
A68: Calls still contribute more absolute CM1 per contact (higher price), so the right commercial move is not to shed voice but to (a) re-price voice at a premium per second in 2027, and (b) shift contact mix to async channels where clients agree.

Sheet CostProgram_ExF
A1: Exhibit F - Cost improvement program (ranked by 12-month EBITDA impact, net of investment)
A2: Each initiative is quantified off the FY26 model base. 12-month window starts at launch; benefits begin after the lead time. Investment fully expensed (conservative). Standalone estimates - see overlap haircut.
A5: # | B5: Initiative | C5: Mechanism - what changes | D5: Driver | E5: Baseline | F5: Target | G5: FY26 cost base affected (mln) | H5: Run-rate annual saving (mln) | I5: Lead time (months) | J5: Months live in 12-m window | K5: One-off investment (mln) | L5: Running cost (mln / month) | M5: Net 12-m EBITDA impact (mln) | N5: Rank | O5: <= 90 days? | P5: Key risk / dependency | Q5: Owner
A6: 1 | B6: Voice AHT reduction (agent-assist & IVR pre-authentication) | C6: Knowledge base + CRM screen-pop, ID&V moved into IVR, auto call-summary to cut after-call work. Revenue is per call, so every second saved is pure margin. | D6: AHT call (sec) | E6: =Assumptions!$C$6 -> 75 | F6: 68 | G6: =-(UnitEcon!$O$12+UnitEcon!$O$13+UnitEcon!$O$16) -> 104569.97 | H6: =G6*(1-F6/E6) -> 9759.8636 | I6: 4 | J6: =MAX(0,12-I6) -> 8 | K6: 1200 | L6: 60 | M6: =H6*J6/12-K6-L6*J6 -> 4826.5757 | N6: =RANK(M6,$M$6:$M$13,0) -> 1 | O6: =IF(I6<=3,"Yes","No") -> No | P6: Must not hurt FCR / CSAT (repeat calls breach SLA); needs client IT integration for screen-pop. Gainshare risk at 2027 renewal. | Q6: Ops / IT
A7: 2 | B7: Shrinkage reduction (absence & adherence management) | C7: Real-time adherence, attendance bonus, move coaching/training into low-occupancy intervals, tighter break control. | D7: Shrinkage (%) | E7: =Assumptions!$C$11 -> 0.3 | F7: 0.27 | G7: =(Costs!$O$22+Costs!$O$23+Costs!$O$24+Costs!$O$25+Costs!$O$26+Costs!$O$36-Costs!$O$34-Costs!$O$35+Costs!$O$40+Costs!$O$45) -> 137997.52 | H7: =G7*(1-(1-E7)/(1-F7)) -> 5671.1309 | I7: 2 | J7: =MAX(0,12-I7) -> 10 | K7: 300 | L7: 40 | M7: =H7*J7/12-K7-L7*J7 -> 4025.9424 | N7: =RANK(M7,$M$6:$M$13,0) -> 2 | O7: =IF(I7<=3,"Yes","No") -> Yes | P7: Agent fatigue -> attrition; requires WFM real-time capability and TL discipline. | Q7: WFM
A8: 3 | B8: Intraday scheduling: part-time peak shifts (voice) | C8: Add 4-hour part-time shifts at lunch/dinner peaks; split shifts. Erlang check shows 80-86% occupancy achievable vs 78% planned. | D8: Voice occupancy (%) | E8: =Assumptions!$C$10 -> 0.78 | F8: 0.81 | G8: =-(UnitEcon!$O$12+UnitEcon!$O$13+UnitEcon!$O$16) -> 104569.97 | H8: =G8*(1-E8/F8) -> 3872.9617 | I8: 3 | J8: =MAX(0,12-I8) -> 9 | K8: 150 | L8: 20 | M8: =H8*J8/12-K8-L8*J8 -> 2574.7213 | N8: =RANK(M8,$M$6:$M$13,0) -> 3 | O8: =IF(I8<=3,"Yes","No") -> Yes | P8: Part-time labour availability; SL 80/20 breach risk if forecast error rises. | Q8: WFM
A9: 4 | B9: Phased seat capacity (don't pay in January for November's seats) | C9: Lease H1 seats at H1 peak + buffer; add H2 expansion (or flexible/co-working seats) from July; hybrid working for ticket agents as enabler. | D9: Seats leased in H1 | E9: =Capacity_ExD!$O$58 -> 141 | F9: =ROUNDUP(MAX(Capacity_ExD!$C$57:$H$57)*(1+Assumptions!$C$30),0) -> 97 | G9: =Costs!$O$49 -> 13536 | H9: =(E9-F9)*Assumptions!$C$56*6 -> 2112 | I9: 1 | J9: =MAX(0,12-I9) -> 11 | K9: 50 | L9: 0 | M9: =H9*J9/12-K9-L9*J9 -> 1886 | N9: =RANK(M9,$M$6:$M$13,0) -> 4 | O9: =IF(I9<=3,"Yes","No") -> Yes | P9: Landlord flexibility / expansion space availability; fit-out lead time for H2 seats. | Q9: Admin / Finance
A10: 5 | B10: Team-leader span of control 1:15 -> 1:18 | C10: Real-time dashboards + automated QA give TLs time back; restructure teams at the April pay review. | D10: Agents per TL | E10: =Assumptions!$C$13 -> 15 | F10: 18 | G10: =Costs!$O$25 -> 14030 | H10: =G10*(1-E10/F10) -> 2338.3333 | I10: 3 | J10: =MAX(0,12-I10) -> 9 | K10: 0 | L10: 0 | M10: =H10*J10/12-K10-L10*J10 -> 1753.75 | N10: =RANK(M10,$M$6:$M$13,0) -> 5 | O10: =IF(I10<=3,"Yes","No") -> Yes | P10: Coaching quality and attrition; change management with TLs. | Q10: Operations
A11: 6 | B11: Telephony & platform renegotiation | C11: Tender SIP trunks, volume-tier per-minute pricing, move licences from named to concurrent seats (1.5 agents/seat). | D11: Unit price reduction (%) | E11: =0 -> 0 | F11: 0.15 | G11: =Costs!$O$42+Costs!$O$43+Costs!$O$44+Costs!$O$45+Costs!$O$46 -> 8793.0769 | H11: =G11*F11 -> 1318.9615 | I11: 3 | J11: =MAX(0,12-I11) -> 9 | K11: 100 | L11: 0 | M11: =H11*J11/12-K11-L11*J11 -> 889.22116 | N11: =RANK(M11,$M$6:$M$13,0) -> 6 | O11: =IF(I11<=3,"Yes","No") -> Yes | P11: Switching risk / downtime; vendor lock-in clauses. | Q11: IT / Procurement
A12: 7 | B12: Flex capacity for short peaks (no permanent hires for 1-month spikes) | C12: Cover Feb / Nov spikes with overtime, cross-skilled back-office and temp agency staff instead of permanent hires that become idle in Mar / Dec. | D12: Residual idle cost (%) | E12: =1 -> 1 | F12: 0.3 | G12: =Costs!$O$23 -> 1612.1035 | H12: =G12*(1-F12/E12) -> 1128.4725 | I12: 1 | J12: =MAX(0,12-I12) -> 11 | K12: 0 | L12: 25 | M12: =H12*J12/12-K12-L12*J12 -> 759.43311 | N12: =RANK(M12,$M$6:$M$13,0) -> 7 | O12: =IF(I12<=3,"Yes","No") -> Yes | P12: Temp quality; OT fatigue; requires 3-month rolling WFM hiring plan. Target = residual idle share. | Q12: WFM / HR
A13: 8 | B13: Automated QA (speech & text analytics) | C13: AI scoring of 100% of contacts replaces 2% manual sampling; QA analysts move to calibration & coaching (1:40 -> 1:80). | D13: Agents per QA | E13: =Assumptions!$C$15 -> 40 | F13: 80 | G13: =Costs!$O$26 -> 2330.2 | H13: =G13*(1-E13/F13) -> 1165.1 | I13: 4 | J13: =MAX(0,12-I13) -> 8 | K13: 300 | L13: 30 | M13: =H13*J13/12-K13-L13*J13 -> 236.73333 | N13: =RANK(M13,$M$6:$M$13,0) -> 8 | O13: =IF(I13<=3,"Yes","No") -> No | P13: Tool accuracy in Persian ASR; client acceptance of automated scoring. | Q13: Quality
B14: Total - standalone sum | H14: =SUM(H6:H13) -> 27366.824 | K14: =SUM(K6:K13) -> 2100 | M14: =SUM(M6:M13) -> 16952.377
B15: Overlap haircut (initiatives share the same FTE pool) | L15: 0.15 | M15: =-M14*L15 -> -2542.8566
B16: Program net 12-month EBITDA impact | M16: =M14+M15 -> 14409.52
B17: FY26 EBITDA (base plan) | M17: =PnL_ExE!$O$35 -> 26561.855
B18: FY26 EBITDA margin incl. program (12-m net impact) | M18: =(M17+M16)/PnL_ExE!$O$9 -> 0.20077701
B19: Base EBITDA margin | M19: =PnL_ExE!$O$36 -> 0.13016428
B20: Initiatives deliverable within 90 days | M20: =COUNTIF(O6:O13,"Yes") -> 6
B22: Considered but not prioritised on a 12-month EBITDA lens:
B23: - Attrition reduction 4% -> 3% / month: saves ~15 hires x (recruitment + 0.5 month training) but a retention bonus large enough to move attrition costs about the same in year 1; pursue for quality/AHT, not for 12-m EBITDA.
B24: - Ticket deflection / self-service: cuts billable volume (revenue is per handled contact) - only with a gainshare clause in the 2027 contract.
B25: Commercial levers (outside cost program, for the 2027 rate card): wage-indexation clause (the April +25% step is unfunded in a fixed 2026 price), volume collar +/-10% with take-or-pay to transfer staffing risk, and SLA bonus/malus symmetry.

Sheet ZBB_Register
A1: Zero-based cost register - every FY26 cost line justified from its driver
A2: ZBB lens: what activity drives the cost, what is the minimum level that meets contract / law, and what decision we take. Links to the Cost Program (#).
A4: Cost line | B4: FY26 (mln IRT) | C4: % of revenue | D4: Cost per contact (IRT) | E4: Driver (what makes it move) | F4: ZBB category | G4: Justification - minimum level needed | H4: Decision | I4: Linked initiative | J4: Owner
A5: Agent payroll - productive | B5: =-PnL_ExE!$O$11 -> 94505.23 | C5: =B5/PnL_ExE!$O$9 -> 0.46311546 | D5: =B5*1000000/(PnL_ExE!$O$46+PnL_ExE!$O$47) -> 12018.367 | E5: Volume x AHT / net productive hours | F5: Core - volume-driven | G5: Contractual volume at 80/20 SL; sized bottom-up, not on last year's HC | H5: Optimise | I5: #1 #2 #3 | J5: =PnL_ExE!$B$11 -> Operations
A6: Agent payroll - surplus / idle | B6: =-PnL_ExE!$O$12 -> 1612.1035 | C6: =B6/PnL_ExE!$O$9 -> 0.0078999868 | D6: =B6*1000000/(PnL_ExE!$O$46+PnL_ExE!$O$47) -> 205.01355 | E6: Hiring for 1-month peaks + no-layoff policy | F6: Non-value-adding | G6: Zero is the ZBB target: idle capacity buys no revenue | H6: Eliminate | I6: #4 | J6: =PnL_ExE!$B$12 -> WFM
A7: Overtime | B7: =-PnL_ExE!$O$13 -> 2913.3155 | C7: =B7/PnL_ExE!$O$9 -> 0.014276474 | D7: =B7*1000000/(PnL_ExE!$O$46+PnL_ExE!$O$47) -> 370.49057 | E7: 3% of productive hours | F7: Core - flex | G7: Cheapest flex for spikes (no shrinkage on OT hours) | H7: Keep / use for peaks | I7: #4 | J7: =PnL_ExE!$B$13 -> WFM
A8: Team leaders | B8: =-PnL_ExE!$O$14 -> 14030 | C8: =B8/PnL_ExE!$O$9 -> 0.068752913 | D8: =B8*1000000/(PnL_ExE!$O$46+PnL_ExE!$O$47) -> 1784.2155 | E8: Span of control 1:15 | F8: Core - semi-variable | G8: Coaching + escalation; span can widen with tooling | H8: Optimise | I8: #5 | J8: =PnL_ExE!$B$14 -> Operations
A9: Quality analysts | B9: =-PnL_ExE!$O$15 -> 2330.2 | C9: =B9/PnL_ExE!$O$9 -> 0.011418962 | D9: =B9*1000000/(PnL_ExE!$O$46+PnL_ExE!$O$47) -> 296.33492 | E9: 1:40 agents, 2% manual sample | F9: Contractual / risk | G9: Client QA reporting is contractual; method can be automated | H9: Optimise | I9: #8 | J9: =PnL_ExE!$B$15 -> Quality
A10: Telephony & messaging | B10: =-PnL_ExE!$O$16 -> 3112.09 | C10: =B10/PnL_ExE!$O$9 -> 0.015250553 | D10: =B10*1000000/(PnL_ExE!$O$46+PnL_ExE!$O$47) -> 395.76901 | E10: Handled calls / tickets | F10: Core - volume-driven | G10: Unavoidable per contact; unit price negotiable | H10: Renegotiate | I10: #6 | J10: =PnL_ExE!$B$16 -> IT
A11: CC platform licences | B11: =-PnL_ExE!$O$17 -> 3678.4869 | C11: =B11/PnL_ExE!$O$9 -> 0.018026136 | D11: =B11*1000000/(PnL_ExE!$O$46+PnL_ExE!$O$47) -> 467.79853 | E11: Named agents | F11: Core - semi-variable | G11: Needed per active seat, not per named agent | H11: Renegotiate | I11: #6 | J11: =PnL_ExE!$B$17 -> IT
A12: Operations management | B12: =-PnL_ExE!$O$22 -> 5032.5 | C12: =B12/PnL_ExE!$O$9 -> 0.024661371 | D12: =B12*1000000/(PnL_ExE!$O$46+PnL_ExE!$O$47) -> 639.99033 | E12: 1 per 6 TLs | F12: Core - semi-variable | G12: Minimum 1 per shift block | H12: Keep | J12: =PnL_ExE!$B$22 -> Operations
A13: Workforce management | B13: =-PnL_ExE!$O$23 -> 2433.9 | C13: =B13/PnL_ExE!$O$9 -> 0.011927136 | D13: =B13*1000000/(PnL_ExE!$O$46+PnL_ExE!$O$47) -> 309.5226 | E13: 1 per 75 agents | F13: Value-adding | G13: Pays for itself: every 1pp occupancy = ~1% of agent cost | H13: Invest | I13: #2 #3 | J13: =PnL_ExE!$B$23 -> WFM
A14: Training team | B14: =-PnL_ExE!$O$24 -> 2452.2 | C14: =B14/PnL_ExE!$O$9 -> 0.012016814 | D14: =B14*1000000/(PnL_ExE!$O$46+PnL_ExE!$O$47) -> 311.84984 | E14: 1 per 60 agents (attrition-driven) | F14: Core - semi-variable | G14: Scales with hires, not with HC | H14: Re-base on hires | J14: =PnL_ExE!$B$24 -> Training
A15: IT / MIS support staff | B15: =-PnL_ExE!$O$25 -> 2781.6 | C15: =B15/PnL_ExE!$O$9 -> 0.013631012 | D15: =B15*1000000/(PnL_ExE!$O$46+PnL_ExE!$O$47) -> 353.74011 | E15: 1 per 75 agents | F15: Support | G15: Uptime of telephony is SLA-critical | H15: Keep | J15: =PnL_ExE!$B$25 -> IT
A16: HR, recruitment & admin staff | B16: =-PnL_ExE!$O$26 -> 1564.65 | C16: =B16/PnL_ExE!$O$9 -> 0.0076674445 | D16: =B16*1000000/(PnL_ExE!$O$46+PnL_ExE!$O$47) -> 198.97881 | E16: 1 per 75 agents | F16: Support | G16: Hiring volume ~40% of HC per year | H16: Keep | J16: =PnL_ExE!$B$26 -> HR
A17: Recruitment & new-hire training | B17: =-PnL_ExE!$O$27 -> 4663.3322 | C17: =B17/PnL_ExE!$O$9 -> 0.022852293 | D17: =B17*1000000/(PnL_ExE!$O$46+PnL_ExE!$O$47) -> 593.04273 | E17: Hires = growth + attrition | F17: Non-value-adding (partly) | G17: Growth hires are needed; attrition-replacement hires are waste | H17: Reduce | I17: #4 | J17: =PnL_ExE!$B$27 -> HR
A18: Facilities | B18: =-PnL_ExE!$O$28 -> 16197.1 | C18: =B18/PnL_ExE!$O$9 -> 0.079372617 | D18: =B18*1000000/(PnL_ExE!$O$46+PnL_ExE!$O$47) -> 2059.8087 | E18: Peak seats leased for 12 months | F18: Fixed / committed | G18: Lease sized to Nov peak sits partly empty in H1 | H18: Challenge | I18: #7 | J18: =PnL_ExE!$B$28 -> Admin
A19: IT infrastructure | B19: =-PnL_ExE!$O$29 -> 2002.5 | C19: =B19/PnL_ExE!$O$9 -> 0.009813094 | D19: =B19*1000000/(PnL_ExE!$O$46+PnL_ExE!$O$47) -> 254.66083 | E19: Fixed | F19: Fixed | G19: Security & redundancy are client requirements | H19: Renegotiate | I19: #6 | J19: =PnL_ExE!$B$29 -> IT
A20: Site leadership | B20: =-PnL_ExE!$O$30 -> 6084.75 | C20: =B20/PnL_ExE!$O$9 -> 0.02981784 | D20: =B20*1000000/(PnL_ExE!$O$46+PnL_ExE!$O$47) -> 773.8065 | E20: Fixed | F20: Mandatory | G20: Given in case | H20: Keep | J20: =PnL_ExE!$B$30 -> Site director
A21: Account management | B21: =-PnL_ExE!$O$31 -> 4172.4 | C21: =B21/PnL_ExE!$O$9 -> 0.020446519 | D21: =B21*1000000/(PnL_ExE!$O$46+PnL_ExE!$O$47) -> 530.61017 | E21: Number of clients | F21: Value-adding | G21: Protects revenue and drives quarterly re-baselining | H21: Keep | J21: =PnL_ExE!$B$31 -> Commercial
A22: Corporate overhead allocation | B22: =-PnL_ExE!$O$32 -> 6121.9224 | C22: =B22/PnL_ExE!$O$9 -> 0.03 | D22: =B22*1000000/(PnL_ExE!$O$46+PnL_ExE!$O$47) -> 778.53376 | E22: % of revenue | F22: Allocated | G22: Should be activity-based (SLA for HQ services) | H22: Challenge | J22: =PnL_ExE!$B$32 -> Finance
A23: Other G&A | B23: =-PnL_ExE!$O$33 -> 1813.9448 | C23: =B23/PnL_ExE!$O$9 -> 0.0088890939 | D23: =B23*1000000/(PnL_ExE!$O$46+PnL_ExE!$O$47) -> 230.68199 | E23: Per employee | F23: Discretionary | G23: Policy-based caps per head | H23: Cap | J23: =PnL_ExE!$B$33 -> Finance
A24: Total operating cost (pre-D&A) | B24: =SUM(B5:B23) -> 177502.23 | C24: =B24/PnL_ExE!$O$9 -> 0.86983572 | D24: =B24*1000000/(PnL_ExE!$O$46+PnL_ExE!$O$47) -> 22573.216
A25: Check vs P&L (should be 0) | B25: =ROUND(B24+PnL_ExE!$O$18+PnL_ExE!$O$34,3) -> 0

Sheet Sensitivity
A1: Sensitivity - FY26 EBITDA vs key drivers (one at a time)
A2: Values are outputs of full model re-runs with one input flexed (static snapshot; base case linked live in row 5). To re-run: change the input on Assumptions and read PnL_ExE!O EBITDA.
A4: Driver | B4: Low case | C4: High case | D4: EBITDA - low (mln) | E4: EBITDA - high (mln) | F4: Delta low vs base | G4: Delta high vs base | H4: Swing (abs) | I4: EBITDA margin low | J4: EBITDA margin high
A5: Base case FY26 EBITDA | D5: =PnL_ExE!$O$35 -> 26561.855 | E5: =PnL_ExE!$O$35 -> 26561.855 | I5: =PnL_ExE!$O$36 -> 0.13016428
A6: Realised volume vs staffed plan (base 1.00) | B6: 0.9 | C6: 1.1 | D6: 7109.1 | E6: 46014.6 | F6: =D6-$D$5 -> -19452.755 | G6: =E6-$D$5 -> 19452.745 | H6: =ABS(E6-D6) -> 38905.5 | I6: 0.0387 | J6: 0.2051
A7: AHT - call, sec (base 75) | B7: 82 | C7: 68 | D7: 16194.6 | E7: 37358.6 | F7: =D7-$D$5 -> -10367.255 | G7: =E7-$D$5 -> 10796.745 | H7: =ABS(E7-D7) -> 21164 | I7: 0.0794 | J7: 0.1831
A8: Agent gross salary, mln IRT (base 50) | B8: 55 | C8: 45 | D8: 16555.9 | E8: 36567.8 | F8: =D8-$D$5 -> -10005.955 | G8: =E8-$D$5 -> 10005.945 | H8: =ABS(E8-D8) -> 20011.9 | I8: 0.0811 | J8: 0.1792
A9: Wage inflation from April (base 25%) | B9: 0.15 | C9: 0.35 | D9: 36039.5 | E9: 17084.2 | F9: =D9-$D$5 -> 9477.6455 | G9: =E9-$D$5 -> -9477.6545 | H9: =ABS(E9-D9) -> 18955.3 | I9: 0.1766 | J9: 0.0837
A10: Price per call, IRT (base 32,000) | B10: 30400 | C10: 33600 | D10: 19359.9 | E10: 33763.8 | F10: =D10-$D$5 -> -7201.9545 | G10: =E10-$D$5 -> 7201.9455 | H10: =ABS(E10-D10) -> 14403.9 | I10: 0.0985 | J10: 0.1596
A11: Shrinkage (base 30%) | B11: 0.33 | C11: 0.27 | D11: 19685.8 | E11: 31691.5 | F11: =D11-$D$5 -> -6876.0545 | G11: =E11-$D$5 -> 5129.6455 | H11: =ABS(E11-D11) -> 12005.7 | I11: 0.0965 | J11: 0.1553
A12: Volume re-planned, staffing follows (base 1.00) | B12: 0.9 | C12: 1.1 | D12: 22271.2 | E12: 31304.1 | F12: =D12-$D$5 -> -4290.6545 | G12: =E12-$D$5 -> 4742.2455 | H12: =ABS(E12-D12) -> 9032.9 | I12: 0.1212 | J12: 0.1395
A13: Occupancy - voice (base 78%) | B13: 0.75 | C13: 0.81 | D13: 21601 | E13: 30187.4 | F13: =D13-$D$5 -> -4960.8545 | G13: =E13-$D$5 -> 3625.5455 | H13: =ABS(E13-D13) -> 8586.4 | I13: 0.1059 | J13: 0.1479
A14: Occupancy - tickets (base 90%) | B14: 0.78 | C14: 0.95 | D14: 20737.5 | E14: 28196 | F14: =D14-$D$5 -> -5824.3545 | G14: =E14-$D$5 -> 1634.1455 | H14: =ABS(E14-D14) -> 7458.5 | I14: 0.1016 | J14: 0.1382
A15: Non-payroll indexation (base 15%) | B15: 0.3 | C15: 0 | D15: 25084 | E15: 28039.7 | F15: =D15-$D$5 -> -1477.8545 | G15: =E15-$D$5 -> 1477.8455 | H15: =ABS(E15-D15) -> 2955.7 | I15: 0.1229 | J15: 0.1374
A16: Agent attrition per month (base 4%) | B16: 0.05 | C16: 0.03 | D16: 26412.9 | E16: 26679.2 | F16: =D16-$D$5 -> -148.9545 | G16: =E16-$D$5 -> 117.3455 | H16: =ABS(E16-D16) -> 266.3 | I16: 0.1294 | J16: 0.1307
A18: STRESS CASES
A19: Stress: high-inflation scenario, wages +52% from April | D19: 972.2 | F19: =D19-$D$5 -> -25589.655 | I19: 0.0048
A20: Stress: volume -10% vs plan AND wage +35% | D20: -2368.6 | F20: =D20-$D$5 -> -28930.455 | I20: -0.0129
A22: Low / high = the input value used in each re-run; EBITDA columns are static outputs (italic) of a full recalculation; deltas are live vs base.
A23: Reading: (1) volume shortfall with staffing locked to plan is the largest risk - Helix carries staffing risk, so a 10% miss removes ~70% of EBITDA;
A24: (2) labour-cost drivers (wage inflation, salary, AHT, shrinkage) dominate the rest - people are ~70% of revenue;
A25: (3) In a high-inflation labour market, +25% is optimistic: at +52% Helix is only break-even at EBITDA -> a wage-indexation clause is essential.
